Trivium/kairo/Trivium_Comp.v
module Trivium_Comp (Kin, Din, Dout, Krdy, Drdy, EncDec, RSTn, EN, CLK, BSY, Kvld, Dvld);

input  [79:0] Kin;  // Key input
input  [79:0] Din;  // Data input
// output [127:0]Dout;// Data output
output Dout;// Data output
input  Krdy;        // Key input ready
input  Drdy;        // Data input ready
input  EncDec;      // 0:Encryption 1:Decryption
input  RSTn;        // Reset (Low active)
input  EN;          // Trivium circuit enable
input  CLK;         // System clock
output BSY;         // Busy signal
output Kvld;        // Data output valid
output Dvld;        // Data output valid

wire [15:0] len, max;
wire [79:0] li_iv, li_key;
reg [15:0] count;
reg [287:0] SET;
reg t1, t2, t3;
reg BSYrg, Kvldrg, Dvldrg;
// reg [127:0]Doutrg;
reg Doutrg;

assign len = 128;
assign max = 1152 + len;
assign li_key = {Kin[7:0], Kin[15:8], Kin[23:16], Kin[31:24], Kin[39:32], Kin[47:40], Kin[55:48], Kin[63:56], Kin[71:64], Kin[79:72]};
assign li_iv  = {Din[7:0], Din[15:8], Din[23:16], Din[31:24], Din[39:32], Din[47:40], Din[55:48], Din[63:56], Din[71:64], Din[79:72]};

assign BSY  = BSYrg;
assign Kvld = Kvldrg;
assign Dvld = Dvldrg;
assign Dout = Doutrg;

always @(posedge CLK) begin
    if(!RSTn) begin
        BSYrg  <= 0;
        Kvldrg <= 0;
        Dvldrg <= 0;
        count  <= 0;
    end else if(EN) begin
        if(Dvldrg) Dvldrg <= 0;
        if(Kvldrg) Kvldrg <= 0;
        if(!EncDec) begin
            if(!BSYrg) begin
                if(Krdy) begin
                    SET    <= {3'b111, 205'b0, li_key};
                    Kvldrg <= 1;
                end else if(Drdy) begin
                    BSYrg       <= 1;
                    SET[172:93] <= li_iv;
                end
            end else begin
                if(max < count) begin
                    Dvldrg <= 1;
                    BSYrg  <= 0;
                    count  <= 0;
                end else begin
                    t1 = SET[65]  ^ SET[92];
                    t2 = SET[161] ^ SET[176];
                    t3 = SET[242] ^ SET[287];
                    // if(1152 <= count) Doutrg[max - count] <= t1 ^ t2 ^ t3;
                    if(1152 <= count) Doutrg <= t1 ^ t2 ^ t3;
                    t1 = t1 ^ (SET[90]  & SET[91] ) ^ SET[170];
                    t2 = t2 ^ (SET[174] & SET[175]) ^ SET[263];
                    t3 = t3 ^ (SET[285] & SET[286]) ^ SET[68];
                    SET   <= {SET[286:177], t2, SET[175:93], t1, SET[91:0], t3};
                    count <= count + 1;
                end
            end
        end
    end
end

endmodule

Trivium/kairo/Trivium_Test.v
// SASEBO checker でやる時は右詰めで80bit
`timescale 1ns/1ns

module Trivium_Test;
    reg  [79:0] Kin;  // Key input
    reg  [79:0] Din;  // Data input
    // wire [127:0]Dout;// Data output
    wire Dout;// Data output
    reg  Krdy;        // Key input ready
    reg  Drdy;        // Data input ready
    reg  EncDec;      // 0:Encryption 1:Decryption
    reg  RSTn;        // Reset (Low active)
    reg  EN;          // Trivium circuit enable
    reg  CLK;         // System clock
    wire BSY;         // Busy signal
    wire Kvld;        // Data output valid
    wire Dvld;        // Data output valid
    parameter times = 0.5;
    always #(times)   CLK = ~CLK;

    Trivium_Comp Trivium_Comp (Kin, Din, Dout, Krdy, Drdy, EncDec, RSTn, EN, CLK, BSY, Kvld, Dvld);

    initial begin
        // repeat(1)   @(negedge CLK);
        Krdy   = 0;
        Drdy   = 0;
        EncDec = 0;
        RSTn   = 1;
        CLK    = 0;
        EN     = 0;
        @(negedge CLK);
        RSTn <= 0;
        @(negedge CLK);
        RSTn <= 1;
        EN   <= 1;
        Krdy <= 1;
        Kin  <= 80'h00000000000000000000;
        @(posedge Kvld);
        Krdy <= 0;
        Kin  <= 80'bX;
        Drdy <= 1;
        Din  <= 80'h00000000000000000000;
        @(posedge BSY);
        Drdy <= 0;
        Din  <= 80'bX;
        @(posedge Dvld);
        repeat(10)  @(negedge CLK);
        $finish;
    end

    initial begin
        $monitor($time , "\nKEY=%h, IV=%h\nOUT=%h", Kin, Din, Dout);
        $dumpfile("Test.vcd");
        $dumpvars(0, Trivium_Test);
    end

endmodule

Trivium/kairo/Test.vcd
$date
	Tue Nov 17 11:45:51 2015
$end
$version
	Icarus Verilog
$end
$timescale
	1ns
$end
$scope module Trivium_Test $end
$var wire 1 ! BSY $end
$var wire 1 " Dout $end
$var wire 1 # Dvld $end
$var wire 1 $ Kvld $end
$var reg 1 % CLK $end
$var reg 80 & Din [79:0] $end
$var reg 1 ' Drdy $end
$var reg 1 ( EN $end
$var reg 1 ) EncDec $end
$var reg 80 * Kin [79:0] $end
$var reg 1 + Krdy $end
$var reg 1 , RSTn $end
$scope module Trivium_Comp $end
$var wire 1 ! BSY $end
$var wire 1 - CLK $end
$var wire 80 . Din [79:0] $end
$var wire 1 " Dout $end
$var wire 1 / Drdy $end
$var wire 1 # Dvld $end
$var wire 1 0 EN $end
$var wire 1 1 EncDec $end
$var wire 80 2 Kin [79:0] $end
$var wire 1 3 Krdy $end
$var wire 1 $ Kvld $end
$var wire 1 4 RSTn $end
$var wire 16 5 len [15:0] $end
$var wire 80 6 li_iv [79:0] $end
$var wire 80 7 li_key [79:0] $end
$var wire 16 8 max [15:0] $end
$var reg 1 9 BSYrg $end
$var reg 1 : Doutrg $end
$var reg 1 ; Dvldrg $end
$var reg 1 < Kvldrg $end
$var reg 288 = SET [287:0] $end
$var reg 16 > count [15:0] $end
$var reg 1 ? t1 $end
$var reg 1 @ t2 $end
$var reg 1 A t3 $end
$upscope $end
$upscope $end
$enddefinitions $end
#0
$dumpvars
xA
x@
x?
bx >
bx =
x<
x;
x:
x9
b10100000000 8
bx 7
bx 6
b10000000 5
14
03
bx 2
01
00
0/
bx .
0-
1,
0+
bx *
0)
0(
0'
bx &
0%
x$
x#
x"
x!
$end
#1
1%
1-
#2
0,
04
0%
0-
#3
b0 >
0;
0#
0<
0$
09
0!
1%
1-
#4
b0 7
b0 *
b0 2
1+
13
1(
10
1,
14
0%
0-
#5
b0 6
bx 7
b0 &
b0 .
1'
1/
bx *
bx 2
0+
03
1<
1$
b111000000000000000000000000000000000000000000000000000000000000000000000000000000000000000000000000000000000000000000000000000000000000000000000000000000000000000000000000000000000000000000000000000000000000000000000000000000000000000000000000000000000000000000000000000000000000000000000 =
1%
1-
#6
0%
0-
#7
bx 6
bx &
bx .
0'
0/
b111000000000000000000000000000000000000000000000000000000000000000000000000000000000000000000000000000000000000000000000000000000000000000000000000000000000000000000000000000000000000000000000000000000000000000000000000000000000000000000000000000000000000000000000000000000000000000000000 =
19
1!
0<
0$
1%
1-
#8
0%
0-
#9
b1 >
b110000000000000000000000000000000000000000000000000000000000000000000000000000000000000000000000000000000000000000000000000000000000000000000000000000000000000000000000000000000000000000000000000000000000000000000000000000000000000000000000000000000000000000000000000000000000000000000000 =
0A
0@
0?
1%
1-
#10
0%
0-
#11
b10 >
b100000000000000000000000000000000000000000000000000000000000000000000000000000000000000000000000000000000000000000000000000000000000000000000000000000000000000000000000000000000000000000000000000000000000000000000000000000000000000000000000000000000000000000000000000000000000000000000001 =
1A
1%
1-
#12
0%
0-
#13
b11 >
b11 =
1%
1-
#14
0%
0-
#15
b100 >
b110 =
0A
1%
1-
#16
0%
0-
#17
b101 >
b1100 =
1%
1-
#18
0%
0-
#19
b110 >
b11000 =
1%
1-
#20
0%
0-
#21
b111 >
b110000 =
1%
1-
#22
0%
0-
#23
b1000 >
b1100000 =
1%
1-
#24
0%
0-
#25
b1001 >
b11000000 =
1%
1-
#26
0%
0-
#27
b1010 >
b110000000 =
1%
1-
#28
0%
0-
#29
b1011 >
b1100000000 =
1%
1-
#30
0%
0-
#31
b1100 >
b11000000000 =
1%
1-
#32
0%
0-
#33
b1101 >
b110000000000 =
1%
1-
#34
0%
0-
#35
b1110 >
b1100000000000 =
1%
1-
#36
0%
0-
#37
b1111 >
b11000000000000 =
1%
1-
#38
0%
0-
#39
b10000 >
b110000000000000 =
1%
1-
#40
0%
0-
#41
b10001 >
b1100000000000000 =
1%
1-
#42
0%
0-
#43
b10010 >
b11000000000000000 =
1%
1-
#44
0%
0-
#45
b10011 >
b110000000000000000 =
1%
1-
#46
0%
0-
#47
b10100 >
b1100000000000000000 =
1%
1-
#48
0%
0-
#49
b10101 >
b11000000000000000000 =
1%
1-
#50
0%
0-
#51
b10110 >
b110000000000000000000 =
1%
1-
#52
0%
0-
#53
b10111 >
b1100000000000000000000 =
1%
1-
#54
0%
0-
#55
b11000 >
b11000000000000000000000 =
1%
1-
#56
0%
0-
#57
b11001 >
b110000000000000000000000 =
1%
1-
#58
0%
0-
#59
b11010 >
b1100000000000000000000000 =
1%
1-
#60
0%
0-
#61
b11011 >
b11000000000000000000000000 =
1%
1-
#62
0%
0-
#63
b11100 >
b110000000000000000000000000 =
1%
1-
#64
0%
0-
#65
b11101 >
b1100000000000000000000000000 =
1%
1-
#66
0%
0-
#67
b11110 >
b11000000000000000000000000000 =
1%
1-
#68
0%
0-
#69
b11111 >
b110000000000000000000000000000 =
1%
1-
#70
0%
0-
#71
b100000 >
b1100000000000000000000000000000 =
1%
1-
#72
0%
0-
#73
b100001 >
b11000000000000000000000000000000 =
1%
1-
#74
0%
0-
#75
b100010 >
b110000000000000000000000000000000 =
1%
1-
#76
0%
0-
#77
b100011 >
b1100000000000000000000000000000000 =
1%
1-
#78
0%
0-
#79
b100100 >
b11000000000000000000000000000000000 =
1%
1-
#80
0%
0-
#81
b100101 >
b110000000000000000000000000000000000 =
1%
1-
#82
0%
0-
#83
b100110 >
b1100000000000000000000000000000000000 =
1%
1-
#84
0%
0-
#85
b100111 >
b11000000000000000000000000000000000000 =
1%
1-
#86
0%
0-
#87
b101000 >
b110000000000000000000000000000000000000 =
1%
1-
#88
0%
0-
#89
b101001 >
b1100000000000000000000000000000000000000 =
1%
1-
#90
0%
0-
#91
b101010 >
b11000000000000000000000000000000000000000 =
1%
1-
#92
0%
0-
#93
b101011 >
b110000000000000000000000000000000000000000 =
1%
1-
#94
0%
0-
#95
b101100 >
b1100000000000000000000000000000000000000000 =
1%
1-
#96
0%
0-
#97
b101101 >
b11000000000000000000000000000000000000000000 =
1%
1-
#98
0%
0-
#99
b101110 >
b110000000000000000000000000000000000000000000 =
1%
1-
#100
0%
0-
#101
b101111 >
b1100000000000000000000000000000000000000000000 =
1%
1-
#102
0%
0-
#103
b110000 >
b11000000000000000000000000000000000000000000000 =
1%
1-
#104
0%
0-
#105
b110001 >
b110000000000000000000000000000000000000000000000 =
1%
1-
#106
0%
0-
#107
b110010 >
b1100000000000000000000000000000000000000000000000 =
1%
1-
#108
0%
0-
#109
b110011 >
b11000000000000000000000000000000000000000000000000 =
1%
1-
#110
0%
0-
#111
b110100 >
b110000000000000000000000000000000000000000000000000 =
1%
1-
#112
0%
0-
#113
b110101 >
b1100000000000000000000000000000000000000000000000000 =
1%
1-
#114
0%
0-
#115
b110110 >
b11000000000000000000000000000000000000000000000000000 =
1%
1-
#116
0%
0-
#117
b110111 >
b110000000000000000000000000000000000000000000000000000 =
1%
1-
#118
0%
0-
#119
b111000 >
b1100000000000000000000000000000000000000000000000000000 =
1%
1-
#120
0%
0-
#121
b111001 >
b11000000000000000000000000000000000000000000000000000000 =
1%
1-
#122
0%
0-
#123
b111010 >
b110000000000000000000000000000000000000000000000000000000 =
1%
1-
#124
0%
0-
#125
b111011 >
b1100000000000000000000000000000000000000000000000000000000 =
1%
1-
#126
0%
0-
#127
b111100 >
b11000000000000000000000000000000000000000000000000000000000 =
1%
1-
#128
0%
0-
#129
b111101 >
b110000000000000000000000000000000000000000000000000000000000 =
1%
1-
#130
0%
0-
#131
b111110 >
b1100000000000000000000000000000000000000000000000000000000000 =
1%
1-
#132
0%
0-
#133
b111111 >
b11000000000000000000000000000000000000000000000000000000000000 =
1%
1-
#134
0%
0-
#135
b1000000 >
b110000000000000000000000000000000000000000000000000000000000000 =
1%
1-
#136
0%
0-
#137
b1000001 >
b1100000000000000000000000000000000000000000000000000000000000000 =
1%
1-
#138
0%
0-
#139
b1000010 >
b11000000000000000000000000000000000000000000000000000000000000000 =
1%
1-
#140
0%
0-
#141
b1000011 >
b110000000000000000000000000000000000000000000000000000000000000000 =
1%
1-
#142
0%
0-
#143
b1000100 >
b1000000000000000000000000001100000000000000000000000000000000000000000000000000000000000000000 =
1?
1%
1-
#144
0%
0-
#145
b1000101 >
b11000000000000000000000000011000000000000000000000000000000000000000000000000000000000000000000 =
1%
1-
#146
0%
0-
#147
b1000110 >
b110000000000000000000000000110000000000000000000000000000000000000000000000000000000000000000000 =
0?
1%
1-
#148
0%
0-
#149
b1000111 >
b1100000000000000000000000001100000000000000000000000000000000000000000000000000000000000000000001 =
1A
1%
1-
#150
0%
0-
#151
b1001000 >
b11000000000000000000000000011000000000000000000000000000000000000000000000000000000000000000000011 =
1A
1%
1-
#152
0%
0-
#153
b1001001 >
b110000000000000000000000000110000000000000000000000000000000000000000000000000000000000000000000110 =
0A
1%
1-
#154
0%
0-
#155
b1001010 >
b1100000000000000000000000001100000000000000000000000000000000000000000000000000000000000000000001100 =
1%
1-
#156
0%
0-
#157
b1001011 >
b11000000000000000000000000011000000000000000000000000000000000000000000000000000000000000000000011000 =
1%
1-
#158
0%
0-
#159
b1001100 >
b110000000000000000000000000110000000000000000000000000000000000000000000000000000000000000000000110000 =
1%
1-
#160
0%
0-
#161
b1001101 >
b1100000000000000000000000001100000000000000000000000000000000000000000000000000000000000000000001100000 =
1%
1-
#162
0%
0-
#163
b1001110 >
b11000000000000000000000000011000000000000000000000000000000000000000000000000000000000000000000011000000 =
1%
1-
#164
0%
0-
#165
b1001111 >
b110000000000000000000000000110000000000000000000000000000000000000000000000000000000000000000000110000000 =
1%
1-
#166
0%
0-
#167
b1010000 >
b1100000000000000000000000001100000000000000000000000000000000000000000000000000000000000000000001100000000 =
1%
1-
#168
0%
0-
#169
b1010001 >
b11000000000000000000000000011000000000000000000000000000000000000000000000000000000000000000000011000000000 =
1%
1-
#170
0%
0-
#171
b1010010 >
b110000000000000000000000000110000000000000000000000000000000000000000000000000000000000000000000110000000000 =
1%
1-
#172
0%
0-
#173
b1010011 >
b1100000000000000000000000001100000000000000000000000000000000000000000000000000000000000000000001100000000000 =
1%
1-
#174
0%
0-
#175
b1010100 >
b11000000000000000000000000011000000000000000000000000000000000000000000000000000000000000000000011000000000000 =
1%
1-
#176
0%
0-
#177
b1010101 >
b110000000000000000000000000110000000000000000000000000000000000000000000000000000000000000000000110000000000000 =
1%
1-
#178
0%
0-
#179
b1010110 >
b1100000000000000000000000001100000000000000000000000000000000000000000000000000000000000000000001100000000000000 =
1%
1-
#180
0%
0-
#181
b1010111 >
b11000000000000000000000000011000000000000000000000000000000000000000000000000000000000000000000011000000000000000 =
1%
1-
#182
0%
0-
#183
b1011000 >
b110000000000000000000000000110000000000000000000000000000000000000000000000000000000000000000000110000000000000000 =
1%
1-
#184
0%
0-
#185
b1011001 >
b1100000000000000000000000001100000000000000000000000000000000000000000000000000000000000000000001100000000000000000 =
1%
1-
#186
0%
0-
#187
b1011010 >
b11000000000000000000000000011000000000000000000000000000000000000000000000000000000000000000000011000000000000000000 =
1%
1-
#188
0%
0-
#189
b1011011 >
b110000000000000000000000000110000000000000000000000000000000000000000000000000000000000000000000110000000000000000000 =
1%
1-
#190
0%
0-
#191
b1011100 >
b1100000000000000000000000001100000000000000000000000000000000000000000000000000000000000000000001100000000000000000000 =
1%
1-
#192
0%
0-
#193
b1011101 >
b11000000000000000000000000011000000000000000000000000000000000000000000000000000000000000000000011000000000000000000000 =
1%
1-
#194
0%
0-
#195
b1011110 >
b110000000000000000000000001110000000000000000000000000000000000000000000000000000000000000000000110000000000000000000000 =
1?
1%
1-
#196
0%
0-
#197
b1011111 >
b1100000000000000000000000011100000000000000000000000000000000000000000000000000000000000000000001100000000000000000000000 =
1%
1-
#198
0%
0-
#199
b1100000 >
b11000000000000000000000000111000000000000000000000000000000000000000000000000000000000000000000011000000000000000000000000 =
1%
1-
#200
0%
0-
#201
b1100001 >
b110000000000000000000000001110000000000000000000000000000000000000000000000000000000000000000000110000000000000000000000000 =
0?
1%
1-
#202
0%
0-
#203
b1100010 >
b1100000000000000000000000011100000000000000000000000000000000000000000000000000000000000000000001100000000000000000000000000 =
1%
1-
#204
0%
0-
#205
b1100011 >
b11000000000000000000000000111000000000000000000000000000000000000000000000000000000000000000000011000000000000000000000000000 =
1%
1-
#206
0%
0-
#207
b1100100 >
b110000000000000000000000001110000000000000000000000000000000000000000000000000000000000000000000110000000000000000000000000000 =
1%
1-
#208
0%
0-
#209
b1100101 >
b1100000000000000000000000011100000000000000000000000000000000000000000000000000000000000000000001100000000000000000000000000000 =
1%
1-
#210
0%
0-
#211
b1100110 >
b11000000000000000000000000111000000000000000000000000000000000000000000000000000000000000000000011000000000000000000000000000000 =
1%
1-
#212
0%
0-
#213
b1100111 >
b110000000000000000000000001110000000000000000000000000000000000000000000000000000000000000000000110000000000000000000000000000000 =
1%
1-
#214
0%
0-
#215
b1101000 >
b1100000000000000000000000011100000000000000000000000000000000000000000000000000000000000000000001100000000000000000000000000000000 =
1%
1-
#216
0%
0-
#217
b1101001 >
b11000000000000000000000000111000000000000000000000000000000000000000000000000000000000000000000011000000000000000000000000000000000 =
1%
1-
#218
0%
0-
#219
b1101010 >
b110000000000000000000000001110000000000000000000000000000000000000000000000000000000000000000000110000000000000000000000000000000000 =
1%
1-
#220
0%
0-
#221
b1101011 >
b1100000000000000000000000011100000000000000000000000000000000000000000000000000000000000000000001100000000000000000000000000000000000 =
1%
1-
#222
0%
0-
#223
b1101100 >
b11000000000000000000000000111000000000000000000000000000000000000000000000000000000000000000000011000000000000000000000000000000000000 =
1%
1-
#224
0%
0-
#225
b1101101 >
b110000000000000000000000001110000000000000000000000000000000000000000000000000000000000000000000110000000000000000000000000000000000000 =
1%
1-
#226
0%
0-
#227
b1101110 >
b1100000000000000000000000011100000000000000000000000000000000000000000000000000000000000000000001100000000000000000000000000000000000000 =
1%
1-
#228
0%
0-
#229
b1101111 >
b11000000000000000000000000111000000000000000000000000000000000000000000000000000000000000000000011000000000000000000000000000000000000000 =
1%
1-
#230
0%
0-
#231
b1110000 >
b110000000000000000000000001110000000000000000000000000000000000000000000000000000000000000000000110000000000000000000000000000000000000000 =
1%
1-
#232
0%
0-
#233
b1110001 >
b1100000000000000000000000011100000000000000000000000000000000000000000000000000000000000000000001100000000000000000000000000000000000000000 =
1%
1-
#234
0%
0-
#235
b1110010 >
b11000000000000000000000000111000000000000000000000000000000000000000000000000000000000000000000011000000000000000000000000000000000000000000 =
1%
1-
#236
0%
0-
#237
b1110011 >
b110000000000000000000000001110000000000000000000000000000000000000000000000000000000000000000000110000000000000000000000000000000000000000000 =
1%
1-
#238
0%
0-
#239
b1110100 >
b1100000000000000000000000011100000000000000000000000000000000000000000000000000000000000000000001100000000000000000000000000000000000000000000 =
1%
1-
#240
0%
0-
#241
b1110101 >
b11000000000000000000000000111000000000000000000000000000000000000000000000000000000000000000000011000000000000000000000000000000000000000000000 =
1%
1-
#242
0%
0-
#243
b1110110 >
b110000000000000000000000001110000000000000000000000000000000000000000000000000000000000000000000110000000000000000000000000000000000000000000000 =
1%
1-
#244
0%
0-
#245
b1110111 >
b1100000000000000000000000011100000000000000000000000000000000000000000000000000000000000000000001100000000000000000000000000000000000000000000000 =
1%
1-
#246
0%
0-
#247
b1111000 >
b11000000000000000000000000111000000000000000000000000000000000000000000000000000000000000000000011000000000000000000000000000000000000000000000000 =
1%
1-
#248
0%
0-
#249
b1111001 >
b110000000000000000000000001110000000000000000000000000000000000000000000000000000000000000000000110000000000000000000000000000000000000000000000000 =
1%
1-
#250
0%
0-
#251
b1111010 >
b1100000000000000000000000011100000000000000000000000000000000000000000000000000000000000000000001100000000000000000000000000000000000000000000000000 =
1%
1-
#252
0%
0-
#253
b1111011 >
b11000000000000000000000000111000000000000000000000000000000000000000000000000000000000000000000011000000000000000000000000000000000000000000000000000 =
1%
1-
#254
0%
0-
#255
b1111100 >
b110000000000000000000000001110000000000000000000000000000000000000000000000000000000000000000000110000000000000000000000000000000000000000000000000000 =
1%
1-
#256
0%
0-
#257
b1111101 >
b1100000000000000000000000011100000000000000000000000000000000000000000000000000000000000000000001100000000000000000000000000000000000000000000000000000 =
1%
1-
#258
0%
0-
#259
b1111110 >
b11000000000000000000000000111000000000000000000000000000000000000000000000000000000000000000000011000000000000000000000000000000000000000000000000000000 =
1%
1-
#260
0%
0-
#261
b1111111 >
b110000000000000000000000001110000000000000000000000000000000000000000000000000000000000000000000110000000000000000000000000000000000000000000000000000000 =
1%
1-
#262
0%
0-
#263
b10000000 >
b1100000000000000000000000011100000000000000000000000000000000000000000000000000000000000000000001100000000000000000000000000000000000000000000000000000000 =
1%
1-
#264
0%
0-
#265
b10000001 >
b11000000000000000000000000111000000000000000000000000000000000000000000000000000000000000000000011000000000000000000000000000000000000000000000000000000000 =
1%
1-
#266
0%
0-
#267
b10000010 >
b110000000000000000000000001110000000000000000000000000000000000000000000000000000000000000000000110000000000000000000000000000000000000000000000000000000000 =
1%
1-
#268
0%
0-
#269
b10000011 >
b1100000000000000000000000011100000000000000000000000000000000000000000000000000000000000000000001100000000000000000000000000000000000000000000000000000000000 =
1%
1-
#270
0%
0-
#271
b10000100 >
b11000000000000000000000000111000000000000000000000000000000000000000000000000000000000000000000011000000000000000000000000000000000000000000000000000000000000 =
1%
1-
#272
0%
0-
#273
b10000101 >
b110000000000000000000000001110000000000000000000000000000000000000000000000000000000000000000000110000000000000000000000000000000000000000000000000000000000000 =
1%
1-
#274
0%
0-
#275
b10000110 >
b1100000000000000000000000011100000000000000000000000000000000000000000000000000000000000000000001100000000000000000000000000000000000000000000000000000000000000 =
1%
1-
#276
0%
0-
#277
b10000111 >
b11000000000000000000000000111000000000000000000000000000000000000000000000000000000000000000000011000000000000000000000000000000000000000000000000000000000000000 =
1%
1-
#278
0%
0-
#279
b10001000 >
b110000000000000000000000001110000000000000000000000000000000000000000000000000000000000000000000110000000000000000000000000000000000000000000000000000000000000000 =
1%
1-
#280
0%
0-
#281
b10001001 >
b1000000000000001100000000000000000000000011100000000000000000000000000000000000000001000000000000000000000000001100000000000000000000000000000000000000000000000000000000000000000 =
1@
1?
1%
1-
#282
0%
0-
#283
b10001010 >
b11000000000000011000000000000000000000000111000000000000000000000000000000000000000011000000000000000000000000011000000000000000000000000000000000000000000000000000000000000000000 =
1%
1-
#284
0%
0-
#285
b10001011 >
b110000000000000110000000000000000000000001110000000000000000000000000000000000000000110000000000000000000000000110000000000000000000000000000000000000000000000000000000000000000000 =
0@
0?
1%
1-
#286
0%
0-
#287
b10001100 >
b1100000000000001100000000000000000000000011100000000000000000000000000000000000000001100000000000000000000000001100000000000000000000000000000000000000000000000000000000000000000001 =
1A
1%
1-
#288
0%
0-
#289
b10001101 >
b11000000000000011000000000000000000000000111000000000000000000000000000000000000000011000000000000000000000000011000000000000000000000000000000000000000000000000000000000000000000011 =
1A
1%
1-
#290
0%
0-
#291
b10001110 >
b110000000000000110000000000000000000000001110000000000000000000000000000000000000000110000000000000000000000000110000000000000000000000000000000000000000000000000000000000000000000110 =
0A
1%
1-
#292
0%
0-
#293
b10001111 >
b1100000000000001100000000000000000000000011100000000000000000000000000000000000000001100000000000000000000000001100000000000000000000000000000000000000000000000000000000000000000001100 =
1%
1-
#294
0%
0-
#295
b10010000 >
b11000000000000011000000000000000000000000111000000000000000000000000000000000000000011000000000000000000000000011000000000000000000000000000000000000000000000000000000000000000000011000 =
1%
1-
#296
0%
0-
#297
b10010001 >
b110000000000000110000000000000000000000001110000000000000000000000000000000000000000110000000000000000000000000110000000000000000000000000000000000000000000000000000000000000000000110000 =
1%
1-
#298
0%
0-
#299
b10010010 >
b1100000000000001100000000000000000000000011100000000000000000000000000000000000000001100000001000000000000000001100000000000000000000000000000000000000000000000000000000000000000001100000 =
1?
1%
1-
#300
0%
0-
#301
b10010011 >
b11000000000000011000000000000000000000000111000000000000000000000000000000000000000011000000011000000000000000011000000000000000000000000000000000000000000000000000000000000000000011000000 =
1?
1%
1-
#302
0%
0-
#303
b10010100 >
b110000000000000110000000000000000000000001110000000000000000000000000000000000000000110000000110000000000000000110000000000000000000000000000000000000000000000000000000000000000000110000000 =
0?
1%
1-
#304
0%
0-
#305
b10010101 >
b1100000000000001100000000000000000000000011100000000000000000000000000000000000000001100000001100000000000000001100000000000000000000000000000000000000000000000000000000000000000001100000000 =
1%
1-
#306
0%
0-
#307
b10010110 >
b11000000000000011000000000000000000000000111000000000000000000000000000000000000000011000000011000000000000000011000000000000000000000000000000000000000000000000000000000000000000011000000000 =
1%
1-
#308
0%
0-
#309
b10010111 >
b110000000000001110000000000000000000000001110000000000000000000000000000000000000000110000000110000000000000000110000000000000000000000000000000000000000000000000000000000000000000110000000000 =
1@
1%
1-
#310
0%
0-
#311
b10011000 >
b1100000000000011100000000000000000000000011100000000000000000000000000000000000000001100000001100000000000000001100000000000000000000000000000000000000000000000000000000000000000001100000000000 =
1%
1-
#312
0%
0-
#313
b10011001 >
b11000000000000111000000000000000000000000111000000000000000000000000000000000000000011000000011000000000000000011000000000000000000000000000000000000000000000000000000000000000000011000000000000 =
1%
1-
#314
0%
0-
#315
b10011010 >
b110000000000001110000000000000000000000001110000000000000000000000000000000000000000110000000110000000000000000110000000000000000000000000000000000000000000000000000000000000000000110000000000000 =
0@
1%
1-
#316
0%
0-
#317
b10011011 >
b1100000000000011100000000000000000000000011100000000000000000000000000000000000000001100000001100000000000000001100000000000000000000000000000000000000000000000000000000000000000001100000000000000 =
1%
1-
#318
0%
0-
#319
b10011100 >
b11000000000000111000000000000000000000000111000000000000000000000000000000000000000011000000011000000000000000011000000000000000000000000000000000000000000000000000000000000000000011000000000000000 =
1%
1-
#320
0%
0-
#321
b10011101 >
b110000000000001110000000000000000000000001110000000000000000000000000000000000000000110000000110000000000000000110000000000000000000000000000000000000000000000000000000000000000000110000000000000000 =
1%
1-
#322
0%
0-
#323
b10011110 >
b1100000000000011100000000000000000000000011100000000000000000000000000000000000000001100000001100000000000000001100000000000000000000000000000000000000000000000000000000000000000001100000000000000000 =
1%
1-
#324
0%
0-
#325
b10011111 >
b11000000000000111000000000000000000000000111000000000000000000000000000000000000000011000000011000000000000000011000000000000000000000000000000000000000000000000000000000000000000011000000000000000000 =
1%
1-
#326
0%
0-
#327
b10100000 >
b110000000000001110000000000000000000000001110000000000000000000000000000000000000000110000000110000000000000000110000000000000000000000000000000000000000000000000000000000000000000110000000000000000000 =
1%
1-
#328
0%
0-
#329
b10100001 >
b1100000000000011100000000000000000000000011100000000000000000000000000000000000000001100000001100000000000000001100000000000000000000000000000000000000000000000000000000000000000001100000000000000000000 =
1%
1-
#330
0%
0-
#331
b10100010 >
b11000000000000111000000000000000000000000111000000000000000000000000000000000000000011000000011000000000000000011000000000000000000000000000000000000000000000000000000000000000000011000000000000000000000 =
1%
1-
#332
0%
0-
#333
b10100011 >
b110000000000001110000000001000000000000001110000000000000000000000000000000000000000110000000110000000000000001110000000000000000000000000000000000000000000000000000000000000000000110000000000000000000000 =
1?
1@
1%
1-
#334
0%
0-
#335
b10100100 >
b1100000000000011100000000011000000000000011100000000000000000000000000000000000000001100000001100000000000000011100000000000000000000000000000000000000000000000000000000000000000001100000000000000000000000 =
1%
1-
#336
0%
0-
#337
b10100101 >
b11000000000000111000000000111000000000000111000000000000000000000000000000000000000011000000011000000000000000111000000000000000000000000000000000000000000000000000000000000000000011000000000000000000000000 =
1%
1-
#338
0%
0-
#339
b10100110 >
b110000000000001110000000001110000000000001110000000000000000000000000000000000000000110000000110000000000000001110000000000000000000000000000000000000000000000000000000000000000000110000000000000000000000000 =
0@
0?
1%
1-
#340
0%
0-
#341
b10100111 >
b1100000000000011100000000011100000000000011100000000000000000000000000000000000000001100000001100000000000000011100000000000000000000000000000000000000000000000000000000000000000001100000000000000000000000000 =
1%
1-
#342
0%
0-
#343
b10101000 >
b11000000000000111000000000111000000000000111000000000000000000000000000000000000000011000000011000000000000000111000000000000000000000000000000000000000000000000000000000000000000011000000000000000000000000000 =
1%
1-
#344
0%
0-
#345
b10101001 >
b110000000000001110000000001110000000000001110000000000000000000000000000000000000000110000000110000000000000001110000000000000000000000000000000000000000000000000000000000000000000110000000000000000000000000000 =
1%
1-
#346
0%
0-
#347
b10101010 >
b1100000000000011100000000011100000000000011100000000000000000000000000000000000000001100000001100000000000000011100000000000000000000000000000000000000000000000000000000000000000001100000000000000000000000000000 =
1%
1-
#348
0%
0-
#349
b10101011 >
b11000000000000111000000000111000000000000111000000000000000000000000000000000000000011000000011000000000000000111000000000000000000000000000000000000000000000000000000000000000000011000000000000000000000000000000 =
1%
1-
#350
0%
0-
#351
b10101100 >
b110000000000001110000000001110000000000001110000000000000000000000000000000000000000110000000110000000000000001110000001000000000000000000000000000000000000000000000000000000000000110000000000000000000000000000000 =
1?
1%
1-
#352
0%
0-
#353
b10101101 >
b1100000000000011100000000011100000000000011100000000000000000000000000000000000000001100000001100000000000000011100000011000000000000000000000000000000000000000000000000000000000001100000000000000000000000000000000 =
1?
1%
1-
#354
0%
0-
#355
b10101110 >
b11000000000000111000000000111000000000000111000000000000000000000000000000000000000011000000011000000000000000111000000111000000000000000000000000000000000000000000000000000000000011000000000000000000000000000000000 =
1?
1%
1-
#356
0%
0-
#357
b10101111 >
b110000000000001110000000001110000000000001110000000000000000000000000000000000000000110000000110000000000000001110000001110000000000000000000000000000000000000000000000000000000000110000000000000000000000000000000000 =
0?
1%
1-
#358
0%
0-
#359
b10110000 >
b1100000000000011100000000011100000000000011100000000000000000000000000000000000000001100000001100000000000000011100000011100000000000000000000000000000000000000000000000000000000001100000000000000000000000000000000000 =
1%
1-
