Trivium/kairo/Trivium_Comp.v
module Trivium_Comp (Kin, Din, Dout, Krdy, Drdy, EncDec, RSTn, EN, CLK, BSY, Kvld, Dvld);

input  [79:0] Kin;  // Key input
input  [79:0] Din;  // Data input
output [127:0]Dout;// Data output
input  Krdy;        // Key input ready
input  Drdy;        // Data input ready
input  EncDec;      // 0:Encryption 1:Decryption
input  RSTn;        // Reset (Low active)
input  EN;          // Trivium circuit enable
input  CLK;         // System clock
output BSY;         // Busy signal
output Kvld;        // Data output valid
output Dvld;        // Data output valid

wire [15:0] len, max;
wire [79:0] li_iv, li_key;
reg [15:0] count;
reg [287:0] SET;
reg t1, t2, t3;
reg BSYrg, Kvldrg, Dvldrg;
reg [127:0]Doutrg;

assign len = 128;
assign max = 1152 + len;
assign li_key = {Kin[7:0], Kin[15:8], Kin[23:16], Kin[31:24], Kin[39:32], Kin[47:40], Kin[55:48], Kin[63:56], Kin[71:64], Kin[79:72]};
assign li_iv  = {Din[7:0], Din[15:8], Din[23:16], Din[31:24], Din[39:32], Din[47:40], Din[55:48], Din[63:56], Din[71:64], Din[79:72]};

assign BSY  = BSYrg;
assign Kvld = Kvldrg;
assign Dvld = Dvldrg;
assign Dout = Doutrg;

always @(posedge CLK) begin
    if(!RSTn) begin
        BSYrg  <= 0;
        Kvldrg <= 0;
        Dvldrg <= 0;
        count  <= 0;
    end else if(EN) begin
        if(Dvldrg) Dvldrg <= 0;
        if(Kvldrg) Kvldrg <= 0;
        if(!EncDec) begin
            if(!BSYrg) begin
                if(Krdy) begin
                    SET    <= {3'b111, 205'b0, li_key};
                    Kvldrg <= 1;
                end else if(Drdy) begin
                    BSYrg       <= 1;
                    SET[172:93] <= li_iv;
                end
            end else begin
                if(max < count) begin
                    Dvldrg <= 1;
                    BSYrg  <= 0;
                end else begin
                    t1 = SET[65]  ^ SET[92];
                    t2 = SET[161] ^ SET[176];
                    t3 = SET[242] ^ SET[287];
                    if(1152 <= count) Doutrg[max - count] <= t1 ^ t2 ^ t3;
                    t1 = t1 ^ (SET[90]  & SET[91] ) ^ SET[170];
                    t2 = t2 ^ (SET[174] & SET[175]) ^ SET[263];
                    t3 = t3 ^ (SET[285] & SET[286]) ^ SET[68];
                    SET   <= {SET[286:177], t2, SET[175:93], t1, SET[91:0], t3};
                    count <= count + 1;
                end
            end
        end
    end
end

endmodule

Trivium/kairo/Trivium_Test.v
// SASEBO checker でやる時は右詰めで80bit
`timescale 1ns/1ns

module Trivium_Test;
    reg  [79:0] Kin;  // Key input
    reg  [79:0] Din;  // Data input
    wire [127:0]Dout;// Data output
    reg  Krdy;        // Key input ready
    reg  Drdy;        // Data input ready
    reg  EncDec;      // 0:Encryption 1:Decryption
    reg  RSTn;        // Reset (Low active)
    reg  EN;          // Trivium circuit enable
    reg  CLK;         // System clock
    wire BSY;         // Busy signal
    wire Kvld;        // Data output valid
    wire Dvld;        // Data output valid
    parameter times = 0.5;
    always #(times)   CLK = ~CLK;

    Trivium_Comp Trivium_Comp (Kin, Din, Dout, Krdy, Drdy, EncDec, RSTn, EN, CLK, BSY, Kvld, Dvld);

    initial begin
        // repeat(1)   @(negedge CLK);
        Krdy   = 0;
        Drdy   = 0;
        EncDec = 0;
        RSTn   = 1;
        CLK    = 0;
        EN     = 0;
        @(negedge CLK);
        RSTn <= 0;
        @(negedge CLK);
        RSTn <= 1;
        EN   <= 1;
        Krdy <= 1;
        Kin  <= 80'h06070809000000000000;
        @(posedge Kvld);
        Krdy <= 0;
        Kin  <= 80'bX;
        Drdy <= 1;
        Din  <= 80'hf47c637c9a443bbd342e;
        @(posedge BSY);
        Drdy <= 0;
        Din  <= 80'bX;
        @(posedge Dvld);
        repeat(10)  @(negedge CLK);
        $finish;
    end

    initial begin
        $monitor($time , "\nKEY=%h, IV=%h\nOUT=%h", Kin, Din, Dout);
        $dumpfile("Test.vcd");
        $dumpvars(0, Trivium_Test);
    end

endmodule

Trivium/kairo/Test.vcd
$date
	Fri Oct 30 17:40:31 2015
$end
$version
	Icarus Verilog
$end
$timescale
	1ns
$end
$scope module Trivium_Test $end
$var wire 1 ! BSY $end
$var wire 128 " Dout [127:0] $end
$var wire 1 # Dvld $end
$var wire 1 $ Kvld $end
$var reg 1 % CLK $end
$var reg 80 & Din [79:0] $end
$var reg 1 ' Drdy $end
$var reg 1 ( EN $end
$var reg 1 ) EncDec $end
$var reg 80 * Kin [79:0] $end
$var reg 1 + Krdy $end
$var reg 1 , RSTn $end
$scope module Trivium_Comp $end
$var wire 1 ! BSY $end
$var wire 1 - CLK $end
$var wire 80 . Din [79:0] $end
$var wire 128 / Dout [127:0] $end
$var wire 1 0 Drdy $end
$var wire 1 # Dvld $end
$var wire 1 1 EN $end
$var wire 1 2 EncDec $end
$var wire 80 3 Kin [79:0] $end
$var wire 1 4 Krdy $end
$var wire 1 $ Kvld $end
$var wire 1 5 RSTn $end
$var wire 16 6 len [15:0] $end
$var wire 80 7 li_iv [79:0] $end
$var wire 80 8 li_key [79:0] $end
$var wire 16 9 max [15:0] $end
$var reg 1 : BSYrg $end
$var reg 128 ; Doutrg [127:0] $end
$var reg 1 < Dvldrg $end
$var reg 1 = Kvldrg $end
$var reg 288 > SET [287:0] $end
$var reg 16 ? count [15:0] $end
$var reg 1 @ t1 $end
$var reg 1 A t2 $end
$var reg 1 B t3 $end
$upscope $end
$upscope $end
$enddefinitions $end
#0
$dumpvars
xB
xA
x@
bx ?
bx >
x=
x<
bx ;
x:
b10100000000 9
bx 8
bx 7
b10000000 6
15
04
bx 3
02
01
00
bx /
bx .
0-
1,
0+
bx *
0)
0(
0'
bx &
0%
x$
x#
bx "
x!
$end
#1
1%
1-
#2
0,
05
0%
0-
#3
b0 ?
0<
0#
0=
0$
0:
0!
1%
1-
#4
b1001000010000000011100000110 8
b110000001110000100000001001000000000000000000000000000000000000000000000000 *
b110000001110000100000001001000000000000000000000000000000000000000000000000 3
1+
14
1(
11
1,
15
0%
0-
#5
b101110001101001011110100111011010001001001101001111100011000110111110011110100 7
bx 8
b11110100011111000110001101111100100110100100010000111011101111010011010000101110 &
b11110100011111000110001101111100100110100100010000111011101111010011010000101110 .
1'
10
bx *
bx 3
0+
04
1=
1$
b111000000000000000000000000000000000000000000000000000000000000000000000000000000000000000000000000000000000000000000000000000000000000000000000000000000000000000000000000000000000000000000000000000000000000000000000000000000000000000000000000000000000000000001001000010000000011100000110 >
1%
1-
#6
0%
0-
#7
bx 7
bx &
bx .
0'
00
b111000000000000000000000000000000000000000000000000000000000000000000000000000000000000000000000000000000000000000000101110001101001011110100111011010001001001101001111100011000110111110011110100000000000000000000000000000000000000000000000000000000000000000001001000010000000011100000110 >
1:
1!
0=
0$
1%
1-
#8
0%
0-
#9
b1 ?
b110000000000000000000000000000000000000000000000000000000000000000000000000000000000000000000000000000000000001000001011100011010010111101001110110100010010011010011111000110001101111100111101001000000000000000000000000000000000000000000000000000000000000000010010000100000000111000001100 >
0B
1A
1@
1%
1-
#10
0%
0-
#11
b10 ?
b100000000000000000000000000000000000000000000000000000000000000000000000000000000000000000000000000000000000010000010111000110100101111010011101101000100100110100111110001100011011111001111010010000000000000000000000000000000000000000000000000000000000000000100100001000000001110000011001 >
1B
0A
0@
1%
1-
#12
0%
0-
#13
b11 ?
b101000101110001101001011110100111011010001001001101001111100011000110111110011110100101000000000000000000000000000000000000000000000000000000000000001001000010000000011100000110011 >
1@
1A
1%
1-
#14
0%
0-
#15
b100 ?
b1010001011100011010010111101001110110100010010011010011111000110001101111100111101001011000000000000000000000000000000000000000000000000000000000000010010000100000000111000001100110 >
0B
0A
1@
1%
1-
#16
0%
0-
#17
b101 ?
b10100010111000110100101111010011101101000100100110100111110001100011011111001111010010111000000000000000000000000000000000000000000000000000000000000100100001000000001110000011001100 >
1@
1%
1-
#18
0%
0-
#19
b110 ?
b101001101110001101001011110100111011010001001001101001111100011000110111110011110100101110000000000000000000000000000000000000000000000000000000000001001000010000000011100000110011000 >
1A
0@
1%
1-
#20
0%
0-
#21
b111 ?
b1010011011100011010010111101001110110100010010011010011111000110001101111100111101001011100000000000000000000000000000000000000000000000000000000000010010000100000000111000001100110000 >
1%
1-
#22
0%
0-
#23
b1000 ?
b10100110111000110100101111010011101101000100100110100111110001100011011111001111010010111000000000000000000000000000000000000000000000000000000000000100100001000000001110000011001100000 >
0A
1%
1-
#24
0%
0-
#25
b1001 ?
b101001101110001101001011110100111011010001001001101001111100011000110111110011110100101110001000000000000000000000000000000000000000000000000000000001001000010000000011100000110011000000 >
1A
1@
1%
1-
#26
0%
0-
#27
b1010 ?
b1010011010100011010010111101001110110100010010011010011111000110001101111100111101001011100011000000000000000000000000000000000000000000000000000000010010000100000000111000001100110000000 >
0A
1@
1%
1-
#28
0%
0-
#29
b1011 ?
b10100110100000110100101111010011101101000100100110100111110001100011011111001111010010111000110000000000000000000000000000000000000000000000000000000100100001000000001110000011001100000000 >
0@
1%
1-
#30
0%
0-
#31
b1100 ?
b101001101000001101001011110100111011010001001001101001111100011000110111110011110100101110001101000000000000000000000000000000000000000000000000000001001000010000000011100000110011000000000 >
1@
1%
1-
#32
0%
0-
#33
b1101 ?
b1010011010001011010010111101001110110100010010011010011111000110001101111100111101001011100011010000000000000000000000000000000000000000000000000000010010000100000000111000001100110000000000 >
1A
0@
1%
1-
#34
0%
0-
#35
b1110 ?
b10100110100011110100101111010011101101000100100110100111110001100011011111001111010010111000110100000000000000000000000000000000000000000000000000000100100001000000001110000011001100000000000 >
1A
1%
1-
#36
0%
0-
#37
b1111 ?
b101001101000111101001011110100111011010001001001101001111100011000110111110011110100101110001101001000000000000000000000000000000000000000000000000001001000010000000011100000110011000000000000 >
1@
1%
1-
#38
0%
0-
#39
b10000 ?
b1010011010001110010010111101001110110100010010011010011111000110001101111100111101001011100011010010000000000000000000000000000000000000000000000000010010000100000000111000001100110000000000000 >
0A
0@
1%
1-
#40
0%
0-
#41
b10001 ?
b10100110100011101100101111010011101101000100100110100111110001100011011111001111010010111000110100101000000000000000000000000000000000000000000000000100100001000000001110000011001100000000000000 >
1@
1A
1%
1-
#42
0%
0-
#43
b10010 ?
b101001101000111010001011110100111011010001001001101001111100011000110111110011110100101110001101001011000000000000000000000000000000000000000000000001001000010000000011100000110011000000000000000 >
0A
1@
1%
1-
#44
0%
0-
#45
b10011 ?
b1010011010001110100010111101001110110100010010011010011111000110001101111100111101001011100011010010111000000000000000000000000000000000000000000000010010000100000000111000001100110000000000000000 >
1@
1%
1-
#46
0%
0-
#47
b10100 ?
b10100110100011101001101111010011101101000100100110100111110001100011011111001111010010111000110100101111000000000000000000000000000000000000000000000100100001000000001110000011001100000000000000000 >
1A
1@
1%
1-
#48
0%
0-
#49
b10101 ?
b101001101000111010010011110100111011010001001001101001111100011000110111110011110100101110001101001011110000000000000000000000000000000000000000000001001000010000000011100000110011000000000000000000 >
0A
0@
1%
1-
#50
0%
0-
#51
b10110 ?
b1010011010001110100101111101001110110100010010011010011111000110001101111100111101001011100011010010111101000000000000000000000000000000000000000000010010000100000000111000001100110000000000000000000 >
1A
1@
1%
1-
#52
0%
0-
#53
b10111 ?
b10100110100011101001011111010011101101000100100110100111110001100011011111001111010010111000110100101111010000000000000000000000000000000000000000000100100001000000001110000011001100000000000000000000 >
1A
0@
1%
1-
#54
0%
0-
#55
b11000 ?
b101001101000111010010110110100111011010001001001101001111100011000110111110011110100101110001101001011110100000000000000000000000000000000000000000001001000010000000011100000110011000000000000000000000 >
0A
1%
1-
#56
0%
0-
#57
b11001 ?
b1010011010001110100101101101001110110100010010011010011111000110001101111100111101001011100011010010111101001000000000000000000000000000000000000000010010000100000000111000001100110000000000000000000000 >
1@
1A
1%
1-
#58
0%
0-
#59
b11010 ?
b10100110100011101001011011010011101101000100100110100111110001100011011111001111010010111000110100101111010011000000000000000000000000000000000000000100100001000000001110000011001100000000000000000000000 >
1@
1%
1-
#60
0%
0-
#61
b11011 ?
b101001101000111010010110111100111011010001001001101001111100011000110111110011110100101110001101001011110100111000000000000000000000000000000000000001001000010000000011100000110011000000000000000000000000 >
1@
1%
1-
#62
0%
0-
#63
b11100 ?
b1010011010001110100101101111001110110100010010011010011111000110001101111100111101001011100011010010111101001110000000000000000000000000000000000000010010000100000000111000001100110000000000000000000000000 >
0@
1%
1-
#64
0%
0-
#65
b11101 ?
b10100110100011101001011011110011101101000100100110100111110001100011011111001111010010111000110100101111010011101000000000000000000000000000000000000100100001000000001110000011001100000000000000000000000000 >
1@
0A
1%
1-
#66
0%
0-
#67
b11110 ?
b101001101000111010010110111100111011010001001001101001111100011000110111110011110100101110001101001011110100111011000000000000000000000000000000000001001000010000000011100000110011000000000000000000000000000 >
0A
1@
1%
1-
#68
0%
0-
#69
b11111 ?
b1010011010001110100101101111000110110100010010011010011111000110001101111100111101001011100011010010111101001110110000000000000000000000000000000000010010000100000000111000001100110000000000000000000000000000 >
0A
0@
1%
1-
#70
0%
0-
#71
b100000 ?
b10100110100011101001011011110001101101000100100110100111110001100011011111001111010010111000110100101111010011101101000000000000000000000000000000000100100001000000001110000011001100000000000000000000000000000 >
1@
1A
1%
1-
#72
0%
0-
#73
b100001 ?
b101001101000111010010110111100010011010001001001101001111100011000110111110011110100101110001101001011110100111011010000000000000000000000000000000001001000010000000011100000110011000000000000000000000000000000 >
0A
0@
1%
1-
#74
0%
0-
#75
b100010 ?
b1010011010001110100101101111000100110100010010011010011111000110001101111100111101001011100011010010111101001110110100000000000000000000000000000000010010000100000000111000001100110000000000000000000000000000000 >
0A
1%
1-
#76
0%
0-
#77
b100011 ?
b10100110100011101001011011110001001101000100100110100111110001100011011111001111010010111000110100101111010011101101000000000000000000000000000000000100100001000000001110000011001100000000000000000000000000000000 >
1A
1%
1-
#78
0%
0-
#79
b100100 ?
b101001101000111010010110111100010010010001001001101001111100011000110111110011110100101110001101001011110100111011010001000000000000000000000000000001001000010000000011100000110011000000000000000000000000000000000 >
1@
0A
1%
1-
#80
0%
0-
#81
b100101 ?
b1010011010001110100101101111000100100100010010011010011111000110001101111100111101001011100011010010111101001110110100010000000000000000000000000000010010000100000000111000001100110000000000000000000000000000000000 >
0@
1%
1-
#82
0%
0-
#83
b100110 ?
b10100110100011101001011011110001001001000100100110100111110001100011011111001111010010111000110100101111010011101101000100000000000000000000000000000100100001000000001110000011001100000000000000000000000000000000000 >
1A
1%
1-
#84
0%
0-
#85
b100111 ?
b101001101000111010010110111100010010011001001001101001111100011000110111110011110100101110001101001011110100111011010001000000000000000000000000000001001000010000000011100000110011000000000000000000000000000000000000 >
0@
1%
1-
#86
0%
0-
#87
b101000 ?
b1010011010001110100101101111000100100111010010011010011111000110001101111100111101001011100011010010111101001110110100010000000000000000000000000000010010000100000000111000001100110000000000000000000000000000000000000 >
1%
1-
#88
0%
0-
#89
b101001 ?
b10100110100011101001011011110001001001111100100110100111110001100011011111001111010010111000110100101111010011101101000100000000000000000000000000000100100001000000001110000011001100000000000000000000000000000000000000 >
1%
1-
#90
0%
0-
#91
b101010 ?
b101001101000111010010110111100010010011110001001101001111100011000110111110011110100101110001101001011110100111011010001000000000000000000000000000001001000010000000011100000110011000000000000000000000000000000000000001 >
1B
0A
0@
1%
1-
#92
0%
0-
#93
b101011 ?
b1010011010001110100101101111000100100111101010011010011111000110001101111100111101001011100011010010111101001110110100010000001000000000000000000000010010000100000000111000001100110000000000000000000000000000000000000010 >
1@
0B
1A
1%
1-
#94
0%
0-
#95
b101100 ?
b10100110100011101001011011110001001001111010100110100111110001100011011111001111010010111000110100101111010011101101000100000010000000000000000000000100100001000000001110000011001100000000000000000000000000000000000000100 >
0A
0@
1%
1-
#96
0%
0-
#97
b101101 ?
b101001101000111010010110111100010010011110101001101001111100011000110111110011110100101110001101001011110100111011010001000000101000000000000000000001001000010000000011100000110011000000000000000000000000000000000000001001 >
1B
1@
1A
1%
1-
#98
0%
0-
#99
b101110 ?
b1010011010001110100101101111000100100111101010011010011111000110001101111100111101001011100011010010111101001110110100010000001010000000000000000000010010000100000000111000001100110000000000000000000000000000000000000010010 >
0B
0A
0@
1%
1-
#100
0%
0-
#101
b101111 ?
b10100110100011101001011011110001001001111010100110100111110001100011011111001111010010111000110100101111010011101101000100000010101000000000000000000100100001000000001110000011001100000000000000000000000000000000000000100100 >
0A
1@
1%
1-
#102
0%
0-
#103
b110000 ?
b101001101000111010010110111100010010011110101000101001111100011000110111110011110100101110001101001011110100111011010001000000101011000000000000000001001000010000000011100000110011000000000000000000000000000000000000001001000 >
1@
1%
1-
#104
0%
0-
#105
b110001 ?
b1010011010001110100101101111000100100111101010001010011111000110001101111100111101001011100011010010111101001110110100010000001010111000000000000000010010000100000000111000001100110000000000000000000000000000000000000010010000 >
1A
1@
1%
1-
#106
0%
0-
#107
b110010 ?
b10100110100011101001011011110001001001111010100010100111110001100011011111001111010010111000110100101111010011101101000100000010101111000000000000000100100001000000001110000011001100000000000000000000000000000000000000100100001 >
1B
0A
1@
1%
1-
#108
0%
0-
#109
b110011 ?
b101001101000111010010110111100010010011110101000101001111100011000110111110011110100101110001101001011110100111011010001000000101011111000000000000001001000010000000011100000110011000000000000000000000000000000000000001001000010 >
0B
1A
1@
1%
1-
#110
0%
0-
#111
b110100 ?
b1010011010001110100101101111000100100111101010001011011111000110001101111100111101001011100011010010111101001110110100010000001010111111000000000000010010000100000000111000001100110000000000000000000000000000000000000010010000100 >
1@
1%
1-
#112
0%
0-
#113
b110101 ?
b10100110100011101001011011110001001001111010100010110111110001100011011111001111010010111000110100101111010011101101000100000010101111110000000000000100100001000000001110000011001100000000000000000000000000000000000000100100001000 >
0A
0@
1%
1-
#114
0%
0-
#115
b110110 ?
b101001101000111010010110111100010010011110101000101100111100011000110111110011110100101110001101001011110100111011010001000000101011111100000000000001001000010000000011100000110011000000000000000000000000000000000000001001000010000 >
0A
1%
1-
#116
0%
0-
#117
b110111 ?
b1010011010001110100101101111000100100111101010001011001111000110001101111100111101001011100011010010111101001110110100010000001010111111000000000000010010000100000000111000001100110000000000000000000000000000000000000010010000100000 >
1A
1%
1-
#118
0%
0-
#119
b111000 ?
b10100110100011101001011011110001001001111010100010110011110001100011011111001111010010111000110100101111010011101101000100000010101111110000000000000100100001000000001110000011001100000000000000000000000000000000000000100100001000000 >
1A
0@
1%
1-
#120
0%
0-
#121
b111001 ?
b101001101000111010010110111100010010011110101000101100110100011000110111110011110100101110001101001011110100111011010001000000101011111100000000000001001000010000000011100000110011000000000000000000000000000000000000001001000010000000 >
0A
0@
1%
1-
#122
0%
0-
#123
b111010 ?
b1010011010001110100101101111000100100111101010001011001100000110001101111100111101001011100011010010111101001110110100010000001010111111000001000000010010000100000000111000001100110000000000000000000000000000000000000010010000100000000 >
1@
1%
1-
#124
0%
0-
#125
b111011 ?
b10100110100011101001011011110001001001111010100010110011001001100011011111001111010010111000110100101111010011101101000100000010101111110000010000000100100001000000001110000011001100000000000000000000000000000000000000100100001000000001 >
1B
1A
0@
1%
1-
#126
0%
0-
#127
b111100 ?
b101001101000111010010110111100010010011110101000101100110010011000110111110011110100101110001101001011110100111011010001000000101011111100000100000001001000010000000011100000110011000000000000000000000000000000000000001001000010000000011 >
1B
0A
1%
1-
#128
0%
0-
#129
b111101 ?
b1010011010001110100101101111000100100111101010001011001100101110001101111100111101001011100011010010111101001110110100010000001010111111000001001000010010000100000000111000001100110000000000000000000000000000000000000010010000100000000111 >
1A
1@
1B
1%
1-
#130
0%
0-
#131
b111110 ?
b10100110100011101001011011110001001001111010100010110011001010100011011111001111010010111000110100101111010011101101000100000010101111110000010011000100100001000000001110000011001100000000000000000000000000000000000000100100001000000001110 >
0B
0A
1@
1%
1-
#132
0%
0-
#133
b111111 ?
b101001101000111010010110111100010010011110101000101100110010100000110111110011110100101110001101001011110100111011010001000000101011111100000100110001001000010000000011100000110011000000000000000000000000000000000000001001000010000000011100 >
0@
1%
1-
#134
0%
0-
#135
b1000000 ?
b1010011010001110100101101111000100100111101010001011001100101001001101111100111101001011100011010010111101001110110100010000001010111111000001001100010010000100000000111000001100110000000000000000000000000000000000000010010000100000000111000 >
1A
0@
1%
1-
#136
0%
0-
#137
b1000001 ?
b10100110100011101001011011110001001001111010100010110011001010011011011111001111010010111000110100101111010011101101000100000010101111110000010011000100100001000000001110000011001100000000000000000000000000000000000000100100001000000001110000 >
0@
1%
1-
#138
0%
0-
#139
b1000010 ?
b101001101000111010010110111100010010011110101000101100110010100111110111110011110100101110001101001011110100111011010001000000101011111100000100110000001000010000000011100000110011000000000000000000000000000000000000001001000010000000011100000 >
1A
0@
1%
1-
#140
0%
0-
#141
b1000011 ?
b1010011010001110100101101111000100100111101010001011001100101001110101111100111101001011100011010010111101001110110100010000001010111111000001001100001010000100000000111000001100110000000000000000000000000000000000000010010000100000000111000000 >
1@
0B
0A
1%
1-
#142
0%
0-
#143
b1000100 ?
b10100110100011101001011011110001001001111010100010110011001010011101011111001111010010111000110100101111010011101101000100000010101111110000010011000010100001000000001110000011001100000000000000000000000000000000000000100100001000000001110000001 >
1B
0@
1A
1%
1-
#144
0%
0-
#145
b1000101 ?
b101001101000111010010110111100010010011110101000101100110010100111011111110011110100101110001101001011110100111011010001000000101011111100000100110000100000010000000011100000110011000000000000000000000000000000000000001001000010000000011100000011 >
1A
1%
1-
#146
0%
0-
#147
b1000110 ?
b1010011010001110100101101111000100100111101010001011001100101001110111111100111101001011100011010010111101001110110100010000001010111111000001001100001000000100000000111000001100110000000000000000000000000000000000000010010000100000000111000000110 >
0B
1A
1%
1-
#148
0%
0-
#149
b1000111 ?
b10100110100011101001011011110001001001111010100010110011001010011101110111001111010010111000110100101111010011101101000100000010101111110000010011000010001001000000001110000011001100000000000000000000000000000000000000100100001000000001110000001101 >
1B
0A
1@
1%
1-
#150
0%
0-
#151
b1001000 ?
b101001101000111010010110111100010010011110101000101100110010100111011101110011110100101110001101001011110100111011010001000000101011111100000100110000100011010000000011100000110011000000000000000000000000000000000000001001000010000000011100000011010 >
0B
1A
1@
1%
1-
#152
0%
0-
#153
b1001001 ?
b1010011010001110100101101111000100100111101010001011001100101001110111010100111101001011100011010010111101001110110100010000001010111111000001001100001000111100000000111000001100110000000000000000000000000000000000000010010000100000000111000000110101 >
1B
0A
1@
1%
1-
#154
0%
0-
#155
b1001010 ?
b10100110100011101001011011110001001001111010100010110011001010011101110100001111010010111000110100101111010011101101000100000010101111110000010011000010001110000000001110000011001100000000000000000000000000000000000000100100001000000001110000001101010 >
0@
0B
1%
1-
#156
0%
0-
#157
b1001011 ?
b101001101000111010010110111100010010011110101000101100110010100111011101000011110100101110001101001011110100111011010001000000101011111100000100110000100011100000000011100000110011000000000000000000000000000000000000001001000010000000011100000011010101 >
1B
1%
1-
#158
0%
0-
#159
b1001100 ?
b1010011010001110100101101111000100100111101010001011001100101001110111010001111101001011100011010010111101001110110100010000001010111111000001001100001000111001000000111000001100110000000000000000000000000000000000000010010000100000000111000000110101010 >
1A
1@
0B
1%
1-
#160
0%
0-
#161
b1001101 ?
b10100110100011101001011011110001001001111010100010110011001010011101110100010111010010111000110100101111010011101101000100000010101111110000010011000010001110010000001110000011001100000000000000000000000000000000000000100100001000000001110000001101010100 >
0A
0@
1%
1-
#162
0%
0-
#163
b1001110 ?
b101001101000111010010110111100010010011110101000101100110010100111011101000101110100101110001101001011110100111011010001000000101011111100000100110000100011100100000011100000110011000000000000000000000000000000000000001001000010000000011100000011010101000 >
1A
1%
1-
#164
0%
0-
#165
b1001111 ?
b1010011010001110100101101111000100100111101010001011001100101001110111010001010101001011100011010010111101001110110100010000001010111111000001001100001000111001001000111000001100110000000000000000000000000000000000000010010000100000000111000000110101010001 >
1@
1B
0A
1%
1-
#166
0%
0-
#167
b1010000 ?
b10100110100011101001011011110001001001111010100010110011001010011101110100010101010010111000110100101111010011101101000100000010101111110000010011000010001110010010001110000011001100000000000000000000000000000000000000100100001000000001110000001101010100011 >
1A
0@
1%
1-
#168
0%
0-
#169
b1010001 ?
b101001101000111010010110111100010010011110101000101100110010100111011101000101011100101110001101001011110100111011010001000000101011111100000100110000100011100100101011100000110011000000000000000000000000000000000000001001000010000000011100000011010101000111 >
1@
1%
1-
#170
0%
0-
#171
b1010010 ?
b1010011010001110100101101111000100100111101010001011001100101001110111010001010111001011100011010010111101001110110100010000001010111111000001001100001000111001001010111000001100110000000000000000000000000000000000000010010000100000000111000000110101010001110 >
0B
0@
1%
1-
#172
0%
0-
#173
b1010011 ?
b10100110100011101001011011110001001001111010100010110011001010011101110100010101110010111000110100101111010011101101000100000010101111110000010011000010001110010010101110000011001100000000000000000000000000000000000000100100001000000001110000001101010100011101 >
1B
0A
1@
1%
1-
#174
0%
0-
#175
b1010100 ?
b101001101000111010010110111100010010011110101000101100110010100111011101000101011101101110001101001011110100111011010001000000101011111100000100110000100011100100101011100000110011000000000000000000000000000000000000001001000010000000011100000011010101000111010 >
0B
1A
1%
1-
#176
0%
0-
#177
b1010101 ?
b1010011010001110100101101111000100100111101010001011001100101001110111010001010111011011100011010010111101001110110100010000001010111111000001001100001000111001001010111000001100110000000000000000000000000000000000000010010000100000000111000000110101010001110100 >
1%
1-
#178
0%
0-
#179
b1010110 ?
b10100110100011101001011011110001001001111010100010110011001010011101110100010101110110111000110100101111010011101101000100000010101111110000010011000010001110010010101110000011001100000000000000000000000000000000000000100100001000000001110000001101010100011101001 >
0A
1B
0@
1%
1-
#180
0%
0-
#181
b1010111 ?
b101001101000111010010110111100010010011110101000101100110010100111011101000101011101101110001101001011110100111011010001000000101011111100000100110000100011100100101011101000110011000000000000000000000000000000000000001001000010000000011100000011010101000111010010 >
1A
1@
0B
1%
1-
#182
0%
0-
#183
b1011000 ?
b1010011010001110100101101111000100100111101010001011001100101001110111010001010111011011100011010010111101001110110100010000001010111111000001001100001000111001001010111011001100110000000000000000000000000000000000000010010000100000000111000000110101010001110100101 >
1B
1A
1@
1%
1-
#184
0%
0-
#185
b1011001 ?
b10100110100011101001011011110001001001111010100010110011001010011101110100010101110110110000110100101111010011101101000100000010101111110000010011000010001110010010101110110011001100000000000000000000000000000000000000100100001000000001110000001101010100011101001011 >
0A
0@
1%
1-
#186
0%
0-
#187
b1011010 ?
b101001101000111010010110111100010010011110101000101100110010100111011101000101011101101101001101001011110100111011010001000000101011111100000100110000100011100100101011101100110011000000000000000000000000000000000000001001000010000000011100000011010101000111010010110 >
1A
0B
1%
1-
#188
0%
0-
#189
b1011011 ?
b1010011010001110100101101111000100100111101010001011001100101001110111010001010111011011011011010010111101001110110100010000001010111111000001001100001000111001001010111011001100110000000000000000000000000000000000000010010000100000000111000000110101010001110100101101 >
1B
1@
1%
1-
#190
0%
0-
#191
b1011100 ?
b10100110100011101001011011110001001001111010100010110011001010011101110100010101110110110111110100101111010011101101000100000010101111110000010011000010001110010010101110110011001100000000000000000000000000000000000000100100001000000001110000001101010100011101001011011 >
1A
1%
1-
#192
0%
0-
#193
b1011101 ?
b101001101000111010010110111100010010011110101000101100110010100111011101000101011101101101110101001011110100111011010001000000101011111100000100110000100011100100101011101100111011000000000000000000000000000000000000001001000010000000011100000011010101000111010010110111 >
0A
1@
1%
1-
#194
0%
0-
#195
b1011110 ?
b1010011010001110100101101111000100100111101010001011001100101001110111010001010111011011011101010010111101001110110100010000001010111111000001001100001000111001001010111011001111110000000000000000000000000000000000000010010000100000000111000000110101010001110100101101111 >
1A
1@
1%
1-
#196
0%
0-
#197
b1011111 ?
b10100110100011101001011011110001001001111010100010110011001010011101110100010101110110110111011100101111010011101101000100000010101111110000010011000010001110010010101110110011110100000000000000000000000000000000000000100100001000000001110000001101010100011101001011011110 >
0@
0B
1%
1-
#198
0%
0-
#199
b1100000 ?
b101001101000111010010110111100010010011110101000101100110010100111011101000101011101101101110111001011110100111011010001000000101011111100000100110000100011100100101011101100111100000000000000000000000000000000000000001001000010000000011100000011010101000111010010110111100 >
1A
0@
1%
1-
#200
0%
0-
#201
b1100001 ?
b1010011010001110100101101111000100100111101010001011001100101001110111010001010111011011011101110010111101001110110100010000001010111111000001001100001000111001001010111011001111001000000000000000000000000000000000000010010000100000000111000000110101010001110100101101111000 >
1@
0A
1%
1-
#202
0%
0-
#203
b1100010 ?
b10100110100011101001011011110001001001111010100010110011001010011101110100010101110110110111011101101111010011101101000100000010101111110000010011000010001110010010101110110011110011000000000000000000000000000000000000100100001000000001110000001101010100011101001011011110001 >
1B
1A
1@
1%
1-
#204
0%
0-
#205
b1100011 ?
b101001101000111010010110111100010010011110101000101100110010100111011101000101011101101101110111010011110100111011010001000000101011111100000100110000100011100100101011101100111100110000000000000000000000000000000000001001000010000000011100000011010101000111010010110111100010 >
0B
0A
0@
1%
1-
#206
0%
0-
#207
b1100100 ?
b1010011010001110100101101111000100100111101010001011001100101001110111010001010111011011011101110100111101001110110100010000001010111111000001001100001000111001001010111011001111001101000000000000000000000000000000000010010000100000000111000000110101010001110100101101111000100 >
1@
1%
1-
#208
0%
0-
#209
b1100101 ?
b10100110100011101001011011110001001001111010100010110011001010011101110100010101110110110111011101000111010011101101000100000010101111110000010011000010001110010010101110110011110011010000000000000000000000000000000000100100001000000001110000001101010100011101001011011110001001 >
1B
0@
1%
1-
#210
0%
0-
#211
b1100110 ?
b101001101000111010010110111100010010011110101000101100110010100111011101000101011101101101110111010001110100111011010001000000101011111100000100110000100011100100101011101100111100110100000000000000000000000000000000001001000010000000011100000011010101000111010010110111100010010 >
0B
1A
1%
1-
#212
0%
0-
#213
b1100111 ?
b1010011010001110100101101111000100100111101010001011001100101001110111010001010111011011011101110100011101001110110100010000001010111111000001001100001000111001001010111011001111001101001000000000000000000000000000000010010000100000000111000000110101010001110100101101111000100100 >
1@
1%
1-
#214
0%
0-
