Trivium/work/hoge.v
module ENCRIPT (KEY, clk, reset, T1, T2, T3);
input [7:0] KEY;
input clk, reset;
output T1, T2, T3;
reg T1, T2, T3;
reg [7:0]SET;

always @(posedge clk or negedge reset) begin
    if(!reset) begin
        T1  <= SET[0] ^ SET[1];
        T2  <= SET[2] ^ SET[3];
        T3  <= SET[4] ^ SET[5];
        SET = {SET[6:0], T1 ^ T2 ^ T3};
    end else SET <= KEY;
end

endmodule

Trivium/work/hoge_te.v
`timescale 1ns/1ns

module test;
    reg  [7:0] KEY;
    reg clk;
    reg reset;
    wire T1, T2, T3;
    parameter times = 0.5;
    always #(times)   clk = ~clk;

    ENCRIPT ENCRIPT (KEY, clk, reset, T1, T2, T3);

    initial begin
        clk = 0;
        KEY = 8'h44;
        reset = 1;
        repeat(2) @(negedge clk);
        reset = 0;
        while(reset) @(negedge clk);
        @(negedge clk);
        repeat(20) @(negedge clk);
        $finish;
    end

    initial begin
        // $monitor($time, ", KEY=%h, IV=%h, OUT=%h", KEY, IV, OUT);
        $dumpfile("hoge.vcd");
        $dumpvars(0, test);
    end

endmodule

Trivium/work/hoge.vcd
$date
	Tue Sep 22 22:47:03 2015
$end
$version
	Icarus Verilog
$end
$timescale
	1ns
$end
$scope module test $end
$var wire 1 ! T1 $end
$var wire 1 " T2 $end
$var wire 1 # T3 $end
$var reg 8 $ KEY [7:0] $end
$var reg 1 % clk $end
$var reg 1 & reset $end
$scope module ENCRIPT $end
$var wire 8 ' KEY [7:0] $end
$var wire 1 ( clk $end
$var wire 1 ) reset $end
$var reg 8 * SET [7:0] $end
$var reg 1 + T1 $end
$var reg 1 , T2 $end
$var reg 1 - T3 $end
$upscope $end
$upscope $end
$enddefinitions $end
#0
$dumpvars
x-
x,
x+
bx *
1)
0(
b1000100 '
1&
0%
b1000100 $
x#
x"
x!
$end
#1
b1000100 *
1%
1(
#2
0%
0(
#3
1%
1(
#4
0-
0#
1,
1"
0+
0!
b1000100x *
0&
0)
0%
0(
#5
x+
x!
b100x1 *
1%
1(
#6
0%
0(
#7
1-
1#
0,
0"
b100x1x *
1%
1(
#8
0%
0(
#9
x,
x"
b100x1xx *
1%
1(
#10
0%
0(
#11
0-
0#
b100x1xxx *
1%
1(
#12
0%
0(
#13
x-
x#
b0x1xxxx *
1%
1(
#14
0%
0(
#15
b0x1xxxxx *
1%
1(
#16
0%
0(
#17
bx1xxxxxx *
1%
1(
#18
0%
0(
#19
b1xxxxxxx *
1%
1(
#20
0%
0(
#21
bx *
1%
1(
