Trivium/temp/init_2.v
module INIT_2 (IN, OUT);
    input [287:0] IN;
    output [287:0] OUT;
    wire t1, t2, t3;

    assign t1 = IN[65]  ^ (IN[90]  & IN[91] ) ^ IN[92]  ^ IN[170];
    assign t2 = IN[161] ^ (IN[174] & IN[175]) ^ IN[176] ^ IN[263];
    assign t3 = IN[242] ^ (IN[285] & IN[286]) ^ IN[287] ^ IN[68];

    assign OUT[92:0]    = {IN[91:0]   , t3};
    assign OUT[176:93]  = {IN[175:93] , t1};
    assign OUT[287:177] = {IN[286:177], t2};
endmodule

Trivium/work/init_te.v
`timescale 1ns/1ns

module test;
    reg  [287:0] IN;
    wire [287:0] OUT;

    INIT_2 INIT_2 (IN, OUT);
    always #10 IN = OUT;
    initial begin
        IN  = 288'h01010101010101101010101101010110101010110101020304040;
        #200    $finish;
    end

    initial begin
        $monitor($time, "IN=%h, OUT=%h", IN, OUT);
        $dumpfile("init.vcd");
        $dumpvars(0, test);
    end
endmodule

Trivium/work/init.vcd
$date
	Tue Aug  4 15:58:32 2015
$end
$version
	Icarus Verilog
$end
$timescale
	1ns
$end
$scope module test $end
$var wire 288 ! OUT [287:0] $end
$var reg 288 " IN [287:0] $end
$scope module INIT_2 $end
$var wire 288 # IN [287:0] $end
$var wire 288 $ OUT [287:0] $end
$var wire 1 % t1 $end
$var wire 1 & t2 $end
$var wire 1 ' t3 $end
$upscope $end
$upscope $end
$enddefinitions $end
#0
$dumpvars
0'
0&
1%
b10000000100000001000000010000000100000001000000010001000000010000000100000001000000010001000000010000000100000001000100000001000000010000000100000001000100000001000000010000001000000011000001000000010000000 $
b1000000010000000100000001000000010000000100000001000100000001000000010000000100000001000100000001000000010000000100010000000100000001000000010000000100010000000100000001000000100000001100000100000001000000 #
b1000000010000000100000001000000010000000100000001000100000001000000010000000100000001000100000001000000010000000100010000000100000001000000010000000100010000000100000001000000100000001100000100000001000000 "
b10000000100000001000000010000000100000001000000010001000000010000000100000001000000010001000000010000000100000001000100000001000000010000000100000001000100000001000000010000001000000011000001000000010000000 !
$end
#10
1%
b100000001000000010000000100000001000000010000000100010000000100000001000000010000000100010000000100000001000000011001000000010000000100000001000000010001000000010000000100000010000000110000010000000100000000 !
b100000001000000010000000100000001000000010000000100010000000100000001000000010000000100010000000100000001000000011001000000010000000100000001000000010001000000010000000100000010000000110000010000000100000000 $
b10000000100000001000000010000000100000001000000010001000000010000000100000001000000010001000000010000000100000001000100000001000000010000000100000001000100000001000000010000001000000011000001000000010000000 "
b10000000100000001000000010000000100000001000000010001000000010000000100000001000000010001000000010000000100000001000100000001000000010000000100000001000100000001000000010000001000000011000001000000010000000 #
#20
0%
b1000000010000000100000001000000010000000100000001000100000001000000010000000100000001000100000001000000010000000110010000000100000001000000010000000100010000000100000001000000100000001100000100000001000000000 !
b1000000010000000100000001000000010000000100000001000100000001000000010000000100000001000100000001000000010000000110010000000100000001000000010000000100010000000100000001000000100000001100000100000001000000000 $
b100000001000000010000000100000001000000010000000100010000000100000001000000010000000100010000000100000001000000011001000000010000000100000001000000010001000000010000000100000010000000110000010000000100000000 "
b100000001000000010000000100000001000000010000000100010000000100000001000000010000000100010000000100000001000000011001000000010000000100000001000000010001000000010000000100000010000000110000010000000100000000 #
#30
b10000000100000001000000010000000100000001000000010001000000010000000100000001000000010001000000010000000100000001100100000001000000010000000100000001000100000001000000010000001000000011000001000000010000000000 !
b10000000100000001000000010000000100000001000000010001000000010000000100000001000000010001000000010000000100000001100100000001000000010000000100000001000100000001000000010000001000000011000001000000010000000000 $
b1000000010000000100000001000000010000000100000001000100000001000000010000000100000001000100000001000000010000000110010000000100000001000000010000000100010000000100000001000000100000001100000100000001000000000 "
b1000000010000000100000001000000010000000100000001000100000001000000010000000100000001000100000001000000010000000110010000000100000001000000010000000100010000000100000001000000100000001100000100000001000000000 #
#40
1%
1&
1'
b100000001000000010000000100000001000000010000000100010000000100000001000000010000000100010000000100000001000000011001000000010000000100000001000000010001000000010000000100000010000000110000010000000100000000001 !
b100000001000000010000000100000001000000010000000100010000000100000001000000010000000100010000000100000001000000011001000000010000000100000001000000010001000000010000000100000010000000110000010000000100000000001 $
b10000000100000001000000010000000100000001000000010001000000010000000100000001000000010001000000010000000100000001100100000001000000010000000100000001000100000001000000010000001000000011000001000000010000000000 "
b10000000100000001000000010000000100000001000000010001000000010000000100000001000000010001000000010000000100000001100100000001000000010000000100000001000100000001000000010000001000000011000001000000010000000000 #
#50
0%
1&
0'
b1000000010000000100000001000000011000000100000001000100000001000000010000000100000001000100000001000000010000000110010000000100000001000000010000000100010000000100000001000000100000001100000100000001000000000010 !
b1000000010000000100000001000000011000000100000001000100000001000000010000000100000001000100000001000000010000000110010000000100000001000000010000000100010000000100000001000000100000001100000100000001000000000010 $
b100000001000000010000000100000001000000010000000100010000000100000001000000010000000100010000000100000001000000011001000000010000000100000001000000010001000000010000000100000010000000110000010000000100000000001 "
b100000001000000010000000100000001000000010000000100010000000100000001000000010000000100010000000100000001000000011001000000010000000100000001000000010001000000010000000100000010000000110000010000000100000000001 #
#60
0&
1%
b10000000100000001000000010000000110000001000000010001000000010000000100000001000000010001000000010000000100000001100101000001000000010000000100000001000100000001000000010000001000000011000001000000010000000000100 !
b10000000100000001000000010000000110000001000000010001000000010000000100000001000000010001000000010000000100000001100101000001000000010000000100000001000100000001000000010000001000000011000001000000010000000000100 $
b1000000010000000100000001000000011000000100000001000100000001000000010000000100000001000100000001000000010000000110010000000100000001000000010000000100010000000100000001000000100000001100000100000001000000000010 "
b1000000010000000100000001000000011000000100000001000100000001000000010000000100000001000100000001000000010000000110010000000100000001000000010000000100010000000100000001000000100000001100000100000001000000000010 #
#70
0%
b100000001000000010000000100000001100000010000000100010000000100000001000000010000000100010000000100000001000000011001010000010000000100000001000000010001000000010000000100000010000000110000010000000100000000001000 !
b100000001000000010000000100000001100000010000000100010000000100000001000000010000000100010000000100000001000000011001010000010000000100000001000000010001000000010000000100000010000000110000010000000100000000001000 $
b10000000100000001000000010000000110000001000000010001000000010000000100000001000000010001000000010000000100000001100101000001000000010000000100000001000100000001000000010000001000000011000001000000010000000000100 "
b10000000100000001000000010000000110000001000000010001000000010000000100000001000000010001000000010000000100000001100101000001000000010000000100000001000100000001000000010000001000000011000001000000010000000000100 #
#80
b1000000010000000100000001000000011000000100000001000100000001000000010000000100000001000100000001000000010000000110010100000100000001000000010000000100010000000100000001000000100000001100000100000001000000000010000 !
b1000000010000000100000001000000011000000100000001000100000001000000010000000100000001000100000001000000010000000110010100000100000001000000010000000100010000000100000001000000100000001100000100000001000000000010000 $
b100000001000000010000000100000001100000010000000100010000000100000001000000010000000100010000000100000001000000011001010000010000000100000001000000010001000000010000000100000010000000110000010000000100000000001000 "
b100000001000000010000000100000001100000010000000100010000000100000001000000010000000100010000000100000001000000011001010000010000000100000001000000010001000000010000000100000010000000110000010000000100000000001000 #
#90
1%
1&
b10000000100000001000000010000000110001001000000010001000000010000000100000001000000010001000000010000000100000001100101001001000000010000000100000001000100000001000000010000001000000011000001000000010000000000100000 !
b10000000100000001000000010000000110001001000000010001000000010000000100000001000000010001000000010000000100000001100101001001000000010000000100000001000100000001000000010000001000000011000001000000010000000000100000 $
b1000000010000000100000001000000011000000100000001000100000001000000010000000100000001000100000001000000010000000110010100000100000001000000010000000100010000000100000001000000100000001100000100000001000000000010000 "
b1000000010000000100000001000000011000000100000001000100000001000000010000000100000001000100000001000000010000000110010100000100000001000000010000000100010000000100000001000000100000001100000100000001000000000010000 #
#100
0%
0&
b100000001000000010000000100000001100010010000000100010000000100000001000000010000000100010000000100000001000000011001010010010000000100000001000000010001000000010000000100000010000000110000010000000100000000001000000 !
b100000001000000010000000100000001100010010000000100010000000100000001000000010000000100010000000100000001000000011001010010010000000100000001000000010001000000010000000100000010000000110000010000000100000000001000000 $
b10000000100000001000000010000000110001001000000010001000000010000000100000001000000010001000000010000000100000001100101001001000000010000000100000001000100000001000000010000001000000011000001000000010000000000100000 "
b10000000100000001000000010000000110001001000000010001000000010000000100000001000000010001000000010000000100000001100101001001000000010000000100000001000100000001000000010000001000000011000001000000010000000000100000 #
#110
b1000000010000000100000001000000011000100100000001000100000001000000010000000100000001000100000001000000010000000110010100100100000001000000010000000100010000000100000001000000100000001100000100000001000000000010000000 !
b1000000010000000100000001000000011000100100000001000100000001000000010000000100000001000100000001000000010000000110010100100100000001000000010000000100010000000100000001000000100000001100000100000001000000000010000000 $
b100000001000000010000000100000001100010010000000100010000000100000001000000010000000100010000000100000001000000011001010010010000000100000001000000010001000000010000000100000010000000110000010000000100000000001000000 "
b100000001000000010000000100000001100010010000000100010000000100000001000000010000000100010000000100000001000000011001010010010000000100000001000000010001000000010000000100000010000000110000010000000100000000001000000 #
#120
1%
1&
1'
b10000000100000001000000010000000110001001000000010001000000010000000100000001000000010001000000010000000100000001100101001001000000010000000100000001000100000001000000010000001000000011000001000000010000000000100000001 !
b10000000100000001000000010000000110001001000000010001000000010000000100000001000000010001000000010000000100000001100101001001000000010000000100000001000100000001000000010000001000000011000001000000010000000000100000001 $
b1000000010000000100000001000000011000100100000001000100000001000000010000000100000001000100000001000000010000000110010100100100000001000000010000000100010000000100000001000000100000001100000100000001000000000010000000 "
b1000000010000000100000001000000011000100100000001000100000001000000010000000100000001000100000001000000010000000110010100100100000001000000010000000100010000000100000001000000100000001100000100000001000000000010000000 #
#130
1%
0&
0'
b100000001000000010000000100000001100010010000000100010000000100000001000000010000000100010000000100000001000000011001010010011000000100000001000000010001000000010000000100000010000000110000010000000100000000001000000010 !
b100000001000000010000000100000001100010010000000100010000000100000001000000010000000100010000000100000001000000011001010010011000000100000001000000010001000000010000000100000010000000110000010000000100000000001000000010 $
b10000000100000001000000010000000110001001000000010001000000010000000100000001000000010001000000010000000100000001100101001001000000010000000100000001000100000001000000010000001000000011000001000000010000000000100000001 "
b10000000100000001000000010000000110001001000000010001000000010000000100000001000000010001000000010000000100000001100101001001000000010000000100000001000100000001000000010000001000000011000001000000010000000000100000001 #
#140
1%
b1000000010000000100000001000000011000100100000001000100000001000000010000000100000001000100000001000000010000000110010100100111000001000000010000000100010000000100000001000000100000001100000100000001000000000010000000100 !
b1000000010000000100000001000000011000100100000001000100000001000000010000000100000001000100000001000000010000000110010100100111000001000000010000000100010000000100000001000000100000001100000100000001000000000010000000100 $
b100000001000000010000000100000001100010010000000100010000000100000001000000010000000100010000000100000001000000011001010010011000000100000001000000010001000000010000000100000010000000110000010000000100000000001000000010 "
b100000001000000010000000100000001100010010000000100010000000100000001000000010000000100010000000100000001000000011001010010011000000100000001000000010001000000010000000100000010000000110000010000000100000000001000000010 #
#150
0%
b10000000100000001000000010000000110001001000000010001000000010000000100000001000000010001000000010000000100000001100101001001110000010000000100000001000100000001000000010000001000000011000001000000010000000000100000001000 !
b10000000100000001000000010000000110001001000000010001000000010000000100000001000000010001000000010000000100000001100101001001110000010000000100000001000100000001000000010000001000000011000001000000010000000000100000001000 $
b1000000010000000100000001000000011000100100000001000100000001000000010000000100000001000100000001000000010000000110010100100111000001000000010000000100010000000100000001000000100000001100000100000001000000000010000000100 "
b1000000010000000100000001000000011000100100000001000100000001000000010000000100000001000100000001000000010000000110010100100111000001000000010000000100010000000100000001000000100000001100000100000001000000000010000000100 #
#160
1'
b100000001000000010000000100000001100010010000000100010000000100000001000000010000000100010000000100000001000000011001010010011100000100000001000000010001000000010000000100000010000000110000010000000100000000001000000010001 !
b100000001000000010000000100000001100010010000000100010000000100000001000000010000000100010000000100000001000000011001010010011100000100000001000000010001000000010000000100000010000000110000010000000100000000001000000010001 $
b10000000100000001000000010000000110001001000000010001000000010000000100000001000000010001000000010000000100000001100101001001110000010000000100000001000100000001000000010000001000000011000001000000010000000000100000001000 "
b10000000100000001000000010000000110001001000000010001000000010000000100000001000000010001000000010000000100000001100101001001110000010000000100000001000100000001000000010000001000000011000001000000010000000000100000001000 #
#170
1&
0'
b1000000010000000100000001000000011000100100001001000100000001000000010000000100000001000100000001000000010000000110010100100111000001000000010000000100010000000100000001000000100000001100000100000001000000000010000000100010 !
b1000000010000000100000001000000011000100100001001000100000001000000010000000100000001000100000001000000010000000110010100100111000001000000010000000100010000000100000001000000100000001100000100000001000000000010000000100010 $
b100000001000000010000000100000001100010010000000100010000000100000001000000010000000100010000000100000001000000011001010010011100000100000001000000010001000000010000000100000010000000110000010000000100000000001000000010001 "
b100000001000000010000000100000001100010010000000100010000000100000001000000010000000100010000000100000001000000011001010010011100000100000001000000010001000000010000000100000010000000110000010000000100000000001000000010001 #
#180
0&
1%
b10000000100000001000000010000000110001001000010010001000000010000000100000001000000010001000000010000000100000001100101001001110001010000000100000001000100000001000000010000001000000011000001000000010000000000100000001000100 !
b10000000100000001000000010000000110001001000010010001000000010000000100000001000000010001000000010000000100000001100101001001110001010000000100000001000100000001000000010000001000000011000001000000010000000000100000001000100 $
b1000000010000000100000001000000011000100100001001000100000001000000010000000100000001000100000001000000010000000110010100100111000001000000010000000100010000000100000001000000100000001100000100000001000000000010000000100010 "
b1000000010000000100000001000000011000100100001001000100000001000000010000000100000001000100000001000000010000000110010100100111000001000000010000000100010000000100000001000000100000001100000100000001000000000010000000100010 #
#190
0%
b100000001000000010000000100000001100010010000100100010000000100000001000000010000000100010000000100000001000000011001010010011100010100000001000000010001000000010000000100000010000000110000010000000100000000001000000010001000 !
b100000001000000010000000100000001100010010000100100010000000100000001000000010000000100010000000100000001000000011001010010011100010100000001000000010001000000010000000100000010000000110000010000000100000000001000000010001000 $
b10000000100000001000000010000000110001001000010010001000000010000000100000001000000010001000000010000000100000001100101001001110001010000000100000001000100000001000000010000001000000011000001000000010000000000100000001000100 "
b10000000100000001000000010000000110001001000010010001000000010000000100000001000000010001000000010000000100000001100101001001110001010000000100000001000100000001000000010000001000000011000001000000010000000000100000001000100 #
#200
1%
1&
b1000000010000000100000001000000011000100100001001000100000001000000010000000100000001000100000001000000010000000110010100100111000101000000010000000100010000000100000001000000100000001100000100000001000000000010000000100010000 !
b1000000010000000100000001000000011000100100001001000100000001000000010000000100000001000100000001000000010000000110010100100111000101000000010000000100010000000100000001000000100000001100000100000001000000000010000000100010000 $
b100000001000000010000000100000001100010010000100100010000000100000001000000010000000100010000000100000001000000011001010010011100010100000001000000010001000000010000000100000010000000110000010000000100000000001000000010001000 "
b100000001000000010000000100000001100010010000100100010000000100000001000000010000000100010000000100000001000000011001010010011100010100000001000000010001000000010000000100000010000000110000010000000100000000001000000010001000 #
