Trivium/work/encript.v
module ENCRIPT (KEY, IV, len, clk, reset, OUT);
    input [79:0] KEY, IV;
    input [11:0] len;
    input clk, reset;
    output [511:0] OUT;
    reg [11:0] key_cot, str_cot;
    reg [287:0] SET;
    reg [511:0] STRM;
    reg [511:0] OUT;
    reg t1, t2, t3;

    always @(posedge clk or negedge reset) begin
        if(reset == 1'b0) begin
            if(key_cot == 1'b0) begin
                SET[79:0]    <= KEY;
                SET[92:80]   <= 0;
                SET[172:93]  <= IV;
                SET[284:173] <= 0;
                SET[287:285] <= 3'b111;
                key_cot      <= 1;
                str_cot      <= 0;
            end else if(key_cot < 12'h480) begin
                SET[92:0]    <= {SET[91:0]   , SET[242] ^ (SET[285] & SET[286]) ^ SET[287] ^ SET[68]};
                SET[176:93]  <= {SET[175:93] , SET[65]  ^ (SET[90]  & SET[91] ) ^ SET[92]  ^ SET[170]};
                SET[287:177] <= {SET[286:177], SET[161] ^ (SET[174] & SET[175]) ^ SET[176] ^ SET[263]};
                key_cot      <= key_cot + 1;
            end else begin
                if(str_cot < len) begin
                    STRM[str_cot] <= SET[65] ^ SET[93] ^ SET[161] ^ SET[176] ^ SET[242] ^ SET[287];
                    SET[92:0]     <= {SET[91:0]   , SET[242] ^ SET[287] ^ (SET[285] & SET[286]) ^ SET[68]};
                    SET[176:93]   <= {SET[175:93] , SET[65]  ^ SET[93]  ^ (SET[90]  & SET[91] ) ^ SET[170]};
                    SET[287:177]  <= {SET[286:177], SET[161] ^ SET[176] ^ (SET[174] & SET[175]) ^ SET[263]};
                    str_cot       <= str_cot + 1;
                end else
                    OUT <= STRM;
            end
        end else begin
            key_cot <= 0;
        end
    end

endmodule

Trivium/work/test_te.v
`timescale 1ns/1ns

module test;
    reg  [79:0] KEY;
    reg  [79:0] IV;
    reg [11:0] len;
    reg clk;
    reg reset;
    wire [511:0] OUT;
    parameter times = 0.5;
    always #(times)   clk = ~clk;

    ENCRIPT ENCRIPT (KEY, IV, len, clk, reset, OUT);
    // ENCRIPT ENCRIPT (KEY, IV, clk, reset, OUT);

    initial begin
        clk = 1'b0;
        KEY = 80'h80000000000000000000;
        IV  = 80'h00000000000000000000;
        // IV  = 80'hffffffffffffffffffff;
        // KEY = 80'hffffffffffffffffffff;
        len = 511;
        reset = 1;
        repeat(2) @(negedge clk);
        reset = 0;
        while(reset) @(negedge clk);
        @(negedge clk);
        repeat(2000) @(negedge clk);
        $finish;
    end

    initial begin
        $dumpfile("trivium.vcd");
        $dumpvars(0, test);
    end

endmodule

Trivium/work/trivium.vcd
$date
	Sun Sep 13 12:47:53 2015
$end
$version
	Icarus Verilog
$end
$timescale
	1ns
$end
$scope module test $end
$var wire 512 ! OUT [511:0] $end
$var reg 80 " IV [79:0] $end
$var reg 80 # KEY [79:0] $end
$var reg 1 $ clk $end
$var reg 12 % len [11:0] $end
$var reg 1 & reset $end
$scope module ENCRIPT $end
$var wire 80 ' IV [79:0] $end
$var wire 80 ( KEY [79:0] $end
$var wire 1 ) clk $end
$var wire 12 * len [11:0] $end
$var wire 1 + reset $end
$var reg 512 , OUT [511:0] $end
$var reg 288 - SET [287:0] $end
$var reg 512 . STRM [511:0] $end
$var reg 12 / key_cot [11:0] $end
$var reg 12 0 str_cot [11:0] $end
$upscope $end
$upscope $end
$enddefinitions $end
#0
$dumpvars
bx 0
bx /
bx .
bx -
bx ,
1+
b1000000000 *
0)
b0 (
b10000000000000000000000000000000000000000000000000000000000000000000000000000000 '
1&
b1000000000 %
0$
b0 #
b10000000000000000000000000000000000000000000000000000000000000000000000000000000 "
bx !
$end
#1
b0 /
1$
1)
#2
0$
0)
#3
1$
1)
#4
b0 0
b1 /
b111000000000000000000000000000000000000000000000000000000000000000000000000000000000000000000000000000000000000000010000000000000000000000000000000000000000000000000000000000000000000000000000000000000000000000000000000000000000000000000000000000000000000000000000000000000000000000000000 -
0&
0+
0$
0)
#5
b10 /
b110000000000000000000000000000000000000000000000000000000000000000000000000000000000000000000000000000000000000000100000000000000000000000000000000000000000000000000000000000000000000000000000000000000000000000000000000000000000000000000000000000000000000000000000000000000000000000000000 -
1$
1)
#6
0$
0)
#7
b11 /
b100000000000000000000000000000000000000000000000000000000000000000000000000000000000000000000000000000000000000001000000000000000000000000000000000000000000000000000000000000000000000000000000000000000000000000000000000000000000000000000000000000000000000000000000000000000000000000000001 -
1$
1)
#8
0$
0)
#9
b100 /
b10000000000000000000000000000000000000000000000000000000000000000000000000000000000000000000000000000000000000000000000000000000000000000000000000000000000000000000000000000011 -
1$
1)
#10
0$
0)
#11
b101 /
b100000000000000000000000000000000000000000000000000000000000000000000000000000000000000000000000000000000000000000000000000000000000000000000000000000000000000000000000000000110 -
1$
1)
#12
0$
0)
#13
b110 /
b1000000000000000000000000000000000000000000000000000000000000000000000000000000000000000000000000000000000000000000000000000000000000000000000000000000000000000000000000000001100 -
1$
1)
#14
0$
0)
#15
b111 /
b10000000000000000000000000000000000000000000000000000000000000000000000000000000000000000000000000000000000000000000000000000000000000000000000000000000000000000000000000000011000 -
1$
1)
#16
0$
0)
#17
b1000 /
b100000000000000000000000000000000000000000000000000000000000000000000000000000000000000000000000000000000000000000000000000000000000000000000000000000000000000000000000000000110000 -
1$
1)
#18
0$
0)
#19
b1001 /
b1000000000000000000000000000000000000000000000000000000000000000000000000000000000000000000000000000000000000000000000000000000000000000000000000000000000000000000000000000001100000 -
1$
1)
#20
0$
0)
#21
b1010 /
b10000000000000000000000000000000000000000000000000000000000000000000000000000000000000000000000000000000000000000000000000000000000000000000000000000000000000000000000000000011000000 -
1$
1)
#22
0$
0)
#23
b1011 /
b100000000000000000000000000000000000000000000000000000000000000000000000000000000000000000000000000000000000000000000000000000000000000000000000000000000000000000000000000000110000000 -
1$
1)
#24
0$
0)
#25
b1100 /
b1000000000000000000000000000000000000000000000000000000000000000000000000000000000000000000000000000000000000000000000000000000000000000000000000000000000000000000000000000001100000000 -
1$
1)
#26
0$
0)
#27
b1101 /
b10000000000000000000000000000000000000000000000000000000000000000000000000000000000000000000000000000000000000000000000000000000000000000000000000000000000000000000000000000011000000000 -
1$
1)
#28
0$
0)
#29
b1110 /
b100000000000000000000000000000000000000000000000000000000000000000000000000000000000000000000000000000000000000000000000000000000000000000000000000000000000000000000000000000110000000000 -
1$
1)
#30
0$
0)
#31
b1111 /
b1000000000000000000000000000000000000000000000000000000000000000000000000000000000000000000000000000000000000000000000000000000000000000000000000000000000000000000000000000001100000000000 -
1$
1)
#32
0$
0)
#33
b10000 /
b10000000000000000000000000000000000000000000000000000000000000000000000000000000000000000000000000000000000000000000000000000000000000000000000000000000000000000000000000000011000000000000 -
1$
1)
#34
0$
0)
#35
b10001 /
b100000000000000000000000000000000000000000000000000000000000000000000000000000000000000000000000000000000000000000000000000000000000000000000000000000000000000000000000000000110000000000000 -
1$
1)
#36
0$
0)
#37
b10010 /
b1000000000000000000000000000000000000000000000000000000000000000000000000000000000000000000000000000000000000000000000000000000000000000000000000000000000000000000000000000001100000000000000 -
1$
1)
#38
0$
0)
#39
b10011 /
b10000000000000000000000000000000000000000000000000000000000000000000000000000000000000000000000000000000000000000000000000000000000000000000000000000000000000000000000000000011000000000000000 -
1$
1)
#40
0$
0)
#41
b10100 /
b100000000000000000000000000000000000000000000000000000000000000000000000000000000000000000000000000000000000000000000000000000000000000000000000000000000000000000000000000000110000000000000000 -
1$
1)
#42
0$
0)
#43
b10101 /
b1000000000000000000000000000000000000000000000000000000000000000000000000000000000000000000000000000000000000000000000000000000000000000000000000000000000000000000000000000001100000000000000000 -
1$
1)
#44
0$
0)
#45
b10110 /
b10000000000000000000000000000000000000000000000000000000000000000000000000000000000000000000000000000000000000000000000000000000000000000000000000000000000000000000000000000011000000000000000000 -
1$
1)
#46
0$
0)
#47
b10111 /
b100000000000000000000000000000000000000000000000000000000000000000000000000000000000000000000000000000000000000000000000000000000000000000000000000000000000000000000000000000110000000000000000000 -
1$
1)
#48
0$
0)
#49
b11000 /
b1000000000000000000000000000000000000000000000000000000000000000000000000000000000000000000000000000000000000000000000000000000000000000000000000000000000000000000000000000001100000000000000000000 -
1$
1)
#50
0$
0)
#51
b11001 /
b10000000000000000000000000000000000000000000000000000000000000000000000000000000000000000000000000000000000000000000000000000000000000000000000000000000000000000000000000000011000000000000000000000 -
1$
1)
#52
0$
0)
#53
b11010 /
b100000000000000000000000000000000000000000000000000000000000000000000000000000000000000000000000000000000000000000000000000000000000000000000000000000000000000000000000000000110000000000000000000000 -
1$
1)
#54
0$
0)
#55
b11011 /
b1000000000000000000000000000000000000000000000000000000000000000000000000000000000000000000000000000000000000000000000000000000000000000000000000000000000000000000000000000001100000000000000000000000 -
1$
1)
#56
0$
0)
#57
b11100 /
b10000000000000000000000000000000000000000000000000000000000000000000000000000000000000000000000000000000000000000000000000000000000000000000000000000000000000000000000000000011000000000000000000000000 -
1$
1)
#58
0$
0)
#59
b11101 /
b100000000000000000000000000000000000000000000000000000000000000000000000000000000000000000000000000000000000000000000000000000000000000000000000000000000000000000000000000000110000000000000000000000000 -
1$
1)
#60
0$
0)
#61
b11110 /
b1000000000000000000000000000000000000000000000000000000000000000000000000000000000000000000000000000000000000000000000000000000000000000000000000000000000000000000000000000001100000000000000000000000000 -
1$
1)
#62
0$
0)
#63
b11111 /
b10000000000000000000000000000000000000000000000000000000000000000000000000000000000000000000000000000000000000000000000000000000000000000000000000000000000000000000000000000011000000000000000000000000000 -
1$
1)
#64
0$
0)
#65
b100000 /
b100000000000000000000000000000000000000000000000000000000000000000000000000000000000000000000000000000000000000000000000000000000000000000000000000000000000000000000000000000110000000000000000000000000000 -
1$
1)
#66
0$
0)
#67
b100001 /
b1000000000000000000000000000000000000000000000000000000000000000000000000000000000000000000000000000000000000000000000000000000000000000000000000000000000000000000000000000001100000000000000000000000000000 -
1$
1)
#68
0$
0)
#69
b100010 /
b10000000000000000000000000000000000000000000000000000000000000000000000000000000000000000000000000000000000000000000000000000000000000000000000000000000000000000000000000000011000000000000000000000000000000 -
1$
1)
#70
0$
0)
#71
b100011 /
b100000000000000000000000000000000000000000000000000000000000000000000000000000000000000000000000000000000000000000000000000000000000000000000000000000000000000000000000000000110000000000000000000000000000000 -
1$
1)
#72
0$
0)
#73
b100100 /
b1000000000000000000000000000000000000000000000000000000000000000000000000000000000000000000000000000000000000000000000000000000000000000000000000000000000000000000000000000001100000000000000000000000000000000 -
1$
1)
#74
0$
0)
#75
b100101 /
b10000000000000000000000000000000000000000000000000000000000000000000000000000000000000000000000000000000000000000000000000000000000000000000000000000000000000000000000000000011000000000000000000000000000000000 -
1$
1)
#76
0$
0)
#77
b100110 /
b100000000000000000000000000000000000000000000000000000000000000000000000000000000000000000000000000000000000000000000000000000000000000000000000000000000000000000000000000000110000000000000000000000000000000000 -
1$
1)
#78
0$
0)
#79
b100111 /
b1000000000000000000000000000000000000000000000000000000000000000000000000000000000000000000000000000000000000000000000000000000000000000000000000000000000000000000000000000001100000000000000000000000000000000000 -
1$
1)
#80
0$
0)
#81
b101000 /
b10000000000000000000000000000000000000000000000000000000000000000000000000000000000000000000000000000000000000000000000000000000000000000000000000000000000000000000000000000011000000000000000000000000000000000000 -
1$
1)
#82
0$
0)
#83
b101001 /
b100000000000000000000000000000000000000000000000000000000000000000000000000000000000000000000000000000000000000000000000000000000000000000000000000000000000000000000000000000110000000000000000000000000000000000000 -
1$
1)
#84
0$
0)
#85
b101010 /
b1000000000000000000000000000000000000000000000000000000000000000000000000000000000000000000000000000000000000000000000000000000000000000000000000000000000000000000000000000001100000000000000000000000000000000000000 -
1$
1)
#86
0$
0)
#87
b101011 /
b10000000000000000000000000000000000000000000000000000000000000000000000000000000000000000000000000000000000000000000000000000000000000000000000000000000000000000000000000000011000000000000000000000000000000000000000 -
1$
1)
#88
0$
0)
#89
b101100 /
b100000000000000000000000000000000000000000000000000000000000000000000000000000000000000000000000000000000000000000000000000000000000000000000000000000000000000000000000000000110000000000000000000000000000000000000000 -
1$
1)
#90
0$
0)
#91
b101101 /
b1000000000000000000000000000000000000000000000000000000000000000000000000000000000000000000000000000000000000000000000000000000000000000000000000000000000000000000000000000001100000000000000000000000000000000000000000 -
1$
1)
#92
0$
0)
#93
b101110 /
b10000000000000000000000000000000000000000000000000000000000000000000000000000000000000000000000000000000000000000000000000000000000000000000000000000000000000000000000000000011000000000000000000000000000000000000000000 -
1$
1)
#94
0$
0)
#95
b101111 /
b100000000000000000000000000000000000000000000000000000000000000000000000000000000000000000000000000000000000000000000000000000000000000000000000000000000000000000000000000000110000000000000000000000000000000000000000000 -
1$
1)
#96
0$
0)
#97
b110000 /
b1000000000000000000000000000000000000000000000000000000000000000000000000000000000000000000000000000000000000000000000000000000000000000000000000000000000000000000000000000001100000000000000000000000000000000000000000000 -
1$
1)
#98
0$
0)
#99
b110001 /
b10000000000000000000000000000000000000000000000000000000000000000000000000000000000000000000000000000000000000000000000000000000000000000000000000000000000000000000000000000011000000000000000000000000000000000000000000000 -
1$
1)
#100
0$
0)
#101
b110010 /
b100000000000000000000000000000000000000000000000000000000000000000000000000000000000000000000000000000000000000000000000000000000000000000000000000000000000000000000000000000110000000000000000000000000000000000000000000000 -
1$
1)
#102
0$
0)
#103
b110011 /
b1000000000000000000000000000000000000000000000000000000000000000000000000000000000000000000000000000000000000000000000000000000000000000000000000000000000000000000000000000001100000000000000000000000000000000000000000000000 -
1$
1)
#104
0$
0)
#105
b110100 /
b10000000000000000000000000000000000000000000000000000000000000000000000000000000000000000000000000000000000000000000000000000000000000000000000000000000000000000000000000000011000000000000000000000000000000000000000000000000 -
1$
1)
#106
0$
0)
#107
b110101 /
b100000000000000000000000000000000000000000000000000000000000000000000000000000000000000000000000000000000000000000000000000000000000000000000000000000000000000000000000000000110000000000000000000000000000000000000000000000000 -
1$
1)
#108
0$
0)
#109
b110110 /
b1000000000000000000000000000000000000000000000000000000000000000000000000000000000000000000000000000000000000000000000000000000000000000000000000000000000000000000000000000001100000000000000000000000000000000000000000000000000 -
1$
1)
#110
0$
0)
#111
b110111 /
b10000000000000000000000000000000000000000000000000000000000000000000000000000000000000000000000000000000000000000000000000000000000000000000000000000000000000000000000000000011000000000000000000000000000000000000000000000000000 -
1$
1)
#112
0$
0)
#113
b111000 /
b100000000000000000000000000000000000000000000000000000000000000000000000000000000000000000000000000000000000000000000000000000000000000000000000000000000000000000000000000000110000000000000000000000000000000000000000000000000000 -
1$
1)
#114
0$
0)
#115
b111001 /
b1000000000000000000000000000000000000000000000000000000000000000000000000000000000000000000000000000000000000000000000000000000000000000000000000000000000000000000000000000001100000000000000000000000000000000000000000000000000000 -
1$
1)
#116
0$
0)
#117
b111010 /
b10000000000000000000000000000000000000000000000000000000000000000000000000000000000000000000000000000000000000000000000000000000000000000000000000000000000000000000000000000011000000000000000000000000000000000000000000000000000000 -
1$
1)
#118
0$
0)
#119
b111011 /
b100000000000000000000000000000000000000000000000000000000000000000000000000000000000000000000000000000000000000000000000000000000000000000000000000000000000000000000000000000110000000000000000000000000000000000000000000000000000000 -
1$
1)
#120
0$
0)
#121
b111100 /
b1000000000000000000000000000000000000000000000000000000000000000000000000000000000000000000000000000000000000000000000000000000000000000000000000000000000000000000000000000001100000000000000000000000000000000000000000000000000000000 -
1$
1)
#122
0$
0)
#123
b111101 /
b10000000000000000000000000000000000000000000000000000000000000000000000000000000000000000000000000000000000000000000000000000000000000000000000000000000000000000000000000000011000000000000000000000000000000000000000000000000000000000 -
1$
1)
#124
0$
0)
#125
b111110 /
b100000000000000000000000000000000000000000000000000000000000000000000000000000000000000000000000000000000000000000000000000000000000000000000000000000000000000000000000000000110000000000000000000000000000000000000000000000000000000000 -
1$
1)
#126
0$
0)
#127
b111111 /
b1000000000000000000000000000000000000000000000000000000000000000000000000000000000000000000000000000000000000000000000000000000000000000000000000000000000000000000000000000001100000000000000000000000000000000000000000000000000000000000 -
1$
1)
#128
0$
0)
#129
b1000000 /
b10000000000000000000000000000000000000000000000000000000000000000000000000000000000000000000000000000000000000000000000000000000000000000000000000000000000000000000000000000011000000000000000000000000000000000000000000000000000000000000 -
1$
1)
#130
0$
0)
#131
b1000001 /
b100000000000000000000000000000000000000000000000000000000000000000000000000000000000000000000000000000000000000000000000000000000000000000000000000000000000000000000000000000110000000000000000000000000000000000000000000000000000000000000 -
1$
1)
#132
0$
0)
#133
b1000010 /
b1000000000000000000000000000000000000000000000000000000000000000000000000000000000000000000000000000000000000000000000000000000000000000000000000000000000000000000000000000001100000000000000000000000000000000000000000000000000000000000000 -
1$
1)
#134
0$
0)
#135
b1000011 /
b10000000000000000000000000000000000000000000000000000000000000000000000000000000000000000000000000000000000000000000000000000000000000000000000000000000000000000000000000000011000000000000000000000000000000000000000000000000000000000000000 -
1$
1)
#136
0$
0)
#137
b1000100 /
b100000000000000000000000000000000000000000000000000000000000000000000000000000000000000000000000000000000000000000000000000000000000000000000000000000000000000000000000000000110000000000000000000000000000000000000000000000000000000000000000 -
1$
1)
#138
0$
0)
#139
b1000101 /
b1000000000000000000000000000000000000000000000000000000000000000000000000000000000000000000000000000000000000000000000000000000000000000000000000001000000000000000000000000001100000000000000000000000000000000000000000000000000000000000000000 -
1$
1)
#140
0$
0)
#141
b1000110 /
b10000000000000000000000000000000000000000000000000000000000000000000000000000000000000000000000000000000000000000000000000000000000000000000000000011000000000000000000000000011000000000000000000000000000000000000000000000000000000000000000000 -
1$
1)
#142
0$
0)
#143
b1000111 /
b100000000000000000000000000000000000000000000000000000000000000000000000000000000000000000000000000000000000000000000000000000000000000000000000000110000000000000000000000000110000000000000000000000000000000000000000000000000000000000000000000 -
1$
1)
#144
0$
0)
#145
b1001000 /
b1000000000000000000000000000000000000000000000000000000000000000000000000000000000000000000000000000000000000000000000000000000000000000000000000001100000000000000000000000001100000000000000000000000000000000000000000000000000000000000000000000 -
1$
1)
#146
0$
0)
#147
b1001001 /
b10000000000000000000000000000000000000000000000000000000000000000000000000000000000000000000000000000000000000000000000000000000000000000000000000011000000000000000000000000011000000000000000000000000000000000000000000000000000000000000000000001 -
1$
1)
#148
0$
0)
#149
b1001010 /
b100000000000000000000000000000000000000000000000000000000000000000000000000000000000000000000000000000000000000000000000000000000000000000000000000110000000000000000000000000110000000000000000000000000000000000000000000000000000000000000000000010 -
1$
1)
#150
0$
0)
#151
b1001011 /
b1000000000000000000000000000000000000000000000000000000000000000000000000000000000000000000000000000000000000000000000000000000000000000000000000001100000000000000000000000001100000000000000000000000000000000000000000000000000000000000000000000100 -
1$
1)
#152
0$
0)
#153
b1001100 /
b10000000000000000000000000000000000000000000000000000000000000000000000000000000000000000000000000000000000000000000000000000000000000000000000000011000000000000000000000000011000000000000000000000000000000000000000000000000000000000000000000001000 -
1$
1)
#154
0$
0)
#155
b1001101 /
b100000000000000000000000000000000000000000000000000000000000000000000000000000000000000000000000000000000000000000000000000000000000000000000000000110000000000000000000000000110000000000000000000000000000000000000000000000000000000000000000000010000 -
1$
1)
#156
0$
0)
#157
b1001110 /
b1000000000000000000000000000000000000000000000000000000000000000000000000000000000000000000000000000000000000000000000000000000000000000000000000001100000000000000000000000001100000000000000000000000000000000000000000000000000000000000000000000100000 -
1$
1)
#158
0$
0)
#159
b1001111 /
b10000000000000000000000000000000000000000000000000000000000000000000000000000000000000000000000000000000000000000000000000000000000000000000000000011000000000000000000000000011000000000000000000000000000000000000000000000000000000000000000000001000000 -
1$
1)
#160
0$
0)
#161
b1010000 /
b100000000000000000000000000000000000000000000000000000000000000000000000000000000000000000000000000000000000000000000000000000000000000000000000000110000000000000000000000000110000000000000000000000000000000000000000000000000000000000000000000010000000 -
1$
1)
#162
0$
0)
#163
b1010001 /
b1000000000000000000000000000000000000000000000000000000000000000000000000000000000000000000000000000000000000000000000000000000000000000000000000001100000000000000000000000001100000000000000000000000000000000000000000000000000000000000000000000100000000 -
1$
1)
#164
0$
0)
#165
b1010010 /
b10000000000000000000000000000000000000000000000000000000000000000000000000000000000000000000000000000000000000000000000000000000000000000000000000011000000000000000000000000011000000000000000000000000000000000000000000000000000000000000000000001000000000 -
1$
1)
#166
0$
0)
#167
b1010011 /
b100000000000000000000000000000000000000000000000000000000000000000000000000000000000000000000000000000000000000000000000000000000000000000000000000110000000000000000000000000110000000000000000000000000000000000000000000000000000000000000000000010000000000 -
1$
1)
#168
0$
0)
#169
b1010100 /
b1000000000000000000000000000000000000000000000000000000000000000000000000000000000000000000000000000000000000000000000000000000000000000000000000001100000000000000000000000001100000000000000000000000000000000000000000000000000000000000000000000100000000000 -
1$
1)
#170
0$
0)
#171
b1010101 /
b10000000000000000000000000000000000000000000000000000000000000000000000000000000000000000000000000000000000000000000000000000000000000000000000000011000000000000000000000000011000000000000000000000000000000000000000000000000000000000000000000001000000000000 -
1$
1)
#172
0$
0)
#173
b1010110 /
b100000000000000000000000000000000000000000000000000000000000000000000000000000000000000000000000000000000000000000000000000000000000000000000000000110000000000000000000000000110000000000000000000000000000000000000000000000000000000000000000000010000000000000 -
1$
1)
#174
0$
0)
#175
b1010111 /
b1000000000000000000000000000000000000000000000000000000000000000000000000000000000000000000000000000000000000000000000000000000000000000000000000001100000000000000000000000001100000000000000000000000000000000000000000000000000000000000000000000100000000000000 -
1$
1)
#176
0$
0)
#177
b1011000 /
b10000000000000000000000000000000000000000000000000000000000000000000000000000000000000000000000000000000000000000000000000000000000000000000000000011000000000000000000000000011000000000000000000000000000000000000000000000000000000000000000000001000000000000000 -
1$
1)
#178
0$
0)
#179
b1011001 /
b100000000000000000000000000000000000000000000000000000000000000000000000000000000000000000000000000000000000000000000000000000000000000000000000000110000000000000000000000000110000000000000000000000000000000000000000000000000000000000000000000010000000000000000 -
1$
1)
#180
0$
0)
#181
b1011010 /
b1000000000000000000000000000000000000000000000000000000000000000000000000000000000000000000000000000000000000000000000000000000000000000000000000001100000000000000000000000001100000000000000000000000000000000000000000000000000000000000000000000100000000000000000 -
1$
1)
#182
0$
0)
#183
b1011011 /
b10000000000000000000000000000000000000000000000000000000000000000000000000000000000000000000000000000000000000000000000000000000000000000000000000011000000000000000000000000011000000000000000000000000000000000000000000000000000000000000000000001000000000000000000 -
1$
1)
#184
0$
0)
#185
b1011100 /
b100000000000000000000000000000000000000000000000000000000000000000000000000000000000000000000000000000000000000000000000000000000000000000000000000110000000000000000000000000110000000000000000000000000000000000000000000000000000000000000000000010000000000000000000 -
1$
1)
#186
0$
0)
#187
b1011101 /
b1000000000000000000000000000000000000000000000000000000000000000000000000000000000000001000000000000000000000000000000000000000000000000000000000001100000000000000000000000001100000000000000000000000000000000000000000000000000000000000000000000100000000000000000000 -
1$
1)
#188
0$
0)
#189
b1011110 /
b10000000000000000000000000000000000000000000000000000000000000000000000000000000000000010000000000000000000000000000000000000000000000000000000000011000000000000000000000000011000000000000000000000000000000000000000000000000000000000000000000001000000000000000000000 -
1$
1)
#190
0$
0)
#191
b1011111 /
b100000000000000000000000000000000000000000000000000000000000000000000000000000000000000100000000000000000000000000000000000000000000000000000000000110000000000000000000000001110000000000000000000000000000000000000000000000000000000000000000000010000000000000000000000 -
1$
1)
#192
0$
0)
#193
b1100000 /
b1000000000000000000000000000000000000000000000000000000000000000000000000000000000000001000000000000000000000000000000000000000000000000000000000001100000000000000000000000011100000000000000000000000000000000000000000000000000000000000000000000100000000000000000000000 -
1$
1)
#194
0$
0)
#195
b1100001 /
b10000000000000000000000000000000000000000000000000000000000000000000000000000000000000010000000000000000000000000000000000000000000000000000000000011000000000000000000000000111000000000000000000000000000000000000000000000000000000000000000000001000000000000000000000000 -
1$
1)
#196
0$
0)
#197
b1100010 /
b100000000000000000000000000000000000000000000000000000000000000000000000000000000000000100000000000000000000000000000000000000000000000000000000000110000000000000000000000001110000000000000000000000000000000000000000000000000000000000000000000010000000000000000000000000 -
1$
1)
#198
0$
0)
#199
b1100011 /
b1000000000000000000000000000000000000000000000000000000000000000000000000000000000000001000000000000000000000000000000000000000000000000000000000001100000000000000000000000011100000000000000000000000000000000000000000000000000000000000000000000100000000000000000000000000 -
1$
1)
#200
0$
0)
#201
b1100100 /
b10000000000000000000000000000000000000000000000000000000000000000000000000000000000000010000000000000000000000000000000000000000000000000000000000011000000000000000000000000111000000000000000000000000000000000000000000000000000000000000000000001000000000000000000000000000 -
1$
1)
#202
0$
0)
#203
b1100101 /
b100000000000000000000000000000000000000000000000000000000000000000000000000000000000000100000000000000000000000000000000000000000000000000000000000110000000000000000000000001110000000000000000000000000000000000000000000000000000000000000000000010000000000000000000000000000 -
1$
1)
#204
0$
0)
#205
b1100110 /
b1000000000000000000000000000000000000000000000000000000000000000000000000000000000000001000000000000000000000000000000000000000000000000000000000001100000000000000000000000011100000000000000000000000000000000000000000000000000000000000000000000100000000000000000000000000000 -
1$
1)
#206
0$
0)
#207
b1100111 /
b10000000000000000000000000000000000000000000000000000000000000000000000000000000000000010000000000000000000000000000000000000000000000000000000000011000000000000000000000000111000000000000000000000000000000000000000000000000000000000000000000001000000000000000000000000000000 -
1$
1)
#208
0$
0)
#209
b1101000 /
b100000000000000000000000000000000000000000000000000000000000000000000000000000000000000100000000000000000000000000000000000000000000000000000000000110000000000000000000000001110000000000000000000000000000000000000000000000000000000000000000000010000000000000000000000000000000 -
1$
1)
#210
0$
0)
#211
b1101001 /
b1000000000000000000000000000000000000000000000000000000000000000000000000000000000000001000000000000000000000000000000000000000000000000000000000001100000000000000000000000011100000000000000000000000000000000000000000000000000000000000000000000100000000000000000000000000000000 -
1$
1)
#212
0$
0)
#213
b1101010 /
b10000000000000000000000000000000000000000000000000000000000000000000000000000000000000010000000000000000000000000000000000000000000000000000000000011000000000000000000000000111000000000000000000000000000000000000000000000000000000000000000000001000000000000000000000000000000000 -
1$
1)
#214
0$
0)
#215
b1101011 /
b100000000000000000000000000000000000000000000000000000000000000000000000000000000000000100000000000000000000000000000000000000000000000000000000000110000000000000000000000001110000000000000000000000000000000000000000000000000000000000000000000010000000000000000000000000000000000 -
1$
1)
#216
0$
0)
#217
b1101100 /
b1000000000000000000000000000000000000000000000000000000000000000000000000000000000000001000000000000000000000000000000000000000000000000000000000001100000000000000000000000011100000000000000000000000000000000000000000000000000000000000000000000100000000000000000000000000000000000 -
1$
1)
#218
0$
0)
#219
b1101101 /
b10000000000000000000000000000000000000000000000000000000000000000000000000000000000000010000000000000000000000000000000000000000000000000000000000011000000000000000000000000111000000000000000000000000000000000000000000000000000000000000000000001000000000000000000000000000000000000 -
1$
1)
#220
0$
0)
#221
b1101110 /
b100000000000000000000000000000000000000000000000000000000000000000000000000000000000000100000000000000000000000000000000000000000000000000000000000110000000000000000000000001110000000000000000000000000000000000000000000000000000000000000000000010000000000000000000000000000000000000 -
1$
1)
#222
0$
0)
#223
b1101111 /
b1000000000000000000000000000000000000000000000000000000000000000000000000000000000000001000000000000000000000000000000000000000000000000000000000001100000000000000000000000011100000000000000000000000000000000000000000000000000000000000000000000100000000000000000000000000000000000000 -
1$
1)
#224
0$
0)
#225
b1110000 /
b10000000000000000000000000000000000000000000000000000000000000000000000000000000000000010000000000000000000000000000000000000000000000000000000000011000000000000000000000000111000000000000000000000000000000000000000000000000000000000000000000001000000000000000000000000000000000000000 -
1$
1)
#226
0$
0)
#227
b1110001 /
b100000000000000000000000000000000000000000000000000000000000000000000000000000000000000100000000000000000000000000000000000000000000000000000000000110000000000000000000000001110000000000000000000000000000000000000000000000000000000000000000000010000000000000000000000000000000000000000 -
1$
1)
#228
0$
0)
#229
b1110010 /
b1000000000000000000000000000000000000000000000000000000000000000000000000000000000000001000000000000000000000000000000000000000000000000000000000001100000000000000000000000011100000000000000000000000000000000000000000000000000000000000000000000100000000000000000000000000000000000000000 -
1$
1)
#230
0$
0)
#231
b1110011 /
b10000000000000000000000000000000000000000000000000000000000000000000000000000000000000010000000000000000000000000000000000000000000000000000000000011000000000000000000000000111000000000000000000000000000000000000000000000000000000000000000000001000000000000000000000000000000000000000000 -
1$
1)
#232
0$
0)
#233
b1110100 /
b100000000000000000000000000000000000000000000000000000000000000000000000000000000000000100000000000000000000000000000000000000000000000000000000000110000000000000000000000001110000000000000000000000000000000000000000000000000000000000000000000010000000000000000000000000000000000000000000 -
1$
1)
#234
0$
0)
#235
b1110101 /
b1000000000000000000000000000000000000000000000000000000000001100000000000000000000000011100000000000000000000000000000000000000000000000000000000000000000000100000000000000000000000000000000000000000001 -
1$
1)
#236
0$
0)
#237
b1110110 /
b10000000000000000000000000000000000000000000000000000000000011000000000000000000000000111000000000000000000000000000000000000000000000000000000000000000000001000000000000000000000000000000000000000000010 -
1$
1)
#238
0$
0)
#239
b1110111 /
b100000000000000000000000000000000000000000000000000000000000110000000000000000000000001110000000000000000000000000000000000000000000000000000000000000000000010000000000000000000000000000000000000000000100 -
1$
1)
#240
0$
0)
#241
b1111000 /
b1000000000000000000000000000000000000000000000000000000000001100000000000000000000000011100000000000000000000000000000000000000000000000000000000000000000000100000000000000000000000000000000000000000001000 -
1$
1)
#242
0$
0)
#243
b1111001 /
b10000000000000000000000000000000000000000000000000000000000011000000000000000000000000111000000000000000000000000000000000000000000000000000000000000000000001000000000000000000000000000000000000000000010000 -
1$
1)
#244
0$
0)
#245
b1111010 /
b100000000000000000000000000000000000000000000000000000000000110000000000000000000000001110000000000000000000000000000000000000000000000000000000000000000000010000000000000000000000000000000000000000000100000 -
1$
1)
#246
0$
0)
#247
b1111011 /
b1000000000000000000000000000000000000000000000000000000000001100000000000000000000000011100000000000000000000000000000000000000000000000000000000000000000000100000000000000000000000000000000000000000001000000 -
1$
1)
#248
0$
0)
#249
b1111100 /
b10000000000000000000000000000000000000000000000000000000000011000000000000000000000000111000000000000000000000000000000000000000000000000000000000000000000001000000000000000000000000000000000000000000010000000 -
1$
1)
#250
0$
0)
