Trivium/work/e_test.v
module ENCRIPT (KEY, IV, len, clk, reset, OUT);
input [79:0] KEY, IV;
input [11:0] len;
input clk, reset;
output [511:0] OUT;
wire [15:0] fst, max;
reg [15:0] count;
reg [287:0] SET;
reg [511:0] STRM, OUT;
reg t1, t2, t3;

assign fst = 4 * 288;
assign max = fst + len;

always @(posedge clk or negedge reset) begin
    if(!reset) begin
        if(count <= max) begin
            // if(count == 0) SET = {3'b111, 112'b0, IV, 13'b0, KEY};
            t1 = SET[65]  ^ SET[92];
            t2 = SET[161] ^ SET[176];
            t3 = SET[242] ^ SET[287];
            if(fst <= count) STRM[len - count + fst - 1] = t1 ^ t2 ^ t3;
            t1 = t1 ^ SET[90]  & SET[91]  ^ SET[170];
            t2 = t2 ^ SET[174] & SET[175] ^ SET[263];
            t3 = t3 ^ SET[285] & SET[286] ^ SET[68];
            SET[92:0]    = {SET[91:0], t3};
            SET[176:93]  = {SET[175:93], t1};
            SET[287:177] = {SET[286:177], t2};
            count = count + 1;
        end else OUT <= STRM;
    end else begin
        count <= 0;
        SET   <= {3'b111, 112'b0, IV, 13'b0, KEY};
    end
end

endmodule

Trivium/work/test_te.v
`timescale 1ns/1ns

module test;
    reg  [79:0] KEY;
    reg  [79:0] IV;
    reg [11:0] len;
    reg clk;
    reg reset;
    wire [511:0] OUT;
    parameter times = 0.5;
    always #(times)   clk = ~clk;

    ENCRIPT ENCRIPT (KEY, IV, len, clk, reset, OUT);
    // ENCRIPT ENCRIPT (KEY, IV, clk, reset, OUT);

    initial begin
// Set 2, vector# 16:
//                          key = 10101010101010101010
//                           IV = 00000000000000000000
//                stream[0..63] = 4567A95BDBA94E17A52438D060DC8EF8
//                                20A7DA9E51E6F1D67247D3807F41338E
//                                3F8DE39BEF9E04BB9EE9F952B411A007
//                                D2F0E295B255A831C264C47D1C078A2B
//             stream[192..255] = F5393FE158303A91214E77B9A76FE062
//                                FD25B7F186137F0D5673B3E3B53CA3CF
//                                2F8B823820EA9646B77D4DBC4A22EF52
//                                D1498698229EAFD28EA151BF581481B6
//             stream[256..319] = C934D399C84DD90EBB1274208437C97C
//                                BDB3C43F65469D131BAD9B49800A9186
//                                EC066A6291706A792398EACF43D97F94
//                                3033B0A1FF96CE8448E37260D740D36D
//             stream[448..511] = EF7226C691BC2EE81DC34FBEAB365944
//                                4A7C976A4894CCFC6D558E73B2FBF33A
//                                1DB9FAAB1D11DB6293D7AC126399057D
//                                C1711DD057FE13395F69D69D37614134
//                   xor-digest = AB585980991C6ACD1889A72ECF42D41E
//                                6BB1EC325FFAD62E7A8514AA87ADAB84
//                                873B44D96413F3AF9AE1A93C02F3E591
//                                E2C4320B3BEA6BE96B1A9337E81AF2B7
        clk = 1'b0;
        // KEY = 80'h80000000000000000000;
        // IV  = 80'h00000000000000000000;
        KEY = 80'h10101010101010101010;
        IV  = 80'h00000000000000000000;
        len = 512;
        reset = 1;
        repeat(2) @(negedge clk);
        reset = 0;
        while(reset) @(negedge clk);
        @(negedge clk);
        repeat(2000) @(negedge clk);
        $finish;
    end

    initial begin
        $dumpfile("trivium.vcd");
        $dumpvars(0, test);
    end

endmodule

Trivium/work/trivium.vcd
$date
	Fri Sep 18 01:53:00 2015
$end
$version
	Icarus Verilog
$end
$timescale
	1ns
$end
$scope module test $end
$var wire 512 ! OUT [511:0] $end
$var reg 80 " IV [79:0] $end
$var reg 80 # KEY [79:0] $end
$var reg 1 $ clk $end
$var reg 12 % len [11:0] $end
$var reg 1 & reset $end
$scope module ENCRIPT $end
$var wire 80 ' IV [79:0] $end
$var wire 80 ( KEY [79:0] $end
$var wire 1 ) clk $end
$var wire 16 * fst [15:0] $end
$var wire 12 + len [11:0] $end
$var wire 16 , max [15:0] $end
$var wire 1 - reset $end
$var reg 512 . OUT [511:0] $end
$var reg 288 / SET [287:0] $end
$var reg 512 0 STRM [511:0] $end
$var reg 16 1 count [15:0] $end
$var reg 1 2 t1 $end
$var reg 1 3 t2 $end
$var reg 1 4 t3 $end
$upscope $end
$upscope $end
$enddefinitions $end
#0
$dumpvars
x4
x3
x2
bx 1
bx 0
bx /
bx .
1-
b11010000000 ,
b1000000000 +
b10010000000 *
0)
b10000000100000001000000010000000100000001000000010000000100000001000000010000 (
b0 '
1&
b1000000000 %
0$
b10000000100000001000000010000000100000001000000010000000100000001000000010000 #
b0 "
bx !
$end
#1
b111000000000000000000000000000000000000000000000000000000000000000000000000000000000000000000000000000000000000000000000000000000000000000000000000000000000000000000000000000000000000000000000000000000000000000010000000100000001000000010000000100000001000000010000000100000001000000010000 /
b0 1
1$
1)
#2
0$
0)
#3
1$
1)
#4
b1 1
b110000000000000000000000000000000000000000000000000000000000000000000000000000000000000000000000000000000000000000000000000000000000000000000000000000000000000000000000000000000000000000000000000000000000000000100000001000000010000000100000001000000010000000100000001000000010000000100001 /
14
03
02
0&
0-
0$
0)
#5
b10 1
b100000000000000000000000000000000000000000000000000000000000000000000000000000000000000000000000000000000000000000000000000000000000000000000000000000000000000000000000000000000000000000000000000000000000000001000000010000000100000001000000010000000100000001000000010000000100000001000011 /
1$
1)
#6
0$
0)
#7
b11 1
b10000000100000001000000010000000100000001000000010000000100000001000000010000111 /
1$
1)
#8
0$
0)
#9
b100 1
b100000001000000010000000100000001000000010000000100000001000000010000000100001110 /
04
1$
1)
#10
0$
0)
#11
b101 1
b1000000010000000100000001000000010000000100000001000000010000000100000001000011100 /
1$
1)
#12
0$
0)
#13
b110 1
b1000000000010000000100000001000000010000000100000001000000010000000100000001000000010000111000 /
12
1$
1)
#14
0$
0)
#15
b111 1
b10000000000100000001000000010000000100000001000000010000000100000001000000010000000100001110000 /
02
1$
1)
#16
0$
0)
#17
b1000 1
b100000000001000000010000000100000001000000010000000100000001000000010000000100000001000011100000 /
1$
1)
#18
0$
0)
#19
b1001 1
b1000000000010000000100000001000000010000000100000001000000010000000100000001000000010000111000001 /
14
1$
1)
#20
0$
0)
#21
b1010 1
b10000000000100000001000000010000000100000001000000010000000100000001000000010000000100001110000010 /
04
1$
1)
#22
0$
0)
#23
b1011 1
b100000000001000000010000000100000001000000010000000100000001000000010000000100000001000011100000100 /
1$
1)
#24
0$
0)
#25
b1100 1
b1000000000010000000100000001000000010000000100000001000000010000000100000001000000010000111000001000 /
1$
1)
#26
0$
0)
#27
b1101 1
b10000000000100000001000000010000000100000001000000010000000100000001000000010000000100001110000010000 /
1$
1)
#28
0$
0)
#29
b1110 1
b100000001001000000010000000100000001000000010000000100000001000000010000000100000001000011100000100000 /
12
1$
1)
#30
0$
0)
#31
b1111 1
b1000000010010000000100000001000000010000000100000001000000010000000100000001000000010000111000001000000 /
02
1$
1)
#32
0$
0)
#33
b10000 1
b10000000100100000001000000010000000100000001000000010000000100000001000000010000000100001110000010000000 /
1$
1)
#34
0$
0)
#35
b10001 1
b100000001001000000010000000100000001000000010000000100000001000000010000000100000001000011100000100000001 /
14
12
1$
1)
#36
0$
0)
#37
b10010 1
b1000000010010000000100000001000000010000000100000001000000010000000100000001000000010000111000001000000010 /
04
02
1$
1)
#38
0$
0)
#39
b10011 1
b10000000100100000001000000010000000100000001000000010000000100000001000000010000000100001110000010000000100 /
1$
1)
#40
0$
0)
#41
b10100 1
b100000001001000000010000000100000001000000010000000100000001000000010000000100000001000011100000100000001000 /
1$
1)
#42
0$
0)
#43
b10101 1
b1000000010010000000100000001000000010000000100000001000000010000000100000001000000010000111000001000000010000 /
1$
1)
#44
0$
0)
#45
b10110 1
b10000000100100001001000000010000000100000001000000010000000100000001000000010000000100001110000010000000100000 /
12
1$
1)
#46
0$
0)
#47
b10111 1
b100000001001000010010000000100000001000000010000000100000001000000010000000100000001000011100000100000001000000 /
02
1$
1)
#48
0$
0)
#49
b11000 1
b1000000010010000100100000001000000010000000100000001000000010000000100000001000000010000111000001000000010000000 /
1$
1)
#50
0$
0)
#51
b11001 1
b10000000100100001001000000010000000100000001000000010000000100000001000000010000000100001110000010000000100000001 /
14
12
1$
1)
#52
0$
0)
#53
b11010 1
b100000001001000010010000000100000001000000010000000100000001000000010000000100000001000011100000100000001000000010 /
04
02
1$
1)
#54
0$
0)
#55
b11011 1
b1000000010010000100100000001000000010000000100000001000000010000000100000001000000010000111000001000000010000000100 /
1$
1)
#56
0$
0)
#57
b11100 1
b10000000100100001001000000010000000100000001000000010000000100000001000000010000000100001110000010000000100000001000 /
1$
1)
#58
0$
0)
#59
b11101 1
b100000001001000010010000000100000001000000010000000100000001000000010000000100000001000011100000100000001000000010000 /
1$
1)
#60
0$
0)
#61
b11110 1
b1000000010010000100100001001000000010000000100000001000000010000000100000001000000010000111000001000000010000000100000 /
12
1$
1)
#62
0$
0)
#63
b11111 1
b10000000100100001001000010010000000100000001000000010000000100000001000000010000000100001110000010000000100000001000000 /
02
1$
1)
#64
0$
0)
#65
b100000 1
b100000001001000010010000100100000001000000010000000100000001000000010000000100000001000011100000100000001000000010000000 /
1$
1)
#66
0$
0)
#67
b100001 1
b1000000010010000100100001001000000010000000100000001000000010000000100000001000000010000111000001000000010000000100000001 /
14
12
1$
1)
#68
0$
0)
#69
b100010 1
b10000000100100001001000010010000000100000001000000010000000100000001000000010000000100001110000010000000100000001000000010 /
04
02
1$
1)
#70
0$
0)
#71
b100011 1
b100000001001000010010000100100000001000000010000000100000001000000010000000100000001000011100000100000001000000010000000100 /
1$
1)
#72
0$
0)
#73
b100100 1
b1000000010010000100100001001000000010000000100000001000000010000000100000001000000010000111000001000000010000000100000001000 /
1$
1)
#74
0$
0)
#75
b100101 1
b10000000100100001001000010010000000100000001000000010000000100000001000000010000000100001110000010000000100000001000000010000 /
1$
1)
#76
0$
0)
#77
b100110 1
b100000001001000010010000100100001001000000010000000100000001000000010000000100000001000011100000100000001000000010000000100000 /
12
1$
1)
#78
0$
0)
#79
b100111 1
b1000000010010000100100001001000010010000000100000001000000010000000100000001000000010000111000001000000010000000100000001000000 /
02
1$
1)
#80
0$
0)
#81
b101000 1
b10000000100100001001000010010000100100000001000000010000000100000001000000010000000100001110000010000000100000001000000010000000 /
1$
1)
#82
0$
0)
#83
b101001 1
b100000001001000010010000100100001001000000010000000100000001000000010000000100000001000011100000100000001000000010000000100000001 /
14
12
1$
1)
#84
0$
0)
#85
b101010 1
b1000000010010000100100001001000010010000000100000001000000010000000100000001000000010000111000001000000010000000100000001000000010 /
04
02
1$
1)
#86
0$
0)
#87
b101011 1
b10000000100100001001000010010000100100000001000000010000000100000001000000010000000100001110000010000000100000001000000010000000100 /
1$
1)
#88
0$
0)
#89
b101100 1
b100000001001000010010000100100001001000000010000000100000001000000010000000100000001000011100000100000001000000010000000100000001000 /
1$
1)
#90
0$
0)
#91
b101101 1
b1000000010010000100100001001000010010000000100000001000000010000000100000001000000010000111000001000000010000000100000001000000010000 /
1$
1)
#92
0$
0)
#93
b101110 1
b10000000100100001001000010010000100100001001000000010000000100000001000000010000000100001110000010000000100000001000000010000000100000 /
12
1$
1)
#94
0$
0)
#95
b101111 1
b100000001001000010010000100100001001000010010000000100000001000000010000000100000001000011100000100000001000000010000000100000001000000 /
02
1$
1)
#96
0$
0)
#97
b110000 1
b1000000010010000100100001001000010010000100100000001000000010000000100000001000000010000111000001000000010000000100000001000000010000000 /
1$
1)
#98
0$
0)
#99
b110001 1
b10000000100100001001000010010000100100001001000000010000000100000001000000010000000100001110000010000000100000001000000010000000100000001 /
14
12
1$
1)
#100
0$
0)
#101
b110010 1
b100000001001000010010000100100001001000010010000000100000001000000010000000100000001000011100000100000001000000010000000100000001000000010 /
04
02
1$
1)
#102
0$
0)
#103
b110011 1
b1000000010010000100100001001000010010000100100000001000000010000000100000001000000010000111000001000000010000000100000001000000010000000100 /
1$
1)
#104
0$
0)
#105
b110100 1
b10000000100100001001000010010000100100001001000000010000000100000001000000010000000100001110000010000000100000001000000010000000100000001000 /
1$
1)
#106
0$
0)
#107
b110101 1
b100000001001000010010000100100001001000010010000000100000001000000010000000100000001000011100000100000001000000010000000100000001000000010000 /
1$
1)
#108
0$
0)
#109
b110110 1
b1000000010010000100100001001000010010000100100001001000000010000000100000001000000010000111000001000000010000000100000001000000010000000100000 /
12
1$
1)
#110
0$
0)
#111
b110111 1
b10000000100100001001000010010000100100001001000010010000000100000001000000010000000100001110000010000000100000001000000010000000100000001000000 /
02
1$
1)
#112
0$
0)
#113
b111000 1
b100000001001000010010000100100001001000010010000100100000001000000010000000100000001000011100000100000001000000010000000100000001000000010000000 /
1$
1)
#114
0$
0)
#115
b111001 1
b1000000010010000100100001001000010010000100100001001000000010000000100000001000000010000111000001000000010000000100000001000000010000000100000001 /
14
12
1$
1)
#116
0$
0)
#117
b111010 1
b10000000100100001001000010010000100100001001000010010000000100000001000000010000000100001110000010000000100000001000000010000000100000001000000010 /
04
02
1$
1)
#118
0$
0)
#119
b111011 1
b100000001001000010010000100100001001000010010000100100000001000000010000000100000001000011100000100000001000000010000000100000001000000010000000100 /
1$
1)
#120
0$
0)
#121
b111100 1
b1000000010010000100100001001000010010000100100001001000000010000000100000001000000010000111000001000000010000000100000001000000010000000100000001000 /
1$
1)
#122
0$
0)
#123
b111101 1
b10000000100100001001000010010000100100001001000010010000000100000001000000010000000100001110000010000000100000001000000010000000100000001000000010000 /
1$
1)
#124
0$
0)
#125
b111110 1
b100000001001000010010000100100001001000010010000100100001001000000010000000100000001000011100000100000001000000010000000100000001000000010000000100000 /
12
1$
1)
#126
0$
0)
#127
b111111 1
b1000000010010000100100001001000010010000100100001001000010010000000100000001000000010000111000001000000010000000100000001000000010000000100000001000000 /
02
1$
1)
#128
0$
0)
#129
b1000000 1
b10000000100100001001000010010000100100001001000010010000100100000001000000010000000100001110000010000000100000001000000010000000100000001000000010000000 /
1$
1)
#130
0$
0)
#131
b1000001 1
b100000001001000010010000100100001001000010010000100100001001000000010000000100000001000011100000100000001000000010000000100000001000000010000000100000001 /
14
12
1$
1)
#132
0$
0)
#133
b1000010 1
b1000000010010000100100001001000010010000100100001001000010010000000100000001000000010000111000001000000010000000100000001000000010000000100000001000000010 /
04
02
1$
1)
#134
0$
0)
#135
b1000011 1
b10000000100100001001000010010000100100001001000010010000100101000001000000010000000100001110000010000000100000001000000010000000100000001000000010000000100 /
12
1$
1)
#136
0$
0)
#137
b1000100 1
b100000001001000010010000100100001001000010010000100100001001011000010000000100000001000011100000100000001000000010000000100000001000000010000000100000001000 /
1$
1)
#138
0$
0)
#139
b1000101 1
b1000000010010000100100001001000010010000100100001001000010010111000100000001000000010000111000001000000010000000100000001000000010000000100000001000000010000 /
1$
1)
#140
0$
0)
#141
b1000110 1
b10000000100100001001000010010000100100001001000010010000100101110001000000010000000100001110000010000000100000001000000010000000100000001000000010000000100001 /
14
02
1$
1)
#142
0$
0)
#143
b1000111 1
b100000001001000010010000100100001001000010010000100100001001011100010000000100000001000011100000100000001000000010000000100000001000000010000000100000001000011 /
14
1$
1)
#144
0$
0)
#145
b1001000 1
b1000000010010000100100001001000010010000100100001001000010010111000100000001000000010000111000001000000010000000100000001000000010000000100000001000000010000111 /
14
1$
1)
#146
0$
0)
#147
b1001001 1
b10000000100100001001000010010000100100001001000010010000100101110001000000010000000100001110000010000000100000001000000010000000100000001000000010000000100001110 /
04
12
1$
1)
#148
0$
0)
#149
b1001010 1
b100000001001000010010000100100001001000010010000100100001001011100010000000100000001000011100000100000001000000010000000100000001000000010000000100000001000011100 /
02
1$
1)
#150
0$
0)
#151
b1001011 1
b1000000000000001000000010010000100100001001000010010000100100001001000010010111000101000001000000010000111000001000000010000000100000001000000010000000100000001000000010000111000 /
13
12
1$
1)
#152
0$
0)
#153
b1001100 1
b10000000000000010000000100100001001000010010000100100001001000010010000100101110001010000010000000100001110000010000000100000001000000010000000100000001000000010000000100001110000 /
03
02
1$
1)
#154
0$
0)
#155
b1001101 1
b100000000000000100000001001000010010000100100001001000010010000100100001001011100010100000100000001000011100000100000001000000010000000100000001000000010000000100000001000011100000 /
1$
1)
#156
0$
0)
#157
b1001110 1
b1000000000000001000000010010000100100001001000010010000100100001001000010010111000101000001000000010000111000001000000010000000100000001000000010000000100000001000000010000111000001 /
14
1$
1)
#158
0$
0)
#159
b1001111 1
b10000000000000010000000100100001001000010010000100100001001000010010000100101110001010000010000000100001110000010000000100000001000000010000000100000001000000010000000100001110000010 /
04
1$
1)
#160
0$
0)
#161
b1010000 1
b100000000000000100000001001000010010000100100001001000010010000100100001001011100010100000100000001000011100000100000001000000010000000100000001000000010000000100000001000011100000100 /
1$
1)
#162
0$
0)
#163
b1010001 1
b1000000000000001000000010010000100100001001000010010000100100001001000010010111000101000001000000010000111000001000000010000000100000001000000010000000100000001000000010000111000001000 /
12
1$
1)
#164
0$
0)
#165
b1010010 1
b10000000000000010000000100100001001000010010000100100001001000010010000100101110001010000010000000100001110000010000000100000001000000010000000100000001000000010000000100001110000010000 /
02
1$
1)
#166
0$
0)
#167
b1010011 1
b100000001000000100000001001000010010000100100001001000010010000100100001001011100010100000101000001000011100000100000001000000010000000100000001000000010000000100000001000011100000100000 /
13
12
1$
1)
#168
0$
0)
#169
b1010100 1
b1000000010000001000000010010000100100001001000010010000100100001001000010010111000101000001011000010000111000001000000010000000100000001000000010000000100000001000000010000111000001000000 /
03
12
1$
1)
#170
0$
0)
#171
b1010101 1
b10000000100000010000000100100001001000010010000100100001001000010010000100101110001010000010110000100001110000010000000100000001000000010000000100000001000000010000000100001110000010000000 /
02
1$
1)
#172
0$
0)
#173
b1010110 1
b100000001001000100000001001000010010000100100001001000010010000100100001001011100010100000101100001000011100000100000001000000010000000100000001000000010000000100000001000011100000100000001 /
14
13
1$
1)
#174
0$
0)
#175
b1010111 1
b1000000010010001000000010010000100100001001000010010000100100001001000010010111000101000001011000010000111000001000000010000000100000001000000010000000100000001000000010000111000001000000010 /
04
03
1$
1)
#176
0$
0)
#177
b1011000 1
b10000000100100010000000100100001001000010010000100100001001000010010000100101110001010000010110000100001110000010000000100000001000000010000000100000001000000010000000100001110000010000000100 /
1$
1)
#178
0$
0)
#179
b1011001 1
b100000001001000100000001001000010010000100100001001000010010000100100001001011100010100000101100001000011100000100000001000000010000000100000001000000010000000100000001000011100000100000001000 /
12
1$
1)
#180
0$
0)
#181
b1011010 1
b1000000010010001000000010010000100100001001000010010000100100001001000010010111000101000001011000010000111000001000000010000000100000001000000010000000100000001000000010000111000001000000010000 /
13
02
1$
1)
#182
0$
0)
#183
b1011011 1
b10000000100100011000000100100001001000010010000100100001001000010010000100101110001010000010110000101001110000010000000100000001000000010000000100000001000000010000000100001110000010000000100000 /
12
1$
1)
#184
0$
0)
#185
b1011100 1
b100000001001000110000001001000010010000100100001001000010010000100100001001011100010100000101100001011011100000100000001000000010000000100000001000000010000000100000001000011100000100000001000000 /
03
12
1$
1)
#186
0$
0)
#187
b1011101 1
b1000000010010001100000010010000100100001001000010010000100100001001000010010111000101000001011000010111111000001000000010000000100000001000000010000000100000001000000010000111000001000000010000000 /
12
1$
1)
#188
0$
0)
#189
b1011110 1
b10000000100100011001000100100001001000010010000100100001001000010010000100101110001010000010110000101110110000010000000100000001000000010000000100000001000000010000000100001110000010000000100000001 /
14
02
13
1$
1)
#190
0$
0)
#191
b1011111 1
b100000001001000110010001001000010010000100100001001000010010000100100001001011100010100000101100001011100100000100000001000000010000000100000001000000010000000100000001000011100000100000001000000010 /
04
03
02
1$
1)
#192
0$
0)
#193
b1100000 1
b1000000010010001100100010010000100100001001000010010000100100001001000010010111000101000001011000010111001000001000000010000000100000001000000010000000100000001000000010000111000001000000010000000100 /
12
1$
1)
#194
0$
0)
#195
b1100001 1
b10000000100100011001000100100001001000010010000100100001001000010010000100101110001010000010110000101110010000010000000100000001000000010000000100000001000000010000000100001110000010000000100000001000 /
02
1$
1)
#196
0$
0)
#197
b1100010 1
b100000001001000110010001001000010010000100100001001000010010000100100001001011100010100000101100001011100100000100000001000000010000000100000001000000010000000100000001000011100000100000001000000010000 /
13
1$
1)
#198
0$
0)
#199
b1100011 1
b1000000010010001100100011010000100100001001000010010000100100001001000010010111000101000001011000010111001001001000000010000000100000001000000010000000100000001000000010000111000001000000010000000100000 /
12
1$
1)
#200
0$
0)
#201
b1100100 1
b10000000100100011001000110100001001000010010000100100001001000010010000100101110001010000010110000101110010011010000000100000001000000010000000100000001000000010000000100001110000010000000100000001000000 /
03
12
1$
1)
#202
0$
0)
#203
b1100101 1
b100000001001000110010001101000010010000100100001001000010010000100100001001011100010100000101100001011100100110100000001000000010000000100000001000000010000000100000001000011100000100000001000000010000000 /
13
02
1$
1)
#204
0$
0)
#205
b1100110 1
b1000000010010001100100011011000100100001001000010010000100100001001000010010111000101000001011000010111001001101000000010000000100000001000000010000000100000001000000010000111000001000000010000000100000001 /
14
12
1$
1)
#206
0$
0)
#207
b1100111 1
b10000000100100011001000110110001001000010010000100100001001000010010000100101110001010000010110000101110010011011000000100000001000000010000000100000001000000010000000100001110000010000000100000001000000010 /
04
03
12
1$
1)
#208
0$
0)
#209
b1101000 1
b100000001001000110010001101100010010000100100001001000010010000100100001001011100010100000101100001011100100110110000001000000010000000100000001000000010000000100000001000011100000100000001000000010000000100 /
02
1$
1)
#210
0$
0)
#211
b1101001 1
b1000000010010001100100011011000100100001001000010010000100100001001000010010111000101000001011000010111001001101100000010000000100000001000000010000000100000001000000010000111000001000000010000000100000001000 /
1$
1)
#212
0$
0)
#213
b1101010 1
b10000000100100011001000110110001001000010010000100100001001000010010000100101110001010000010110000101110010011011000000100000001000000010000000100000001000000010000000100001110000010000000100000001000000010000 /
13
1$
1)
#214
0$
0)
#215
b1101011 1
b100000001001000110010001101100011010000100100001001000010010000100100001001011100010100000101100001011100100110110001001000000010000000100000001000000010000000100000001000011100000100000001000000010000000100000 /
12
1$
1)
#216
0$
0)
#217
b1101100 1
b1000000010010001100100011011000110100001001000010010000100100001001000010010111000101000001011000010111001001101100011010000000100000001000000010000000100000001000000010000111000001000000010000000100000001000000 /
03
12
1$
1)
#218
0$
0)
#219
b1101101 1
b10000000100100011001000110110001101000010010000100100001001000010010000100101110001010000010110000101110010011011000110100000001000000010000000100000001000000010000000100001110000010000000100000001000000010000000 /
13
02
1$
1)
#220
0$
0)
#221
b1101110 1
b100000001001000110010001101100011011000100100001001000010010000100100001001011100010100000101100001011100100110110001101000000010000000100000001000000010000000100000001000011100000100000001000000010000000100000001 /
14
12
1$
1)
#222
0$
0)
#223
b1101111 1
b1000000010010001100100011011000110110001001000010010000100100001001000010010111000101000001011000010111001001101100011011000000100000001000000010000000100000001000000010000111000001000000010000000100000001000000010 /
04
03
12
1$
1)
#224
0$
0)
#225
b1110000 1
b10000000100100011001000110110001101100010010000100100001001000010010000100101110001010000010110000101110010011011000110110000001000000010000000100000001000000010000000100001110000010000000100000001000000010000000100 /
02
1$
1)
#226
0$
0)
#227
b1110001 1
b100000001001000110010001101100011011000100100001001000010010000100100001001011100010100000101100001011100100110110001101100000010000000100000001000000010000000100000001000011100000100000001000000010000000100000001000 /
1$
1)
#228
0$
0)
#229
b1110010 1
b1000000010010001100100011011000110110001001000010010000100100001001000010010111000101000001011000010111001001101100011011000000100000001000000010000000100000001000000010000111000001000000010000000100000001000000010000 /
13
1$
1)
#230
0$
0)
#231
b1110011 1
b10000000100100011001000110110001101100011010000100100001001000010010000100101110001010000010110000101110010011011000110110001001000000010000000100000001000000010000000100001110000010000000100000001000000010000000100000 /
12
1$
1)
#232
0$
0)
#233
b1110100 1
b100000001001000110010001101100011011000110100001001000010010000100100001001011100010100000101100001011100100110110001101100011010000000100000001000000010000000100000001000011100000100000001000000010000000100000001000000 /
03
12
1$
1)
#234
0$
0)
#235
b1110101 1
b1000000010010001100100011011000110110001101000010010000100100001001000010010111000101000001011000010111001001101100011011000110100000001000000010000000100000001000000010000111000001000000010000000100000001000000010000000 /
13
02
1$
1)
#236
0$
0)
#237
b1110110 1
b10000000100100011001000110110001101100011011000100100001001000010010000100101110001010000010110000101110010011011000110110001101000000010000000100000001000000010000000100001110000010000000100000001000000010000000100000001 /
14
12
1$
1)
#238
0$
0)
#239
b1110111 1
b100000001001000110010001101100011011000110110001001000010010000100100001001011100010100000101100001011100100110110001101100011011000000100000001000000010000000100000001000011100000100000001000000010000000100000001000000010 /
04
03
12
1$
1)
#240
0$
0)
#241
b1111000 1
b1000000010010001100100011011000110110001101100010010000100100001001000010010111000101000001011000010111001001101100011011000110110000001000000010000000100000001000000010000111000001000000010000000100000001000000010000000100 /
02
1$
1)
#242
0$
0)
#243
b1111001 1
b10000000100100011001000110110001101100011011000100100001001000010010000100101110001010000010110000101110010011011000110110001101100000010000000100000001000000010000000100001110000010000000100000001000000010000000100000001000 /
1$
1)
#244
0$
0)
#245
b1111010 1
b100000001001000110010001101100011011000110110001001000010010000100100001001011100010100000101100001011100100110110001101100011011000000100000001000000010000000100000001000011100000100000001000000010000000100000001000000010000 /
13
1$
1)
#246
0$
0)
#247
b1111011 1
b1000000010010001100100011011000110110001101100011010000100100001001000010010111000101000001011000010111001001101100011011000110110001001000000010000000100000001000000010000111000001000000010000000100000001000000010000000100000 /
12
1$
1)
#248
0$
0)
#249
b1111100 1
b10000000100100011001000110110001101100011011000110100001001000010010000100101110001010000010110000101110010011011000110110001101100011010000000100000001000000010000000100001110000010000000100000001000000010000000100000001000000 /
03
12
1$
1)
#250
0$
0)
#251
b1111101 1
b100000001001000110010001101100011011000110110001101000010010000100100001001011100010100000101100001011100100110110001101100011011000110100000001000000010000000100000001000011100000100000001000000010000000100000001000000010000000 /
13
02
1$
1)
#252
0$
0)
#253
b1111110 1
b1000000010010001100100011011000110110001101100011011000100100001001000010010111000101000001011000010111001001101100011011000110110001101000000010000000100000001000000010000111000001000000010000000100000001000000010000000100000001 /
14
12
1$
1)
#254
0$
0)
#255
b1111111 1
b10000000100100011001000110110001101100011011000110110001001000010010000100101110001010000010110000101110010011011000110110001101100011011000000100000001000000010000000100001110000010000000100000001000000010000000100000001000000010 /
04
03
12
1$
1)
#256
0$
0)
#257
b10000000 1
b100000001001000110010001101100011011000110110001101100010010000100100001001011100010100000101100001011100100110110001101100011011000110110000001000000010000000100000001000011100000100000001000000010000000100000001000000010000000100 /
02
1$
1)
#258
0$
0)
#259
b10000001 1
b1000000010010001100100011011000110110001101100011011000100100001001000010010111000101000001011000010111001001101100011011000110110001101100000010000000100000001000000010000111000001000000010000000100000001000000010000000100000001000 /
1$
1)
#260
0$
0)
#261
b10000010 1
b10000000100100011001000110110001101100011011000110110001001000010010000100101110001010000010110000101110010011011000110110001101100011011000000100000001000000010000000100001110000010000000100000001000000010000000100000001000000010000 /
13
1$
1)
#262
0$
0)
#263
b10000011 1
b100000001001000110010001101100011011000110110001101100011010000100100001001011100010100000101100001011100100110110001101100011011000110110001001000000010000000100000001000011100000100000001000000010000000100000001000000010000000100000 /
12
1$
1)
#264
0$
0)
#265
b10000100 1
b1000000010010001100100011011000110110001101100011011000110100001001000010010111000101000001011000010111001001101100011011000110110001101100011010000000100000001000000010000111000001000000010000000100000001000000010000000100000001000000 /
03
12
1$
1)
#266
0$
0)
#267
b10000101 1
b10000000100100011001000110110001101100011011000110110001101000010010000100101110001010000010110000101110010011011000110110001101100011011000110100000001000000010000000100001110000010000000100000001000000010000000100000001000000010000000 /
13
02
1$
1)
#268
0$
0)
#269
b10000110 1
b100000001001000110010001101100011011000110110001101100011011000100100001001011100010100000101100001011100100110110001101100011011000110110001101000000010000000100000001000011100000100000001000000010000000100000001000000010000000100000001 /
14
12
1$
1)
#270
0$
0)
#271
b10000111 1
b1000000010010001100100011011000110110001101100011011000110110001001000010010111000101000001011000010111001001101100011011000110110001101100011011000000100000001000000010000111000001000000010000000100000001000000010000000100000001000000010 /
04
03
12
1$
1)
#272
0$
0)
#273
b10001000 1
b10000000100100011001000110110001101100011011000110110001101101010010000100101110001010000010110000101110010011011000110110001101100011011000110111000001000000010000000100001110000010000000100000001000000010000000100000001000000010000000100 /
13
1$
1)
#274
0$
0)
#275
b10001001 1
b100000001001000110010001101100011011000110110001101100011011011100100001001011100010100000101100001011100100110110001101100011011000110110001101111000010000000100000001000011100000100000001000000010000000100000001000000010000000100000001000 /
1$
1)
#276
0$
0)
#277
b10001010 1
b1000000010010001100100011011000110110001101100011011000110110110001000010010111000101000001011000010111001001101100011011000110110001101100011011111000100000001000000010000111000001000000010000000100000001000000010000000100000001000000010000 /
03
1$
1)
#278
0$
0)
#279
b10001011 1
b10000000100100011001000110110001101100011011000110110001101101100010000100101110001010000010110000101110010011011000110110001101100011011000110111110001000000010000000100001110000010000000100000001000000010000000100000001000000010000000100001 /
14
02
1$
1)
#280
0$
0)
#281
b10001100 1
b100000001001000110010001101100011011000110110001101100011011011000100001001011100010100000101100001011100100110110001101100011011000110110001101111101010000000100000001000011100000100000001000000010000000100000001000000010000000100000001000011 /
12
14
1$
1)
#282
0$
0)
#283
b10001101 1
b1000000010010001100100011011000110110001101100011011000110110110001000010010111000101000001011000010111001001101100011011000110110001101100011011111010100000001000000010000111000001000000010000000100000001000000010000000100000001000000010000110 /
04
13
02
1$
1)
#284
0$
0)
#285
b10001110 1
b10000000100100011001000110110001101100011011000110110001101101100011000100101110001010000010110000101110010011011000110110001101100011011000110111110101000000010000000100001110000010000000100000001000000010000000100000001000000010000000100001100 /
12
1$
1)
#286
0$
0)
#287
b10001111 1
b100000001001000110010001101100011011000110110001101100011011011000110001001011100010100000101100001011100100110110001101100011011000110110001101111101011000000100000001000011100000100000001000000010000000100000001000000010000000100000001000011000 /
03
12
1$
1)
#288
0$
0)
#289
b10010000 1
b1000000010010001100100011011000110110001101100011011000110110110001101010010111000101000001011000010111001001101100011011000110110001101100011011111010111000001000000010000111000001000000010000000100000001000000010000000100000001000000010000110000 /
13
1$
1)
#290
0$
0)
