HMAC/SHA256/SHA256.v
//******************************************************************
//* Designer     : 
//* E-Mail       : 
//* Dept         : 
//*
//* Version      : 0.1
//* Created      : June/09/2010
//* Last Updated : June/09/2010
//*
//* File Name    : SHA256.v
//******************************************************************
`timescale 1ns / 1ps

// Standard
`define SHA256_H0 32'h6a09e667
`define SHA256_H1 32'hbb67ae85
`define SHA256_H2 32'h3c6ef372
`define SHA256_H3 32'ha54ff53a
`define SHA256_H4 32'h510e527f
`define SHA256_H5 32'h9b05688c
`define SHA256_H6 32'h1f83d9ab
`define SHA256_H7 32'h5be0cd19

//---------------------------------------------
// MAIN_LOOP : main loop
//---------------------------------------------
//module SHA_CORE (t, Hinit, Hena, ABCena, Wout, clk, en, Hout);
module SHA_CORE ( clk, en, Hinit, Hena, ABCena, MSGin, Wena, MSGsel, t, Hout );
  input          clk;
  input          en;
  input          Hinit;   // Initialize H registers with constants
  input          Hena;    // Enable to load data in H regsters when en = '1'
  input          ABCena;  // Enable to load data in a-h regsters when en = '1'
  input   [31:0] MSGin;
  input          Wena;
  input          MSGsel;
  input    [5:0] t;       // integer range 0 to 63;
  output [255:0] Hout;

  wire    [31:0] sigma0;  // ROTR2(x) + ROTR13(x) + ROTR22(x)
  wire    [31:0] sigma1;  // ROTR6(x) + ROTR11(x) + ROTR25(x)
  wire    [31:0] MJ, CHF;
  wire    [31:0] Kt;
  reg     [31:0] H0, H1, H2, H3, H4, H5, H6, H7;
  reg     [31:0] a, b, c, d, e, f, g, h;
  wire    [31:0] ain, ein;

  reg     [31:0] w[15:0];
  wire    [31:0] del0;    // Delta 0 : ROTR7(x)  + ROTR18(x) + SHR3(x)
  wire    [31:0] del1;    // Delta 1 : ROTR17(x) + ROTR19(x) + SHR10(x)
  wire    [31:0] wt;
  wire    [31:0] Wout;

  integer i;

  function [31:0] Kj;
  input     [5:0] t;
    case ( t )
      // Standard
      0  : Kj = 32'h428a2f98;
      1  : Kj = 32'h71374491;
      2  : Kj = 32'hb5c0fbcf;
      3  : Kj = 32'he9b5dba5;
      4  : Kj = 32'h3956c25b;
      5  : Kj = 32'h59f111f1;
      6  : Kj = 32'h923f82a4;
      7  : Kj = 32'hab1c5ed5;
      8  : Kj = 32'hd807aa98;
      9  : Kj = 32'h12835b01;
      10 : Kj = 32'h243185be;
      11 : Kj = 32'h550c7dc3;
      12 : Kj = 32'h72be5d74;
      13 : Kj = 32'h80deb1fe;
      14 : Kj = 32'h9bdc06a7;
      15 : Kj = 32'hc19bf174;
      16 : Kj = 32'he49b69c1;
      17 : Kj = 32'hefbe4786;
      18 : Kj = 32'h0fc19dc6;
      19 : Kj = 32'h240ca1cc;
      20 : Kj = 32'h2de92c6f;
      21 : Kj = 32'h4a7484aa;
      22 : Kj = 32'h5cb0a9dc;
      23 : Kj = 32'h76f988da;
      24 : Kj = 32'h983e5152;
      25 : Kj = 32'ha831c66d;
      26 : Kj = 32'hb00327c8;
      27 : Kj = 32'hbf597fc7;
      28 : Kj = 32'hc6e00bf3;
      29 : Kj = 32'hd5a79147;
      30 : Kj = 32'h06ca6351;
      31 : Kj = 32'h14292967;
      32 : Kj = 32'h27b70a85;
      33 : Kj = 32'h2e1b2138;
      34 : Kj = 32'h4d2c6dfc;
      35 : Kj = 32'h53380d13;
      36 : Kj = 32'h650a7354;
      37 : Kj = 32'h766a0abb;
      38 : Kj = 32'h81c2c92e;
      39 : Kj = 32'h92722c85;
      40 : Kj = 32'ha2bfe8a1;
      41 : Kj = 32'ha81a664b;
      42 : Kj = 32'hc24b8b70;
      43 : Kj = 32'hc76c51a3;
      44 : Kj = 32'hd192e819;
      45 : Kj = 32'hd6990624;
      46 : Kj = 32'hf40e3585;
      47 : Kj = 32'h106aa070;
      48 : Kj = 32'h19a4c116;
      49 : Kj = 32'h1e376c08;
      50 : Kj = 32'h2748774c;
      51 : Kj = 32'h34b0bcb5;
      52 : Kj = 32'h391c0cb3;
      53 : Kj = 32'h4ed8aa4a;
      54 : Kj = 32'h5b9cca4f;
      55 : Kj = 32'h682e6ff3;
      56 : Kj = 32'h748f82ee;
      57 : Kj = 32'h78a5636f;
      58 : Kj = 32'h84c87814;
      59 : Kj = 32'h8cc70208;
      60 : Kj = 32'h90befffa;
      61 : Kj = 32'ha4506ceb;
      62 : Kj = 32'hbef9a3f7;
      63 : Kj = 32'hc67178f2;
    endcase
  endfunction

  assign sigma0 = { a[1:0], a[31:2] } ^ { a[12:0], a[31:13] } ^ { a[21:0], a[31:22] };
  assign sigma1 = { e[5:0], e[31:6] } ^ { e[10:0], e[31:11] } ^ { e[24:0], e[31:25] };

  assign MJ  = ( a & b ) | ( a & c ) | ( b & c ); // Maj|ity
  assign CHF = ( e & f ) | ( ~e & g );            // Ch & f
  assign Kt  = Kj( t );  
  assign ain = h + CHF + sigma1 + Kt + Wout + MJ + sigma0;
  assign ein = h + CHF + sigma1 + Kt + Wout + d;

  assign Hout = { H0, H1, H2, H3, H4, H5, H6, H7 };

  always @( posedge clk ) begin
    if ( en == 1 ) begin
      if ( Hinit == 1'b1 ) begin
        a <= `SHA256_H0;
        b <= `SHA256_H1;
        c <= `SHA256_H2;
        d <= `SHA256_H3;
        e <= `SHA256_H4;
        f <= `SHA256_H5;
        g <= `SHA256_H6;
        h <= `SHA256_H7;

        H0 <= `SHA256_H0;
        H1 <= `SHA256_H1;
        H2 <= `SHA256_H2;
        H3 <= `SHA256_H3;
        H4 <= `SHA256_H4;
        H5 <= `SHA256_H5;
        H6 <= `SHA256_H6;
        H7 <= `SHA256_H7;
      end
      else if ( Hena == 1'b1 ) begin
        a <= h + H7;
        b <= a;
        c <= b;
        d <= c;
        e <= d;
        f <= e;
        g <= f;
        h <= g;

        H0 <= h + H7;
        H1 <= H0;
        H2 <= H1;
        H3 <= H2;
        H4 <= H3;
        H5 <= H4;
        H6 <= H5;
        H7 <= H6;
      end
      else if ( ABCena == 1'b1 ) begin
        a <= ain;
        b <= a;
        c <= b;
        d <= c;
        e <= ein;
        f <= e;
        g <= f;
        h <= g;

        H0 <= H0;
        H1 <= H1;
        H2 <= H2;
        H3 <= H3;
        H4 <= H4;
        H5 <= H5;
        H6 <= H6;
        H7 <= H7;
      end
    end
  end

  assign del0 = { w[1][6:0], w[1][31:7] } ^ { w[1][17:0], w[1][31:18] } ^ { 3'b000, w[1][31:3] };
  assign del1 = { w[14][16:0], w[14][31:17] } ^ { w[14][18:0], w[14][31:19] } ^ { 10'b0000000000, w[14][31:10] };
  assign wt   = del0 + w[0][31:0] + del1 + w[9][31:0];

  always @( posedge clk ) begin
    if (( en & Wena ) == 1 ) begin
      w[15] <= ( MSGsel == 1'b0 )? MSGin : wt;
      for ( i=0; i<15; i=i+1 ) w[i] <= w[i+1];
    end
  end

  assign Wout = w[15];

endmodule


// ==================================================================================================
// SHA256 : Secure Hash Function SHA-256
// ==================================================================================================
module SHA256( RSTn, CLK, EN, INIT, MSGin, Mrdy, Hout, Hvld, LED_out, Busy );
  input              RSTn;  // Reset
  input              CLK;   // System clock

  input              EN;    // Enable
  input              INIT;  // Initialize
  input       [31:0] MSGin; // Message input
  input              Mrdy;  // Message input is ready
  output     [255:0] Hout;  // Hash value output
  output reg         Hvld;  // Hash value output raedy
  output reg         LED_out;
  output reg         Busy;  // Hash unit busy
  

  parameter [2:0] SHA_WAIT = 0, SHA_INIT = 1, MSG_WAIT = 2, MSG_IN = 3, SHA_GEN = 4, HADD_ST = 5;

  reg          [2:0] sha_state;   // State machine register
  reg          [3:0] mcnt;        // Message counter
  reg          [5:0] t;           // integer range 0 to 80;
  reg                Hinit, Hena, ABCena;
  wire               Wena;        // 'W' register enable
  reg                MSGsel;
  //reg                led1;
  
  function [31:0] MSG_in;
  input     [5:0] mcnt;
    case ( mcnt )
      0  : MSG_in = 32'h61626380;
      1  : MSG_in = 32'h00000000;
      2  : MSG_in = 32'h00000000;
      3  : MSG_in = 32'h00000000;
      4  : MSG_in = 32'h00000000;
      5  : MSG_in = 32'h00000000;
      6  : MSG_in = 32'h00000000;
      7  : MSG_in = 32'h00000000;
      8  : MSG_in = 32'h00000000;
      9  : MSG_in = 32'h00000000;
      10 : MSG_in = 32'h00000000;
      11 : MSG_in = 32'h00000000;
      12 : MSG_in = 32'h00000000;
      13 : MSG_in = 32'h00000000;
      14 : MSG_in = 32'h00000000;
      15 : MSG_in = 32'h00000018;
		default : MSG_in = 32'h00000000;
    endcase
  endfunction
  //assign Kt  = Kj( t );  
  //assign MSGin = MSG_in(mcnt);
  
  SHA_CORE G0( .clk( CLK ), .en( EN ), .Hinit( Hinit ), .Hena( Hena ), .ABCena( ABCena ),
               .MSGin( MSG_in(mcnt) ), .Wena( Wena ), .MSGsel( MSGsel ), .t( t ), .Hout( Hout )
             );

  assign Wena = (( sha_state == MSG_WAIT ) && ( Mrdy == 1 ))? 1 : 0
              ||(( sha_state == MSG_IN   ) && ( Mrdy == 1 ))? 1 : 0
              || ( sha_state == SHA_GEN )? 1 : 0;
  
  always @( posedge CLK or negedge RSTn ) begin
    if ( RSTn == 1'b0 ) begin
      Hinit   <= 1'b0;
      Hena    <= 1'b0;
      ABCena  <= 1'b0;
      MSGsel  <= 1'b0;
      Hvld    <= 1'b0;
      Busy    <= 1'b0;
      mcnt    <= 4'h0;
      t       <= 6'h00;
      sha_state <= SHA_WAIT;
	   LED_out <= 1'b0;
    end
    else if ( EN == 1'b1 ) begin
      case ( sha_state )
        SHA_WAIT: begin
                    Hinit     <= 1'b1;
                    Hena      <= 1'b0;
                    ABCena    <= 1'b0;
                    sha_state <= SHA_INIT;
                  end
        SHA_INIT: begin     // H and a-h registers initialize
                    Hinit     <= 1'b0;
                    Hena      <= 1'b0;
                    ABCena    <= 1'b0;
                    MSGsel    <= 1'b0;
                    mcnt      <= 4'h0;
                    t         <= 6'h00;
                    sha_state <= MSG_WAIT;
                  end

        MSG_WAIT: begin       // Message input wait
		              if ( INIT == 1'b1 ) sha_state <= SHA_WAIT;
                    else if ( Mrdy == 1'b1 ) begin
                      ABCena    <= 1'b1;
                      mcnt      <= mcnt + 1;
                      sha_state <= MSG_IN;
                    end
                    else sha_state <= MSG_WAIT;
                  end

        MSG_IN  : begin       // 16-word message input
                    if ( Mrdy == 1'b1 ) begin
                      if ( mcnt == 15 ) begin
                        MSGsel    <= 1'b1;
                        Busy      <= 1'b1;
                        sha_state <= SHA_GEN;
                      end

                      ABCena <= 1'b1;
                      mcnt   <= mcnt + 1;
                      t      <= t + 1;
                    end
                    else ABCena <= 1'b0;

                    Hinit  <= 1'b0;
                    Hena   <= 1'b0;
                    Hvld   <= 1'b0;
                  end

        SHA_GEN : begin
                    if ( t == 6'd63 ) begin
                      Hinit     <= 1'b0;
                      Hena      <= 1'b1;
                      ABCena    <= 1'b1;
                      mcnt      <= 4'h0;
                      t         <= 6'h00;
                      sha_state <= HADD_ST;
							 //led1      <= 1'b1;
							 //if
							 if(Hout == 512'hba7816bf8f01cfea414140de5dae2223b00361a396177a9cb410ff61f20015ad)begin
							    //LED_out <= led1;
								 LED_out <= 1'b1;
							 end
                    end
                    else begin
                      mcnt <= 0;
                      t  <= t + 1;
                      sha_state <= SHA_GEN;
                    end
                  end

        HADD_ST : begin
                    if ( mcnt == 4'h7 ) begin
                      Hinit     <= 1'b0;
                      Hena      <= 1'b0;
                      Hvld      <= 1'b1;
                      Busy      <= 1'b0;
                      ABCena    <= 1'b0;
                      MSGsel    <= 1'b0;
                      t         <= 6'h00;
                      sha_state <= MSG_WAIT;
                    end
                    else begin
                      mcnt <= mcnt + 1;
                      sha_state <= HADD_ST;
                    end
                  end
      endcase
    end
  end

endmodule

HMAC/SHA256/SHA256_TB.v
//******************************************************************************//* Designer     : Akashi Satoh
//* E-Mail       : akashi.satoh@aist.go.jp
//* Version      : 0.1
//* Created      : June/09/2007
//* Updated      : June/09/2007
//*
//* File Name    : SHA256_TB.v
//******************************************************************************
`timescale 1ns/1ns

module SHA256_TB;

parameter CLOCK = 10;

reg         RSTn;
reg         CLK;
reg         EN;
reg         INIT;
reg  [31:0] MSGin;
reg         Mrdy;
wire [255:0] Hout;
wire        Hvld;

reg  [31:0] W[0:15];
wire        LED_out;

SHA256 C2( RSTn, CLK, EN, INIT, MSGin, Mrdy, Hout, Hvld, LED_out, Busy ); 

initial W[ 0] = 32'h61626380;
initial W[ 1] = 32'h00000000;
initial W[ 2] = 32'h00000000;
initial W[ 3] = 32'h00000000;
initial W[ 4] = 32'h00000000;
initial W[ 5] = 32'h00000000;
initial W[ 6] = 32'h00000000;
initial W[ 7] = 32'h00000000;
initial W[ 8] = 32'h00000000;
initial W[ 9] = 32'h00000000;
initial W[10] = 32'h00000000;
initial W[11] = 32'h00000000;
initial W[12] = 32'h00000000;
initial W[13] = 32'h00000000;
initial W[14] = 32'h00000000;
initial W[15] = 32'h00000018;

initial CLK  = 0;
  always #(CLOCK/2)
    CLK <= ~CLK;

initial begin

// Data Initialize and Sequencer Reset
  RSTn  <= 0;
  EN    <= 0;
  INIT  <= 0;
  MSGin <= 0;
  Mrdy  <= 0;
#(CLOCK*5)  RSTn <= 1;

#(CLOCK/5)
#(CLOCK)    EN     <= 1;

// 1st 32-bit*16 block
#(CLOCK*10) MSGin  <= W[0]; Mrdy <= 1;
#(CLOCK)    MSGin  <= W[1];// Mrdy <= 0;
//#(CLOCK)    Mrdy <= 1;
#(CLOCK*14) MSGin  <= W[15];
#(CLOCK)    Mrdy <= 0;
#(CLOCK*56)
#(CLOCK*14)

// 2nd 32-bit*16 block
            MSGin  <= W[0];  Mrdy <= 1;
#(CLOCK)    MSGin  <= W[15]; Mrdy <= 0;
#(CLOCK)                     Mrdy <= 1;
#(CLOCK*15) MSGin  <= W[15];
#(CLOCK)                     Mrdy <= 0;
#(CLOCK*6000)

$stop;
end
initial begin  
    $dumpfile("sha.vcd");  
    $dumpvars(0, SHA256_TB);  
end
endmodule

HMAC/SHA256/sha.vcd
$date
	Fri Jan 27 15:53:57 2017
$end
$version
	Icarus Verilog
$end
$timescale
	1ps
$end
$scope module SHA256_TB $end
$var wire 1 ! LED_out $end
$var wire 1 " Hvld $end
$var wire 256 # Hout [255:0] $end
$var wire 1 $ Busy $end
$var reg 1 % CLK $end
$var reg 1 & EN $end
$var reg 1 ' INIT $end
$var reg 32 ( MSGin [31:0] $end
$var reg 1 ) Mrdy $end
$var reg 1 * RSTn $end
$scope module C2 $end
$var wire 1 % CLK $end
$var wire 1 & EN $end
$var wire 1 ' INIT $end
$var wire 32 + MSGin [31:0] $end
$var wire 1 ) Mrdy $end
$var wire 1 * RSTn $end
$var wire 1 , Wena $end
$var wire 256 - Hout [255:0] $end
$var reg 1 . ABCena $end
$var reg 1 $ Busy $end
$var reg 1 / Hena $end
$var reg 1 0 Hinit $end
$var reg 1 " Hvld $end
$var reg 1 ! LED_out $end
$var reg 1 1 MSGsel $end
$var reg 4 2 mcnt [3:0] $end
$var reg 3 3 sha_state [2:0] $end
$var reg 6 4 t [5:0] $end
$scope function MSG_in $end
$var reg 32 5 MSG_in [31:0] $end
$var reg 6 6 mcnt [5:0] $end
$upscope $end
$scope module G0 $end
$var wire 1 . ABCena $end
$var wire 32 7 CHF [31:0] $end
$var wire 1 / Hena $end
$var wire 1 0 Hinit $end
$var wire 32 8 MJ [31:0] $end
$var wire 32 9 MSGin [31:0] $end
$var wire 1 1 MSGsel $end
$var wire 1 , Wena $end
$var wire 32 : Wout [31:0] $end
$var wire 1 % clk $end
$var wire 32 ; del0 [31:0] $end
$var wire 32 < del1 [31:0] $end
$var wire 1 & en $end
$var wire 32 = sigma0 [31:0] $end
$var wire 32 > sigma1 [31:0] $end
$var wire 6 ? t [5:0] $end
$var wire 32 @ wt [31:0] $end
$var wire 32 A ein [31:0] $end
$var wire 32 B ain [31:0] $end
$var wire 32 C Kt [31:0] $end
$var wire 256 D Hout [255:0] $end
$var reg 32 E H0 [31:0] $end
$var reg 32 F H1 [31:0] $end
$var reg 32 G H2 [31:0] $end
$var reg 32 H H3 [31:0] $end
$var reg 32 I H4 [31:0] $end
$var reg 32 J H5 [31:0] $end
$var reg 32 K H6 [31:0] $end
$var reg 32 L H7 [31:0] $end
$var reg 32 M a [31:0] $end
$var reg 32 N b [31:0] $end
$var reg 32 O c [31:0] $end
$var reg 32 P d [31:0] $end
$var reg 32 Q e [31:0] $end
$var reg 32 R f [31:0] $end
$var reg 32 S g [31:0] $end
$var reg 32 T h [31:0] $end
$var integer 32 U i [31:0] $end
$scope function Kj $end
$var reg 32 V Kj [31:0] $end
$var reg 6 W t [5:0] $end
$upscope $end
$upscope $end
$upscope $end
$upscope $end
$enddefinitions $end
#0
$dumpvars
b0 W
b1000010100010100010111110011000 V
bx U
bx T
bx S
bx R
bx Q
bx P
bx O
bx N
bx M
bx L
bx K
bx J
bx I
bx H
bx G
bx F
bx E
bx D
b1000010100010100010111110011000 C
bx B
bx A
bx @
b0 ?
bx >
bx =
bx <
bx ;
bx :
b1100001011000100110001110000000 9
bx 8
bx 7
b0 6
b1100001011000100110001110000000 5
b0 4
b0 3
b0 2
01
00
0/
0.
bx -
0,
b0 +
0*
0)
b0 (
0'
0&
0%
0$
bx #
0"
0!
$end
#5000
1%
#10000
0%
#15000
1%
#20000
0%
#25000
1%
#30000
0%
#35000
1%
#40000
0%
#45000
1%
#50000
0%
1*
#55000
1%
#60000
0%
#62000
1&
#65000
b1 3
10
1%
#70000
0%
#75000
b110101100001110010011100101011 >
b11001110001000001011010001111110 =
b11111100001011100100110001100 7
b111010011011111110011001100111 8
b1011011111000001100110100011001 L
b11111100000111101100110101011 K
b10011011000001010110100010001100 J
b1010001000011100101001001111111 I
b10100101010011111111010100111010 H
b111100011011101111001101110010 G
b10111011011001111010111010000101 F
b110101000001001111001100110011110111011011001111010111010000101001111000110111011110011011100101010010101001111111101010011101001010001000011100101001001111111100110110000010101101000100011000001111110000011110110011010101101011011111000001100110100011001 #
b110101000001001111001100110011110111011011001111010111010000101001111000110111011110011011100101010010101001111111101010011101001010001000011100101001001111111100110110000010101101000100011000001111110000011110110011010101101011011111000001100110100011001 -
b110101000001001111001100110011110111011011001111010111010000101001111000110111011110011011100101010010101001111111101010011101001010001000011100101001001111111100110110000010101101000100011000001111110000011110110011010101101011011111000001100110100011001 D
b1101010000010011110011001100111 E
b1011011111000001100110100011001 T
b11111100000111101100110101011 S
b10011011000001010110100010001100 R
b1010001000011100101001001111111 Q
b10100101010011111111010100111010 P
b111100011011101111001101110010 O
b10111011011001111010111010000101 N
b1101010000010011110011001100111 M
b10 3
00
1%
#80000
0%
#85000
1%
#90000
0%
#95000
1%
#100000
0%
#105000
1%
#110000
0%
#115000
1%
#120000
0%
#125000
1%
#130000
0%
#135000
1%
#140000
0%
#145000
1%
#150000
0%
#155000
1%
#160000
0%
#162000
1,
1)
b1100001011000100110001110000000 (
b1100001011000100110001110000000 +
#165000
1,
b0 9
b0 5
b1 6
b1011101011010101110101111001101 B
b11111010001010100100011000100010 A
b1100001011000100110001110000000 :
b11 3
b1 2
1.
b1111 U
1%
#170000
0%
#172000
b0 (
b0 +
#175000
b1111101101010000110010000000101 <
b1011010100101001111110100101101 >
b1010001000011110110101010101110 7
b1111011011010111110111011000101 8
b10100010100111110110010011010001 =
b1110001001101110100010010010001 C
b1110001001101110100010010010001 V
b1 W
b10 6
b0 :
b1011010011010101101100110101101 B
b11111100000111101100110101011 T
b10011011000001010110100010001100 S
b1010001000011100101001001111111 R
b11111010001010100100011000100010 Q
b1111000110011100111100110001001 A
b111100011011101111001101110010 P
b10111011011001111010111010000101 O
b1101010000010011110011001100111 N
b1011101011010101110101111001101 M
b1 4
b1 ?
b10 2
b1111 U
1%
#180000
0%
#185000
b1110011111100001110010010010101 >
b1111001000010100100001001110110 7
b1011010011010101110101111101101 8
b110000100101101101000001010100 =
b0 <
b10110101110000001111101111001111 C
b10110101110000001111101111001111 V
b10 W
b11 6
b11001000110000110100011110100111 B
b10011011000001010110100010001100 T
b1010001000011100101001001111111 S
b11111010001010100100011000100010 R
b1111000110011100111100110001001 Q
b11111001001010010011100111101011 A
b10111011011001111010111010000101 P
b1101010000010011110011001100111 O
b1011101011010101110101111001101 N
b1011010011010101101100110101101 M
b10 4
b10 ?
b11 2
b1111 U
1%
#190000
0%
#195000
b110000001110111010000111100 >
b1111010000010100111111110001001 7
b1011000011010101100101110101101 8
b11000010000100000000100011010000 =
b11101001101101011101101110100101 C
b11101001101101011101101110100101 V
b11 W
b100 6
b11010101010100001111011001100110 B
b1010001000011100101001001111111 T
b11111010001010100100011000100010 S
b1111000110011100111100110001001 R
b11111001001010010011100111101011 Q
b100100111000000000100001010000 A
b1101010000010011110011001100111 P
b1011101011010101110101111001101 O
b1011010011010101101100110101101 N
b11001000110000110100011110100111 M
b11 4
b11 ?
b100 2
b1111 U
1%
#200000
0%
#205000
b111010100100110011010000110010 >
b1111000001011100111100111001001 7
b11011000010000101101011110100111 8
b1000101101110110000110001001011 =
b111001010101101100001001011011 C
b111001010101101100001001011011 V
b100 W
b101 6
b100010000001001101001101010 B
b11111010001010100100011000100010 T
b1111000110011100111100110001001 S
b11111001001010010011100111101011 R
b100100111000000000100001010000 Q
b1000011101011011010001001000101 A
b1011101011010101110101111001101 P
b1011010011010101101100110101101 O
b11001000110000110100011110100111 N
b11010101010100001111011001100110 M
b100 4
b100 ?
b101 2
b1111 U
1%
#210000
0%
#215000
b10001011011101111110000110011100 >
b10111000101000000001100111101010 7
b11000100010000001101011001100110 8
b1010000001010011010110010001111 =
b1011001111100010001000111110001 C
b1011001111100010001000111110001 V
b101 W
b110 6
b101011010000100000100111110101 B
b1111000110011100111100110001001 T
b11111001001010010011100111101011 S
b100100111000000000100001010000 R
b1000011101011011010001001000101 Q
b1110001010000100110000010101101 A
b1011010011010101101100110101101 P
b11001000110000110100011110100111 O
b11010101010100001111011001100110 N
b100010000001001101001101010 M
b101 4
b101 ?
b110 2
b1111 U
1%
#220000
0%
#225000
b1010110110111011101110110 >
b1000101101000000010100001010101 7
b101010000001001101001100110 8
b1101010111100000110011000000 =
b10010010001111111000001010100100 C
b10010010001111111000001010100100 V
b110 W
b111 6
b11100101000000110000001110000000 B
b11111001001010010011100111101011 T
b100100111000000000100001010000 S
b1000011101011011010001001000101 R
b1110001010000100110000010101101 Q
b10011011001001111010010000000001 A
b11001000110000110100011110100111 P
b11010101010100001111011001100110 O
b100010000001001101001101010 N
b101011010000100000100111110101 M
b110 4
b110 ?
b111 2
b1111 U
1%
#230000
0%
#235000
b10101100011011111101010101001 >
b1010001100010100010001001000101 7
b100101010000100000101111100000 8
b101001010010011110101101101100 =
b10101011000111000101111011010101 C
b10101011000111000101111011010101 V
b111 W
b1000 6
b10000101101000000111101101011111 B
b100100111000000000100001010000 T
b1000011101011011010001001000101 S
b1110001010000100110000010101101 R
b10011011001001111010010000000001 Q
b1100011001010111101001111001 A
b11010101010100001111011001100110 P
b100010000001001101001101010 O
b101011010000100000100111110101 N
b11100101000000110000001110000000 M
b111 4
b111 ?
b1000 2
b1111 U
1%
#240000
0%
#245000
b10011001101011010010010111000000 >
b1111001001001110010000010000101 7
b10100101000000100000101111010101 8
b10111010011110010100110111000010 =
b11011000000001111010101010011000 C
b11011000000001111010101010011000 V
b1000 W
b1001 6
b10001110000001001110110010111001 B
b1000011101011011010001001000101 T
b1110001010000100110000010101101 S
b10011011001001111010010000000001 R
b1100011001010111101001111001 Q
b110010110010100010110110001100 A
b100010000001001101001101010 P
b101011010000100000100111110101 O
b11100101000000110000001110000000 N
b10000101101000000111101101011111 M
b1000 4
b1000 ?
b1001 2
b1111 U
1%
#250000
0%
#255000
b11100100010110111011011111101010 >
b10001001011001011010100000001001 7
b10000101000000000110101110011001 8
b10101111111111010110100110001 =
b10010100000110101101100000001 C
b10010100000110101101100000001 V
b1001 W
b1010 6
b10001100100001110011010001101011 B
b1110001010000100110000010101101 T
b10011011001001111010010000000001 S
b1100011001010111101001111001 R
b110010110010100010110110001100 Q
b11100110010010010010110010110 A
b101011010000100000100111110101 P
b11100101000000110000001110000000 O
b10000101101000000111101101011111 N
b10001110000001001110110010111001 M
b1001 4
b1001 ?
b1010 2
b1111 U
1%
#260000
0%
#265000
b10001110001000100111011010111100 >
b10000111011000111111111101101 7
b10001100100001000111110001111011 8
b1011100101011000000011100010001 =
b100100001100011000010110111110 C
b100100001100011000010110111110 V
b1010 W
b1011 6
b1000111100110001010001111110100 B
b10011011001001111010010000000001 T
b1100011001010111101001111001 S
b110010110010100010110110001100 R
b11100110010010010010110010110 Q
b1000011011010110010001111101000 A
b11100101000000110000001110000000 P
b10000101101000000111101101011111 O
b10001110000001001110110010111001 N
b10001100100001110011010001101011 M
b1010 4
b1010 ?
b1011 2
b1111 U
1%
#270000
0%
#275000
b1101001100101000011010111001010 >
b110000110010010010110110000100 7
b10001110100001001010010011111001 8
b1101100110010111100010100100110 =
b1010101000011000111110111000011 C
b1010101000011000111110111000011 V
b1011 W
b1100 6
b11110111000111111100010110101001 B
b1100011001010111101001111001 T
b110010110010100010110110001100 S
b11100110010010010010110010110 R
b1000011011010110010001111101000 Q
b10000001011011111101011011101001 A
b10000101101000000111101101011111 P
b10001110000001001110110010111001 O
b10001100100001110011010001101011 N
b1000111100110001010001111110100 M
b1011 4
b1011 ?
b1100 2
b1111 U
1%
#280000
0%
#285000
b11001100110111101110011001100001 >
b11101111010110010001111111110 7
b11000111100111111010010111101001 8
b101111100111101110111001001000 =
b1110010101111100101110101110100 C
b1110010101111100101110101110100 V
b1100 W
b1101 6
b10000111100100010010100110010000 B
b110010110010100010110110001100 T
b11100110010010010010110010110 S
b1000011011010110010001111101000 R
b10000001011011111101011011101001 Q
b11110010101111000001000011000 A
b10001110000001001110110010111001 P
b10001100100001110011010001101011 O
b1000111100110001010001111110100 N
b11110111000111111100010110101001 M
b1100 4
b1100 ?
b1101 2
b1111 U
1%
#290000
0%
#295000
b1000101110111001100011110111 >
b1000001011011111010001111101000 7
b11000111100110011010000110110000 8
b101001110001100011010011110011 =
b10000000110111101011000111111110 C
b10000000110111101011000111111110 V
b1101 W
b1110 6
b11011001001100101110101100010110 B
b11100110010010010010110010110 T
b1000011011010110010001111101000 S
b10000001011011111101011011101001 R
b11110010101111000001000011000 Q
b1110100010110100100100011011110 A
b10001100100001110011010001101011 P
b1000111100110001010001111110100 O
b11110111000111111100010110101001 N
b10000111100100010010100110010000 M
b1101 4
b1101 ?
b1110 2
b1111 U
1%
#300000
0%
#305000
b10010100000011101001000011101111 ;
b1001111001110111000110101010000 >
b10010101011101111001011000111001 7
b11010111000100111110100110010000 8
b100101010101100010100000110110 =
b10011011110111000000011010100111 C
b10011011110111000000011010100111 V
b1110 W
b11000 9
b11000 5
b1111 6
b11000000011001000101111111011110 B
b1000011011010110010001111101000 T
b10000001011011111101011011101001 S
b11110010101111000001000011000 R
b1110100010110100100100011011110 Q
b1011100100101111001000001100 A
b1000111100110001010001111110100 P
b11110111000111111100010110101001 O
b10000111100100010010100110010000 N
b11011001001100101110101100010110 M
b1110 4
b1110 ?
b1111 2
b1111 U
1%
#310000
0%
#312000
b11000 (
b11000 +
#315000
b0 ;
b10111000110101100011111110010011 >
b10100010101110100000000011100 7
b11000001001100000110101110010110 8
b11011111100100000110111111010100 =
b11000001100110111111000101110100 C
b11000001100110111111000101110100 V
b1111 W
b1100001011000100110001110000000 9
b1100001011000100110001110000000 5
b0 6
b1100001011000100110001110000000 @
b11000 :
b10110000111110100010001110001110 B
b10000001011011111101011011101001 T
b11110010101111000001000011000 S
b1110100010110100100100011011110 R
b1011100100101111001000001100 Q
b111010110010000110111001101 A
b11110111000111111100010110101001 P
b10000111100100010010100110010000 O
b11011001001100101110101100010110 N
b11000000011001000101111111011110 M
b1111 4
b1111 ?
b0 2
b100 3
1$
11
b1111 U
1%
#320000
0%
#322000
0)
#325000
b11110000000000000000 <
b100001001110110110100110010101 >
b1110011000100100100000000011110 7
b11010000011100100110101110011110 8
b1011000110001010011010111110001 =
b11100100100110110110100111000001 C
b11100100100110110110100111000001 V
b10000 W
b11110010101111000001000011000 T
b1110100010110100100100011011110 S
b1011100100101111001000001100 R
b111010110010000110111001101 Q
b10000111100100010010100110010000 P
b11011001001100101110101100010110 O
b11000000011001000101111111011110 N
b10110000111110100010001110001110 M
b11110000000000000000 @
b100001110110101001101010011011 B
b10000000001101000010001010011100 A
b1100001011000100110001110000000 :
b10000 4
b10000 ?
b1111 U
1%
#330000
0%
#335000
b1111101101010000110010000000101 @
b1111101101010000110010000000101 <
b111011100000011001100001001110 >
b1011100100101101000010001100 7
b10100000111110100001101110011110 8
b1110110110001011100010011110101 =
b11101111101111100100011110000110 C
b11101111101111100100011110000110 V
b10001 W
b11110000000000000000 :
b11000010111110111101100111010001 B
b1110100010110100100100011011110 T
b1011100100101111001000001100 S
b111010110010000110111001101 R
b10000000001101000010001010011100 Q
b10000100011011101110010001010100 A
b11011001001100101110101100010110 P
b11000000011001000101111111011110 O
b10110000111110100010001110001110 N
b100001110110101001101010011011 M
b10001 4
b10001 ?
b1111 U
1%
#340000
0%
#345000
b11101111111100110001110000001111 >
b10000011001101010010100110011101 7
b10100000111110101001101110011011 8
b1010001010101111010011010100001 =
b1100000000000000000001111000110 @
b1100000000000000000001111000110 <
b1111110000011001110111000110 C
b1111110000011001110111000110 V
b10010 W
b1011100100101111001000001100 T
b111010110010000110111001101 S
b10000000001101000010001010011100 R
b10000100011011101110010001010100 Q
b11000000011001000101111111011110 P
b10110000111110100010001110001110 O
b100001110110101001101010011011 N
b11000010111110111101100111010001 M
b11111110011101110111101110111111 B
b11001100100010011001100101100001 A
b1111101101010000110010000000101 :
b10010 4
b10010 ?
b1111 U
1%
#350000
0%
