work/hoge.v
`define def_BUF     3'b000
`define def_AND_2   3'b001
`define def_OR_3    3'b010
`define def_NAND_2  3'b011
`define def_NOR_2   3'b100
`define def_NOT     3'b101
`define def_FIN     3'b111

module state (clk, res, cot, cs);
input clk, res;
output [7:0] cot;
output [2:0] cs;
reg [7:0] cot;
reg [2:0] cs;

always @(posedge clk or negedge res) begin
    if(res) begin
        cs  <= `def_BUF;
        cot <= 0;
    end else begin
        case (cs)
            `def_BUF:                   cs  <= `def_AND_2;
            `def_AND_2: if(cot > 8'h09) cs  <= `def_FIN;
                        else begin
                                        cs  <= `def_OR_3;
                                        cot <= cot + 8'h01;
                        end
            `def_OR_3:                  cs  <= `def_NAND_2;
            `def_NAND_2:                cs  <= `def_NOR_2;
            `def_NOR_2: if(cot >8'h08)  cs  <= `def_AND_2;
                        else            cs  <= `def_NOT;
            `def_NOT:                   cs  <= `def_AND_2;
            `def_FIN:                   cs  <= `def_FIN;
            default:                    cs  <= `def_FIN;
        endcase
    end
end
endmodule


module cal (IN1, IN2, IN3, cs, cot, OUT);
input IN1, IN2, IN3;
input [2:0] cs;
input [7:0] cot;
wire and_out, or_out, nand_out, nor_out, not_out, buf_out;
output OUT;
reg OUT;

AND_2   and_2   (IN1, IN2, and_out);
OR_3    or_3    (IN1, IN2, IN3, or_out);
NAND_2  nand_2  (IN1, IN2, nand_out);
NOR_2   nor_2   (IN1, IN2, nor_out);
NOT     not_0   (IN1, not_out);
BUF     buf_0   (IN1, buf_out);

always @(cs) begin
    case (cs)
        `def_AND_2:     OUT <= and_out;
        `def_OR_3:      OUT <= or_out;
        `def_NAND_2:    OUT <= nand_out;
        `def_NOR_2:     OUT <= nor_out;
        `def_NOT:       OUT <= not_out;
        `def_BUF:       OUT <= buf_out;
        `def_FIN:       OUT <= 1;
        default:        OUT <= 0;
    endcase
end

endmodule


module AND_2(IN1, IN2, OUT);
    input   IN1, IN2;
    output  OUT;
    assign  OUT = IN1 & IN2;
endmodule


module OR_3(IN1, IN2, IN3, OUT);
    input   IN1, IN2, IN3;
    output  OUT;
    assign  OUT = IN1 | IN2 | IN3;
endmodule


module NAND_2(IN1, IN2, OUT);
    input   IN1, IN2;
    output  OUT;
    assign  OUT = ~(IN1 & IN2);
endmodule


module NOR_2(IN1, IN2, OUT);
    input   IN1, IN2;
    output  OUT;
    assign  OUT = ~(IN1 | IN2);
endmodule


module NOT(IN, OUT);
    input   IN;
    output  OUT;
    assign  OUT = ~IN;
endmodule


module BUF(IN, OUT);
    input   IN;
    output  OUT;
    assign  OUT = IN;
endmodule

work/hoge_te.v
`timescale 1ns/1ns

module test;
reg clk, reset;
wire [7:0] count;
wire [2:0] cs;
parameter times = 4;

reg IN2, IN3;
wire OUT;

state   state   (clk, reset, count, cs);
cal     cal     (clk, IN2, IN3, cs, count, OUT);

initial begin
    clk = 1'b0;
    IN2 = 1'b0;
    IN3 = 1'b1;
end

always #(times/2)   clk = ~clk;
always #(times/4)   IN2 = ~IN2;
always #(times)     IN3 = ~IN3;

initial begin
    reset = 1;
    repeat(5) @(negedge clk);
    reset = 0;
end

initial begin
    @(negedge clk);
    while(reset) @(negedge clk);
    repeat(100) @(negedge clk);
    $finish;
end

initial begin
    $dumpfile("hoge.vcd");
    $dumpvars(0, test);
end

endmodule

work/hoge.vcd
$date
	Fri Jun 19 00:41:39 2015
$end
$version
	Icarus Verilog
$end
$timescale
	1ns
$end
$scope module test $end
$var wire 1 ! OUT $end
$var wire 8 " count [7:0] $end
$var wire 3 # cs [2:0] $end
$var reg 1 $ IN2 $end
$var reg 1 % IN3 $end
$var reg 1 & clk $end
$var reg 1 ' reset $end
$scope module state $end
$var wire 1 ( clk $end
$var wire 1 ) res $end
$var reg 8 * cot [7:0] $end
$var reg 3 + cs [2:0] $end
$upscope $end
$scope module cal $end
$var wire 1 ( IN1 $end
$var wire 1 , IN2 $end
$var wire 1 - IN3 $end
$var wire 1 . and_out $end
$var wire 1 / buf_out $end
$var wire 8 0 cot [7:0] $end
$var wire 3 1 cs [2:0] $end
$var wire 1 2 nand_out $end
$var wire 1 3 nor_out $end
$var wire 1 4 not_out $end
$var wire 1 5 or_out $end
$var reg 1 6 OUT $end
$scope module and_2 $end
$var wire 1 ( IN1 $end
$var wire 1 , IN2 $end
$var wire 1 . OUT $end
$upscope $end
$scope module or_3 $end
$var wire 1 ( IN1 $end
$var wire 1 , IN2 $end
$var wire 1 - IN3 $end
$var wire 1 5 OUT $end
$upscope $end
$scope module nand_2 $end
$var wire 1 ( IN1 $end
$var wire 1 , IN2 $end
$var wire 1 2 OUT $end
$upscope $end
$scope module nor_2 $end
$var wire 1 ( IN1 $end
$var wire 1 , IN2 $end
$var wire 1 3 OUT $end
$upscope $end
$scope module not_0 $end
$var wire 1 ( IN $end
$var wire 1 4 OUT $end
$upscope $end
$scope module buf_0 $end
$var wire 1 ( IN $end
$var wire 1 / OUT $end
$upscope $end
$upscope $end
$upscope $end
$enddefinitions $end
#0
$dumpvars
x6
15
14
13
12
bx 1
bx 0
0/
0.
1-
0,
bx +
bx *
1)
0(
1'
0&
1%
0$
bx #
bx "
x!
$end
#1
03
1$
1,
#2
16
1!
b0 *
b0 "
b0 0
b0 +
b0 #
b0 1
04
0$
0,
1&
1(
1/
#3
02
1.
1$
1,
#4
05
12
13
0.
14
0$
0,
0&
0(
0/
0%
0-
#5
15
03
1$
1,
#6
04
0$
0,
1&
1(
1/
#7
02
1.
1$
1,
#8
12
13
0.
14
0$
0,
0&
0(
0/
1%
1-
#9
03
1$
1,
#10
04
0$
0,
1&
1(
1/
#11
02
1.
1$
1,
#12
05
12
13
0.
14
0$
0,
0&
0(
0/
0%
0-
#13
15
03
1$
1,
#14
04
0$
0,
1&
1(
1/
#15
02
1.
1$
1,
#16
12
13
0.
14
0$
0,
0&
0(
0/
1%
1-
#17
03
1$
1,
#18
04
0$
0,
1&
1(
1/
#19
02
1.
1$
1,
#20
06
0!
b1 +
b1 #
b1 1
05
12
13
0'
0)
0.
14
0$
0,
0&
0(
0/
0%
0-
#21
15
03
1$
1,
#22
16
1!
b1 *
b1 "
b1 0
b10 +
b10 #
b10 1
04
0$
0,
1&
1(
1/
#23
02
1.
1$
1,
#24
12
13
0.
14
0$
0,
0&
0(
0/
1%
1-
#25
03
1$
1,
#26
b11 +
b11 #
b11 1
04
0$
0,
1&
1(
1/
#27
02
1.
1$
1,
#28
05
12
13
0.
14
0$
0,
0&
0(
0/
0%
0-
#29
15
03
1$
1,
#30
06
0!
b100 +
b100 #
b100 1
04
0$
0,
1&
1(
1/
#31
02
1.
1$
1,
#32
12
13
0.
14
0$
0,
0&
0(
0/
1%
1-
#33
03
1$
1,
#34
b101 +
b101 #
b101 1
04
0$
0,
1&
1(
1/
#35
02
1.
1$
1,
#36
05
12
13
0.
14
0$
0,
0&
0(
0/
0%
0-
#37
15
03
1$
1,
#38
b1 +
b1 #
b1 1
04
0$
0,
1&
1(
1/
#39
02
1.
1$
1,
#40
12
13
0.
14
0$
0,
0&
0(
0/
1%
1-
#41
03
1$
1,
#42
16
1!
b10 *
b10 "
b10 0
b10 +
b10 #
b10 1
04
0$
0,
1&
1(
1/
#43
02
1.
1$
1,
#44
05
12
13
0.
14
0$
0,
0&
0(
0/
0%
0-
#45
15
03
1$
1,
#46
b11 +
b11 #
b11 1
04
0$
0,
1&
1(
1/
#47
02
1.
1$
1,
#48
12
13
0.
14
0$
0,
0&
0(
0/
1%
1-
#49
03
1$
1,
#50
06
0!
b100 +
b100 #
b100 1
04
0$
0,
1&
1(
1/
#51
02
1.
1$
1,
#52
05
12
13
0.
14
0$
0,
0&
0(
0/
0%
0-
#53
15
03
1$
1,
#54
b101 +
b101 #
b101 1
04
0$
0,
1&
1(
1/
#55
02
1.
1$
1,
#56
12
13
0.
14
0$
0,
0&
0(
0/
1%
1-
#57
03
1$
1,
#58
b1 +
b1 #
b1 1
04
0$
0,
1&
1(
1/
#59
02
1.
1$
1,
#60
05
12
13
0.
14
0$
0,
0&
0(
0/
0%
0-
#61
15
03
1$
1,
#62
16
1!
b11 *
b11 "
b11 0
b10 +
b10 #
b10 1
04
0$
0,
1&
1(
1/
#63
02
1.
1$
1,
#64
12
13
0.
14
0$
0,
0&
0(
0/
1%
1-
#65
03
1$
1,
#66
b11 +
b11 #
b11 1
04
0$
0,
1&
1(
1/
#67
02
1.
1$
1,
#68
05
12
13
0.
14
0$
0,
0&
0(
0/
0%
0-
#69
15
03
1$
1,
#70
06
0!
b100 +
b100 #
b100 1
04
0$
0,
1&
1(
1/
#71
02
1.
1$
1,
#72
12
13
0.
14
0$
0,
0&
0(
0/
1%
1-
#73
03
1$
1,
#74
b101 +
b101 #
b101 1
04
0$
0,
1&
1(
1/
#75
02
1.
1$
1,
#76
05
12
13
0.
14
0$
0,
0&
0(
0/
0%
0-
#77
15
03
1$
1,
#78
b1 +
b1 #
b1 1
04
0$
0,
1&
1(
1/
#79
02
1.
1$
1,
#80
12
13
0.
14
0$
0,
0&
0(
0/
1%
1-
#81
03
1$
1,
#82
16
1!
b100 *
b100 "
b100 0
b10 +
b10 #
b10 1
04
0$
0,
1&
1(
1/
#83
02
1.
1$
1,
#84
05
12
13
0.
14
0$
0,
0&
0(
0/
0%
0-
#85
15
03
1$
1,
#86
b11 +
b11 #
b11 1
04
0$
0,
1&
1(
1/
#87
02
1.
1$
1,
#88
12
13
0.
14
0$
0,
0&
0(
0/
1%
1-
#89
03
1$
1,
#90
06
0!
b100 +
b100 #
b100 1
04
0$
0,
1&
1(
1/
#91
02
1.
1$
1,
#92
05
12
13
0.
14
0$
0,
0&
0(
0/
0%
0-
#93
15
03
1$
1,
#94
b101 +
b101 #
b101 1
04
0$
0,
1&
1(
1/
#95
02
1.
1$
1,
#96
12
13
0.
14
0$
0,
0&
0(
0/
1%
1-
#97
03
1$
1,
#98
b1 +
b1 #
b1 1
04
0$
0,
1&
1(
1/
#99
02
1.
1$
1,
#100
05
12
13
0.
14
0$
0,
0&
0(
0/
0%
0-
#101
15
03
1$
1,
#102
16
1!
b101 *
b101 "
b101 0
b10 +
b10 #
b10 1
04
0$
0,
1&
1(
1/
#103
02
1.
1$
1,
#104
12
13
0.
14
0$
0,
0&
0(
0/
1%
1-
#105
03
1$
1,
#106
b11 +
b11 #
b11 1
04
0$
0,
1&
1(
1/
#107
02
1.
1$
1,
#108
05
12
13
0.
14
0$
0,
0&
0(
0/
0%
0-
#109
15
03
1$
1,
#110
06
0!
b100 +
b100 #
b100 1
04
0$
0,
1&
1(
1/
#111
02
1.
1$
1,
#112
12
13
0.
14
0$
0,
0&
0(
0/
1%
1-
#113
03
1$
1,
#114
b101 +
b101 #
b101 1
04
0$
0,
1&
1(
1/
#115
02
1.
1$
1,
#116
05
12
13
0.
14
0$
0,
0&
0(
0/
0%
0-
#117
15
03
1$
1,
#118
b1 +
b1 #
b1 1
04
0$
0,
1&
1(
1/
#119
02
1.
1$
1,
#120
12
13
0.
14
0$
0,
0&
0(
0/
1%
1-
#121
03
1$
1,
#122
16
1!
b110 *
b110 "
b110 0
b10 +
b10 #
b10 1
04
0$
0,
1&
1(
1/
#123
02
1.
1$
1,
#124
05
12
13
0.
14
0$
0,
0&
0(
0/
0%
0-
#125
15
03
1$
1,
#126
b11 +
b11 #
b11 1
04
0$
0,
1&
1(
1/
#127
02
1.
1$
1,
#128
12
13
0.
14
0$
0,
0&
0(
0/
1%
1-
#129
03
1$
1,
#130
06
0!
b100 +
b100 #
b100 1
04
0$
0,
1&
1(
1/
#131
02
1.
1$
1,
#132
05
12
13
0.
14
0$
0,
0&
0(
0/
0%
0-
#133
15
03
1$
1,
#134
b101 +
b101 #
b101 1
04
0$
0,
1&
1(
1/
#135
02
1.
1$
1,
#136
12
13
0.
14
0$
0,
0&
0(
0/
1%
1-
#137
03
1$
1,
#138
b1 +
b1 #
b1 1
04
0$
0,
1&
1(
1/
#139
02
1.
1$
1,
#140
05
12
13
0.
14
0$
0,
0&
0(
0/
0%
0-
#141
15
03
1$
1,
#142
16
1!
b111 *
b111 "
b111 0
b10 +
b10 #
b10 1
04
0$
0,
1&
1(
1/
#143
02
1.
1$
1,
#144
12
13
0.
14
0$
0,
0&
0(
0/
1%
1-
#145
03
1$
1,
#146
b11 +
b11 #
b11 1
04
0$
0,
1&
1(
1/
#147
02
1.
1$
1,
#148
05
12
13
0.
14
0$
0,
0&
0(
0/
0%
0-
#149
15
03
1$
1,
#150
06
0!
b100 +
b100 #
b100 1
04
0$
0,
1&
1(
1/
#151
02
1.
1$
1,
#152
12
13
0.
14
0$
0,
0&
0(
0/
1%
1-
#153
03
1$
1,
#154
b101 +
b101 #
b101 1
04
0$
0,
1&
1(
1/
#155
02
1.
1$
1,
#156
05
12
13
0.
14
0$
0,
0&
0(
0/
0%
0-
#157
15
03
1$
1,
#158
b1 +
b1 #
b1 1
04
0$
0,
1&
1(
1/
#159
02
1.
1$
1,
#160
12
13
0.
14
0$
0,
0&
0(
0/
1%
1-
#161
03
1$
1,
#162
16
1!
b1000 *
b1000 "
b1000 0
b10 +
b10 #
b10 1
04
0$
0,
1&
1(
1/
#163
02
1.
1$
1,
#164
05
12
13
0.
14
0$
0,
0&
0(
0/
0%
0-
#165
15
03
1$
1,
#166
b11 +
b11 #
b11 1
04
0$
0,
1&
1(
1/
#167
02
1.
1$
1,
#168
12
13
0.
14
0$
0,
0&
0(
0/
1%
1-
#169
03
1$
1,
#170
06
0!
b100 +
b100 #
b100 1
04
0$
0,
1&
1(
1/
#171
02
1.
1$
1,
#172
05
12
13
0.
14
0$
0,
0&
0(
0/
0%
0-
#173
15
03
1$
1,
#174
b101 +
b101 #
b101 1
04
0$
0,
1&
1(
1/
#175
02
1.
1$
1,
#176
12
13
0.
14
0$
0,
0&
0(
0/
1%
1-
#177
03
1$
1,
#178
b1 +
b1 #
b1 1
04
0$
0,
1&
1(
1/
#179
02
1.
1$
1,
#180
05
12
13
0.
14
0$
0,
0&
0(
0/
0%
0-
#181
15
03
1$
1,
#182
16
1!
b1001 *
b1001 "
b1001 0
b10 +
b10 #
b10 1
04
0$
0,
1&
1(
1/
#183
02
1.
1$
1,
#184
12
13
0.
14
0$
0,
0&
0(
0/
1%
1-
#185
03
1$
1,
#186
b11 +
b11 #
b11 1
04
0$
0,
1&
1(
1/
#187
02
1.
1$
1,
#188
05
12
13
0.
14
0$
0,
0&
0(
0/
0%
0-
#189
15
03
1$
1,
#190
06
0!
b100 +
b100 #
b100 1
04
0$
0,
1&
1(
1/
#191
02
1.
1$
1,
#192
12
13
0.
14
0$
0,
0&
0(
0/
1%
1-
#193
03
1$
1,
#194
b1 +
b1 #
b1 1
04
0$
0,
1&
1(
1/
#195
02
1.
1$
1,
#196
05
12
13
0.
14
0$
0,
0&
0(
0/
0%
0-
#197
15
03
1$
1,
#198
16
1!
b1010 *
b1010 "
b1010 0
b10 +
b10 #
b10 1
04
0$
0,
1&
1(
1/
#199
02
1.
1$
1,
#200
12
13
0.
14
0$
0,
0&
0(
0/
1%
1-
#201
03
1$
1,
#202
b11 +
b11 #
b11 1
04
0$
0,
1&
1(
1/
#203
02
1.
1$
1,
#204
05
12
13
0.
14
0$
0,
0&
0(
0/
0%
0-
#205
15
03
1$
1,
#206
06
0!
b100 +
b100 #
b100 1
04
0$
0,
1&
1(
1/
#207
02
1.
1$
1,
#208
12
13
0.
14
0$
0,
0&
0(
0/
1%
1-
#209
03
1$
1,
#210
b1 +
b1 #
b1 1
04
0$
0,
1&
1(
1/
#211
02
1.
1$
1,
#212
05
12
13
0.
14
0$
0,
0&
0(
0/
0%
0-
#213
15
03
1$
1,
#214
16
1!
b111 +
b111 #
b111 1
04
0$
0,
1&
1(
1/
#215
02
1.
1$
1,
#216
12
13
0.
14
0$
0,
0&
0(
0/
1%
1-
#217
03
1$
1,
#218
04
0$
0,
1&
1(
1/
#219
02
1.
1$
1,
#220
05
12
13
0.
14
0$
0,
0&
0(
0/
0%
0-
#221
15
03
1$
1,
#222
04
0$
0,
1&
1(
1/
#223
02
1.
1$
1,
#224
12
13
0.
14
0$
0,
0&
0(
0/
1%
1-
#225
03
1$
1,
#226
04
0$
0,
1&
1(
1/
#227
02
1.
1$
1,
#228
05
12
13
0.
14
0$
0,
0&
0(
0/
0%
0-
#229
15
03
1$
1,
#230
04
0$
0,
1&
1(
1/
#231
02
1.
1$
1,
#232
12
13
0.
14
0$
0,
0&
0(
0/
1%
1-
#233
03
1$
1,
#234
04
0$
0,
1&
1(
1/
#235
02
1.
1$
1,
#236
05
12
13
0.
14
0$
0,
0&
0(
0/
0%
0-
#237
15
03
1$
1,
#238
04
0$
0,
1&
1(
1/
#239
02
1.
1$
1,
#240
12
13
0.
14
0$
0,
0&
0(
0/
1%
1-
#241
03
1$
1,
#242
04
0$
0,
1&
1(
1/
#243
02
1.
1$
1,
#244
05
12
13
0.
14
0$
0,
0&
0(
0/
0%
0-
#245
15
03
1$
1,
#246
04
0$
0,
1&
1(
1/
#247
02
1.
1$
1,
#248
12
13
0.
14
0$
0,
0&
0(
0/
1%
1-
#249
03
1$
1,
#250
04
0$
0,
1&
1(
1/
#251
02
1.
1$
1,
#252
05
12
13
0.
14
0$
0,
0&
0(
0/
0%
0-
#253
15
03
1$
1,
#254
04
0$
0,
1&
1(
1/
#255
02
1.
1$
1,
#256
12
13
0.
14
0$
0,
0&
0(
0/
1%
1-
#257
03
1$
1,
#258
04
0$
0,
1&
1(
1/
#259
02
1.
1$
1,
#260
05
12
13
0.
14
0$
0,
0&
0(
0/
0%
0-
#261
15
03
1$
1,
#262
04
0$
0,
1&
1(
1/
#263
02
1.
1$
1,
#264
12
13
0.
14
0$
0,
0&
0(
0/
1%
1-
#265
03
1$
1,
#266
04
0$
0,
1&
1(
1/
#267
02
1.
1$
1,
#268
05
12
13
0.
14
0$
0,
0&
0(
0/
0%
0-
#269
15
03
1$
1,
#270
04
0$
0,
1&
1(
1/
#271
02
1.
1$
1,
#272
12
13
0.
14
0$
0,
0&
0(
0/
1%
1-
#273
03
1$
1,
#274
04
0$
0,
1&
1(
1/
#275
02
1.
1$
1,
#276
05
12
13
0.
14
0$
0,
0&
0(
0/
0%
0-
#277
15
03
1$
1,
#278
04
0$
0,
1&
1(
1/
#279
02
1.
1$
1,
#280
12
13
0.
14
0$
0,
0&
0(
0/
1%
1-
#281
03
1$
1,
#282
04
0$
0,
1&
1(
1/
#283
02
1.
1$
1,
#284
05
12
13
0.
14
0$
0,
0&
0(
0/
0%
0-
#285
15
03
1$
1,
#286
04
0$
0,
1&
1(
1/
#287
02
1.
1$
1,
#288
12
13
0.
14
0$
0,
0&
0(
0/
1%
1-
#289
03
1$
1,
#290
04
0$
0,
1&
1(
1/
#291
02
1.
1$
1,
#292
05
12
13
0.
14
0$
0,
0&
0(
0/
0%
0-
#293
15
03
1$
1,
#294
04
0$
0,
1&
1(
1/
#295
02
1.
1$
1,
#296
12
13
0.
14
0$
0,
0&
0(
0/
1%
1-
#297
03
1$
1,
#298
04
0$
0,
1&
1(
1/
#299
02
1.
1$
1,
#300
05
12
13
0.
14
0$
0,
0&
0(
0/
0%
0-
#301
15
03
1$
1,
#302
04
0$
0,
1&
1(
1/
#303
02
1.
1$
1,
#304
12
13
0.
14
0$
0,
0&
0(
0/
1%
1-
#305
03
1$
1,
#306
04
0$
0,
1&
1(
1/
#307
02
1.
1$
1,
#308
05
12
13
0.
14
0$
0,
0&
0(
0/
0%
0-
#309
15
03
1$
1,
#310
04
0$
0,
1&
1(
1/
#311
02
1.
1$
1,
#312
12
13
0.
14
0$
0,
0&
0(
0/
1%
1-
#313
03
1$
1,
#314
04
0$
0,
1&
1(
1/
#315
02
1.
1$
1,
#316
05
12
13
0.
14
0$
0,
0&
0(
0/
0%
0-
#317
15
03
1$
1,
#318
04
0$
0,
1&
1(
1/
#319
02
1.
1$
1,
#320
12
13
0.
14
0$
0,
0&
0(
0/
1%
1-
#321
03
1$
1,
#322
04
0$
0,
1&
1(
1/
#323
02
1.
1$
1,
#324
05
12
13
0.
14
0$
0,
0&
0(
0/
0%
0-
#325
15
03
1$
1,
#326
04
0$
0,
1&
1(
1/
#327
02
1.
1$
1,
#328
12
13
0.
14
0$
0,
0&
0(
0/
1%
1-
#329
03
1$
1,
#330
04
0$
0,
1&
1(
1/
#331
02
1.
1$
1,
#332
05
12
13
0.
14
0$
0,
0&
0(
0/
0%
0-
#333
15
03
1$
1,
#334
04
0$
0,
1&
1(
1/
#335
02
1.
1$
1,
#336
12
13
0.
14
0$
0,
0&
0(
0/
1%
1-
#337
03
1$
1,
#338
04
0$
0,
1&
1(
1/
#339
02
1.
1$
1,
#340
05
12
13
0.
14
0$
0,
0&
0(
0/
0%
0-
#341
15
03
1$
1,
#342
04
0$
0,
1&
1(
1/
#343
02
1.
1$
1,
#344
12
13
0.
14
0$
0,
0&
0(
0/
1%
1-
#345
03
1$
1,
#346
04
0$
0,
1&
1(
1/
#347
02
1.
1$
1,
#348
05
12
13
0.
14
0$
0,
0&
0(
0/
0%
0-
#349
15
03
1$
1,
#350
04
0$
0,
1&
1(
1/
#351
02
1.
1$
1,
#352
12
13
0.
14
0$
0,
0&
0(
0/
1%
1-
#353
03
1$
1,
#354
04
0$
0,
1&
1(
1/
#355
02
1.
1$
1,
#356
05
12
13
0.
14
0$
0,
0&
0(
0/
0%
0-
#357
15
03
1$
1,
#358
04
0$
0,
1&
1(
1/
#359
02
1.
1$
1,
#360
12
13
0.
14
0$
0,
0&
0(
0/
1%
1-
#361
03
1$
1,
#362
04
0$
0,
1&
1(
1/
#363
02
1.
1$
1,
#364
05
12
13
0.
14
0$
0,
0&
0(
0/
0%
0-
#365
15
03
1$
1,
#366
04
0$
0,
1&
1(
1/
#367
02
1.
1$
1,
#368
12
13
0.
14
0$
0,
0&
0(
0/
1%
1-
#369
03
1$
1,
#370
04
0$
0,
1&
1(
1/
#371
02
1.
1$
1,
#372
05
12
13
0.
14
0$
0,
0&
0(
0/
0%
0-
#373
15
03
1$
1,
#374
04
0$
0,
1&
1(
1/
#375
02
1.
1$
1,
#376
12
13
0.
14
0$
0,
0&
0(
0/
1%
1-
#377
03
1$
1,
#378
04
0$
0,
1&
1(
1/
#379
02
1.
1$
1,
#380
05
12
13
0.
14
0$
0,
0&
0(
0/
0%
0-
#381
15
03
1$
1,
#382
04
0$
0,
1&
1(
1/
#383
02
1.
1$
1,
#384
12
13
0.
14
0$
0,
0&
0(
0/
1%
1-
#385
03
1$
1,
#386
04
0$
0,
1&
1(
1/
#387
02
1.
1$
1,
#388
05
12
13
0.
14
0$
0,
0&
0(
0/
0%
0-
#389
15
03
1$
1,
#390
04
0$
0,
1&
1(
1/
#391
02
1.
1$
1,
#392
12
13
0.
14
0$
0,
0&
0(
0/
1%
1-
#393
03
1$
1,
#394
04
0$
0,
1&
1(
1/
#395
02
1.
1$
1,
#396
05
12
13
0.
14
0$
0,
0&
0(
0/
0%
0-
#397
15
03
1$
1,
#398
04
0$
0,
1&
1(
1/
#399
02
1.
1$
1,
#400
12
13
0.
14
0$
0,
0&
0(
0/
1%
1-
#401
03
1$
1,
#402
04
0$
0,
1&
1(
1/
#403
02
1.
1$
1,
#404
05
12
13
0.
14
0$
0,
0&
0(
0/
0%
0-
#405
15
03
1$
1,
#406
04
0$
0,
1&
1(
1/
#407
02
1.
1$
1,
#408
12
13
0.
14
0$
0,
0&
0(
0/
1%
1-
#409
03
1$
1,
#410
04
0$
0,
1&
1(
1/
#411
02
1.
1$
1,
#412
05
12
13
0.
14
0$
0,
0&
0(
0/
0%
0-
#413
15
03
1$
1,
#414
04
0$
0,
1&
1(
1/
#415
02
1.
1$
1,
#416
12
13
0.
14
0$
0,
0&
0(
0/
1%
1-
#417
03
1$
1,
#418
04
0$
0,
1&
1(
1/
#419
02
1.
1$
1,
#420
05
12
13
0.
14
0$
0,
0&
0(
0/
0%
0-
#421
15
03
1$
1,
#422
04
0$
0,
1&
1(
1/
#423
02
1.
1$
1,
#424
12
13
0.
14
0$
0,
0&
0(
0/
1%
1-
