work/rcon.v
module rcon (in, out);
input [7:0] in;
output [7:0] out;

assign out = (in > 8'h08)? (8'h1b << (in - 8'h09)) : (8'h01 << (in - 1));

endmodule

work/rcon_te.v
`timescale 1ns/1ns

module test;
    reg [7:0] word;
    wire [7:0] s0;

    rcon rcon (word, s0);
    initial begin
                word = 8'h00;
        #100    word = 8'h01;
        #100    word = 8'h02;
        #100    word = 8'h03;
        #100    word = 8'h04;
        #100    word = 8'h05;
        #100    word = 8'h06;
        #100    word = 8'h07;
        #100    word = 8'h08;
        #100    word = 8'h09;
        #100    word = 8'h0a;
        #100    $finish;
    end

    initial begin
        #0      $display($time, "word=%h, s0=%h", word, s0);
        #100    $display($time, "word=%h, s0=%h", word, s0);
        #100    $display($time, "word=%h, s0=%h", word, s0);
        #100    $display($time, "word=%h, s0=%h", word, s0);
        #100    $display($time, "word=%h, s0=%h", word, s0);
        #100    $display($time, "word=%h, s0=%h", word, s0);
        #100    $display($time, "word=%h, s0=%h", word, s0);
        #100    $display($time, "word=%h, s0=%h", word, s0);
        #100    $display($time, "word=%h, s0=%h", word, s0);
        #100    $display($time, "word=%h, s0=%h", word, s0);
        #100    $display($time, "word=%h, s0=%h", word, s0);
        #100    $display($time, "word=%h, s0=%h", word, s0);
        #100    $display($time, "word=%h, s0=%h", word, s0);
        #100    $display($time, "word=%h, s0=%h", word, s0);
    end

    initial begin
        $dumpfile("rcon.vcd");
        $dumpvars(0, test);
    end

endmodule

work/rcon.vcd
$date
	Sun Jun 14 23:11:51 2015
$end
$version
	Icarus Verilog
$end
$timescale
	1ns
$end
$scope module test $end
$var wire 8 ! s0 [7:0] $end
$var reg 8 " word [7:0] $end
$scope module rcon $end
$var wire 8 # in [7:0] $end
$var wire 8 $ out [7:0] $end
$upscope $end
$upscope $end
$enddefinitions $end
#0
$dumpvars
b0 $
b0 #
b0 "
b0 !
$end
#100
b1 !
b1 $
b1 "
b1 #
#200
b10 !
b10 $
b10 "
b10 #
#300
b100 !
b100 $
b11 "
b11 #
#400
b1000 !
b1000 $
b100 "
b100 #
#500
b10000 !
b10000 $
b101 "
b101 #
#600
b100000 !
b100000 $
b110 "
b110 #
#700
b1000000 !
b1000000 $
b111 "
b111 #
#800
b10000000 !
b10000000 $
b1000 "
b1000 #
#900
b11011 !
b11011 $
b1001 "
b1001 #
#1000
b110110 !
b110110 $
b1010 "
b1010 #
